Workbook

Sheet Анализ по мес
B3: Апрель
B4: Бренд | C4: Количество | D4: Ср маржа | E4: Маржа всего | F4: ДО всего | G4: К получению
B5: KIA | C5: 463 | D5: 605417.44 | E5: 280308275 | F5: 84053500 | G5: 364361775
B6: Chevrolet | C6: 858 | D6: 264234.29 | E6: 2.2671283e+08 | F6: 950000 | G6: 2.2766283e+08
B7: JAC | C7: 190 | D7: 578658.6 | E7: 109945150 | F7: 2550000 | G7: 112495150
B8: JETOUR | C8: 436 | D8: 659702.06 | E8: 287630100 | F8: 3992200 | G8: 291622300
B9: Тотал | C9: 1947 | D9: 464610.44 | E9: 9.0459635e+08 | F9: 91545700 | G9: 9.9614205e+08
B11: Май
B12: Бренд | C12: Количество | D12: Ср маржа | E12: Маржа всего | F12: ДО всего | G12: К получению
B13: KIA | C13: 409 | D13: 534787.24 | E13: 2.1611918e+08 | F13: 61325470 | G13: 2.7744465e+08
B14: Chevrolet | C14: 768 | D14: 261982.81 | E14: 201202800 | F14: 600000 | G14: 201802800
B15: JAC | C15: 236 | D15: 470619.49 | E15: 111066200 | F15: 4950000 | G15: 116016200
B16: JETOUR | C16: 423 | D16: 686793.41 | E16: 256322400 | F16: 2283500 | G16: 258605900
B17: Тотал | C17: 1836 | D17: 447445.86 | E17: 7.8471058e+08 | F17: 69158970 | G17: 8.5386955e+08
B19: Июнь
B20: Бренд | C20: Количество | D20: Ср маржа | E20: Маржа всего | F20: ДО всего | G20: К получению
B21: KIA | C21: 507 | D21: 448667.95 | E21: 223258750 | F21: 52605000 | G21: 275863750
B22: Chevrolet | C22: 788 | D22: 271441.62 | E22: 213896000 | F22: 9500500 | G22: 223396500
B23: JAC | C23: 244 | D23: 446697.13 | E23: 108994100 | F23: 7050000 | G23: 116044100
B24: JETOUR | C24: 467 | D24: 629376.87 | E24: 293919000 | F24: 3162500 | G24: 297081500
B25: Тотал | C25: 2006 | D25: 420879.24 | E25: 840067850 | F25: 72318000 | G25: 912385850
B27: Июль
B28: Бренд | C28: Количество | D28: Ср маржа | E28: Маржа всего | F28: ДО всего | G28: К получению
B29: KIA | C29: 472 | D29: 473325.42 | E29: 214309700 | F29: 56939300 | G29: 271249000
B30: Chevrolet | C30: 1189 | D30: 239705.63 | E30: 285010000 | F30: 135916500 | G30: 420926500
B31: JAC | C31: 326 | D31: 323326.53 | E31: 105404450 | F31: 7990000 | G31: 113394450
B32: JETOUR | C32: 404 | D32: 656017.33 | E32: 265031000 | F32: 1210500 | G32: 266241500
B33: Тотал | C33: 2391 | D33: 367567.98 | E33: 869755150 | F33: 202056300 | G33: 1071811450
B35: Август
B36: Бренд | C36: Количество | D36: Ср маржа | E36: Маржа всего | F36: ДО всего | G36: К получению
B37: KIA | C37: 457 | D37: 570560.63 | E37: 257149810 | F37: 66976600 | G37: 324126410
B38: Chevrolet | C38: 809 | D38: 227305.32 | E38: 183890000 | F38: 84787400 | G38: 268677400
B39: JAC | C39: 247 | D39: 304207.69 | E39: 75139300 | F39: 2744400 | G39: 77883700
B40: JETOUR | C40: 259 | D40: 685496.53 | E40: 177543600 | F40: 2248100 | G40: 179791700
B41: Тотал | C41: 1772 | D41: 393520.94 | E41: 693722710 | F41: 156756500 | G41: 850479210
B43: Сентябрь
B44: Бренд | C44: Количество | D44: Ср маржа | E44: Маржа всего | F44: ДО всего | G44: К получению
B45: KIA | C45: 407 | D45: 702001.91 | E45: 285714779 | F45: 62820010 | G45: 348534789
B46: Chevrolet | C46: 948 | D46: 250200.42 | E46: 237190000 | F46: 117355900 | G46: 354545900
B47: JAC | C47: 197 | D47: 346040.36 | E47: 68169950 | F47: 2427700 | G47: 70597650
B48: JETOUR | C48: 283 | D48: 613947.35 | E48: 173747100 | F48: 18096650 | G48: 191843750
B49: Тотал | C49: 1835 | D49: 416796.64 | E49: 764821829 | F49: 200700260 | G49: 965522089
B51: Октябрь
B52: Бренд | C52: Количество | D52: Ср маржа | E52: Маржа всего | F52: ДО всего | G52: К получению
B53: KIA | C53: 438 | D53: 665489.93 | E53: 2.9148459e+08 | F53: 67053750 | G53: 3.5853834e+08
B54: Chevrolet | C54: 935 | D54: 259083.42 | E54: 242243000 | F54: 120108500 | G54: 362351500
B55: JAC | C55: 235 | D55: 390028.09 | E55: 91656600 | F55: 11832000 | G55: 103488600
B56: JETOUR | C56: 360 | D56: 572039.03 | E56: 205934050 | F56: 33233550 | G56: 239167600
B57: Skoda | C57: 15 | D57: 522055.33 | E57: 7830830 | F57: 0 | G57: 7830830
B58: Тотал | C58: 1983 | D58: 423171.49 | E58: 8.3914907e+08 | F58: 232227800 | G58: 1.0713769e+09
B60: Ноябрь
B61: Бренд | C61: Количество | D61: Ср маржа | E61: Маржа всего | F61: ДО всего | G61: К получению | H61: % маржы
B62: KIA | C62: 600 | D62: 668431.78 | E62: 401059068 | F62: 92840800 | G62: 493899868 | H62: 0.036446993
B63: Chevrolet | C63: 2723 | D63: 253158.28 | E63: 689350000 | F63: 276149250 | G63: 965499250 | H63: 0.039018148
B64: JAC | C64: 162 | D64: 452530.86 | E64: 73310000 | F64: 15242435 | G64: 88552435 | H64: 0.048573106
B65: JETOUR | C65: 395 | D65: 577598.48 | E65: 228151400 | F65: 39751900 | G65: 267903300 | H65: 0.048869051
B66: Skoda | C66: 6 | D66: 493003.33 | E66: 2958020 | F66: 0 | G66: 2958020 | H66: 0.021632441
B67: Тотал | C67: 3886 | D67: 358936.82 | E67: 1394828488 | F67: 423984385 | G67: 1818812873 | H67: *
B69: Декабрь
B70: Бренд | C70: Количество | D70: Ср маржа | E70: Маржа всего | F70: ДО всего | G70: К получению | H70: % маржы
B71: KIA | C71: 277 | D71: 608634.22 | E71: 168591680 | F71: 37865400 | G71: 206457080 | H71: 0.033041449
B72: Chevrolet | C72: 1745 | D72: 249690.83 | E72: 435710500 | F72: 191120350 | G72: 626830850 | H72: 0.036935011
B73: JAC | C73: 420 | D73: 408313.33 | E73: 171491600 | F73: 56542500 | G73: 228034100 | H73: 0.052974273
B74: JETOUR | C74: 397 | D74: 606943.83 | E74: 240956700 | F74: 31131200 | G74: 272087900 | H74: 0.05214114
B75: Skoda | C75: 9 | D75: 593621.11 | E75: 5342590 | F75: 0 | G75: 5342590 | H75: 0.024894413
B76: Тотал | C76: 2848 | D76: 358880.99 | E76: 1022093070 | F76: 316659450 | G76: 1338752520 | H76: *
B78: 46023
B79: Бренд | C79: Количество | D79: Ср маржа | E79: Маржа всего | F79: ДО всего | G79: К получению | H79: % маржы
B80: KIA | C80: 584 | D80: 412220.5 | E80: 240736770 | F80: 51441000 | G80: 292177770 | H80: 0.022500951
B81: Chevrolet | C81: 845 | D81: 291062.13 | E81: 245947500 | F81: 96240150 | G81: 342187650 | H81: 0.041380363
B82: JAC | C82: 172 | D82: 386587.21 | E82: 66493000 | F82: 30155000 | G82: 96648000 | H82: 0.052054571
B83: JETOUR | C83: 206 | D83: 455383.01 | E83: 93808900 | F83: 24697150 | G83: 118506050 | H83: 0.043931212
B84: Skoda | C84: 2 | D84: 625000 | E84: 1250000 | F84: 0 | G84: 1250000 | H84: 0.02874885
B85: Тотал | C85: 1809 | D85: 358339.51 | E85: 648236170 | F85: 202533300 | G85: 850769470 | H85: *
B87: 46054
B88: Бренд | C88: Количество | D88: Ср маржа | E88: Маржа всего | F88: ДО всего | G88: К получению | H88: % маржы
B89: KIA | C89: 610 | D89: 511116.89 | E89: 311781300 | F89: 92679000 | G89: 404460300 | H89: 0.033844325
B90: Chevrolet | C90: 646 | D90: 303152.01 | E90: 195836200 | F90: 99248800 | G90: 295085000 | H90: 0.043756901
B91: JAC | C91: 104 | D91: 398653.85 | E91: 41460000 | F91: 14896300 | G91: 56356300 | H91: 0.050877221
B92: JETOUR | C92: 179 | D92: 583324.02 | E92: 104415000 | F92: 14256000 | G92: 118671000 | H92: 0.050316845
B93: Skoda | C93: 6 | D93: 723330 | E93: 4339980 | F93: 0 | G93: 4339980 | H93: 0.031546605
B94: Тотал | C94: 1545 | D94: 425781.54 | E94: 657832480 | F94: 221080100 | G94: 878912580 | H94: *
B97: 46082
B98: Бренд | C98: Количество | D98: Ср маржа | E98: Маржа всего | F98: ДО всего | G98: К получению | H98: % маржы
B99: KIA | C99: 508 | D99: 656344.86 | E99: 333423191 | F99: 94872200 | G99: 428295391 | H99: 0.046120453
B100: Chevrolet | C100: 665 | D100: 312241.8 | E100: 207640800 | F100: 90062750 | G100: 297703550 | H100: 0.044032929
B101: JAC | C101: 127 | D101: 348494.49 | E101: 44258800 | F101: 19761700 | G101: 64020500 | H101: 0.038873635
B102: JETOUR | C102: 193 | D102: 561797.93 | E102: 108427000 | F102: 14619200 | G102: 123046200 | H102: 0.047483019
B103: Skoda | C103: 12 | D103: 657715.83 | E103: 7892590 | F103: 250000 | G103: 8142590 | H103: 0.029989323
B104: Тотал | C104: 1505 | D104: 466207.56 | E104: 701642381 | F104: 219565850 | G104: 921208231 | H104: *
B107: 46113
B108: Бренд | C108: Количество | D108: Ср маржа | E108: Маржа всего | F108: ДО всего | G108: К получению | H108: % маржы
B109: KIA | C109: =GETPIVOTDATA("Кол",'Анализ Киа'!$A$3) -> 408 | D109: ='Анализ Киа'!H12 -> 632360.63 | E109: =GETPIVOTDATA("Маржа после скидокк",'Анализ Киа'!$A$3) -> 258003139 | F109: =GETPIVOTDATA("Доп",'Анализ Киа'!$A$3) -> 66880100 | G109: =E109+F109 -> 324883239 | H109: ='Анализ Киа'!I12 -> 0.044939828
B110: Chevrolet | C110: =GETPIVOTDATA("Кол",'Анализ Шеви'!$A$3) -> 1787 | D110: =GETPIVOTDATA("Ср Маржа",'Анализ Шеви'!$A$21) -> 230626.75 | E110: =GETPIVOTDATA("Маржа",'Анализ Шеви'!$A$3) -> 412130000 | F110: =GETPIVOTDATA("ДОП",'Анализ Шеви'!$A$3) -> 94248350 | G110: =E110+F110 -> 506378350 | H110: ='Анализ Шеви'!G16 -> 0.035805509
B111: JAC | C111: =GETPIVOTDATA("Кол",'Анализ Джак'!$A$3) -> 88 | D111: ='Анализ Джак'!F15 -> 402827.27 | E111: =GETPIVOTDATA("Маржа",'Анализ Джак'!$A$3) -> 35448800 | F111: =GETPIVOTDATA("Доп",'Анализ Джак'!$A$3) -> 9576520 | G111: =E111+F111 -> 45025320 | H111: ='Анализ Джак'!G15 -> 0.043664762
B112: JETOUR | C112: =GETPIVOTDATA("Кол",'Анализ Джетур'!$A$3) -> 343 | D112: ='Анализ Джетур'!F15 -> 496012.83 | E112: =GETPIVOTDATA("Маржа",'Анализ Джетур'!$A$3) -> 170132400 | F112: =GETPIVOTDATA("Доп",'Анализ Джетур'!$A$3) -> 20055000 | G112: =E112+F112 -> 190187400 | H112: ='Анализ Джетур'!G15 -> 0.04732565
B113: Skoda | C113: =GETPIVOTDATA("Сумма по полю Кол-во",'Анализ Шкода'!$A$3) -> 3 | D113: =GETPIVOTDATA("Среднее по полю Вознаграждение без скидки",'Анализ Шкода'!$A$10) -> 538476.67 | E113: =GETPIVOTDATA("Сумма по полю Вознаграждение без скидки",'Анализ Шкода'!$A$3) -> 1615430 | F113: 0 | G113: =E113+F113 -> 1615430 | H113: ='Анализ Шкода'!F6 -> 0.021809505
B114: Soueast | C114: 2 | D114: =Лист9!E4 -> 559650 | E114: =GETPIVOTDATA("Сумма по полю Вознаграждение без скидки",Лист9!$A$3) -> 1119300 | F114: 0 | G114: =E114+F114 -> 1119300 | H114: =Лист9!F4 -> 0.035209407
B115: Тотал | C115: =SUM(C109:C113) -> 2629 | D115: =(C109*D109+C110*D110+C111*D111+C112*D112+C113*D113+C114*D114)/C115 -> 334138.1 | E115: =SUM(E109:E113) -> 877329769 | F115: =SUM(F109:F113) -> 190759970 | G115: =SUM(G109:G113) -> 1068089739 | H115: *

Sheet Анализ Киа
A3: Названия строк | B3: Кол | C3: РРЦ | D3: Маржа тотал | E3: Скидка | F3: Маржа после скидокк | G3: Доп | H3: Средний маржа | I3: %
A4: 1069 Актау TOO «DCG Aktau» (KIA) | B4: 18 | C4: 14054433 | D4: 12585739 | E4: 359800 | F4: 12225939 | G4: 2942000 | H4: =F4/B4 -> 679218.83 | I4: =H4/C4 -> 0.048327728
A5: 1151 Алматы ТОО «DCG Qulja» (KIA) | B5: 57 | C5: 14670702 | D5: 41978400 | E5: 6980000 | F5: 34998400 | G5: 8300000 | H5: =F5/B5 -> 614007.02 | I5: =H5/C5 -> 0.0418526
A6: 331 Шымкент ТОО «DCG ONTUSTIK» (KIA) | B6: 125 | C6: 14035600 | D6: 85360200 | E6: 216000 | F6: 85144200 | G6: 29148100 | H6: =F6/B6 -> 681153.6 | I6: =H6/C6 -> 0.048530423
A7: 363 Алматы ТОО «DCG ALMATY» (KIA) | B7: 59 | C7: 13784915 | D7: 35633650 | E7: 2018400 | F7: 33615250 | G7: 6050000 | H7: =F7/B7 -> 569750 | I7: =H7/C7 -> 0.041331411
A8: 365 Тараз ТОО «DCGTARAZ» (KIA) | B8: 23 | C8: 13916087 | D8: 14232300 | E8: 600000 | F8: 13632300 | G8: 7650000 | H8: =F8/B8 -> 592708.7 | I8: =H8/C8 -> 0.042591621
A9: 371 Астана ТОО «DCG ASTANA» (KIA) | B9: 65 | C9: 14362308 | D9: 40969400 | E9: 290000 | F9: 40679400 | G9: 8690000 | H9: =F9/B9 -> 625836.92 | I9: =H9/C9 -> 0.043574956
A10: 735 Усть-Каменогорск ТОО «DCG VOSTOK» (KIA) | B10: 34 | C10: 13328235 | D10: 20042050 | E10: 1800000 | F10: 18242050 | G10: 4100000 | H10: =F10/B10 -> 536530.88 | I10: =H10/C10 -> 0.040255208
A11: 863 Павлодар ТОО «DCG ERTIS» (KIA) | B11: 27 | C11: 13975185 | D11: 19465600 | E11: 0 | F11: 19465600 | G11: 0 | H11: =F11/B11 -> 720948.15 | I11: =H11/C11 -> 0.051587735
A12: Общий итог | B12: 408 | C12: 14071274 | D12: 270267339 | E12: 12264200 | F12: 258003139 | G12: 66880100 | H12: =F12/B12 -> 632360.63 | I12: =H12/C12 -> 0.044939828
A18: Модель | B18: Кол | C18: РРЦ | D18: Маржаа | E18: % | F18: % авто
A19: Carnival | B19: 3 | C19: 24323333 | D19: 1234416.7 | E19: =D19/C19 -> 0.050750308 | F19: =B19/$B$32 -> 0.0073529412
A20: Ceed | B20: 6 | C20: 9890000 | D20: 437641.67 | E20: =D20/C20 -> 0.044250927 | F20: =B20/$B$32 -> 0.014705882
A21: Ceed SW | B21: 10 | C21: 11390000 | D21: 512550 | E21: =D21/C21 -> 0.045 | F21: =B21/$B$32 -> 0.024509804
A22: Cerato | B22: 48 | C22: 10437917 | D22: 382550 | E22: =D22/C22 -> 0.036650034 | F22: =B22/$B$32 -> 0.11764706
A23: K5 | B23: 91 | C23: 13472418 | D23: 675655.49 | E23: =D23/C23 -> 0.050151021 | F23: =B23/$B$32 -> 0.22303922
A24: K8 | B24: 1 | C24: 26490000 | D24: 1721850 | E24: =D24/C24 -> 0.065 | F24: =B24/$B$32 -> 0.0024509804
A25: Seltos | B25: 26 | C25: 12463077 | D25: 558340.38 | E25: =D25/C25 -> 0.044799562 | F25: =B25/$B$32 -> 0.06372549
A26: Soluto | B26: 38 | C26: 7384736.8 | D26: 298947.37 | E26: =D26/C26 -> 0.04048179 | F26: =B26/$B$32 -> 0.093137255
A27: Sorento 2025 | B27: 61 | C27: 18811311 | D27: 743282.79 | E27: =D27/C27 -> 0.039512545 | F27: =B27/$B$32 -> 0.1495098
A28: Sorento 2026 | B28: 11 | C28: 22390000 | D28: 1123313.6 | E28: =D28/C28 -> 0.050170328 | F28: =B28/$B$32 -> 0.026960784
A29: Soul | B29: 4 | C29: 12015000 | D29: 540675 | E29: =D29/C29 -> 0.045 | F29: =B29/$B$32 -> 0.0098039216
A30: Sportage | B30: 93 | C30: 16023976 | D30: 788217.09 | E30: =D30/C30 -> 0.049189856 | F30: =B30/$B$32 -> 0.22794118
... A32: Общий итог | B32: 408 | C32: 14071274 | D32: 632360.63 | E32: =D32/C32 -> 0.044939828 | F32: =B32/$B$32 -> 1
A35: Сумма скидки | B35: (несколько элементов)
A37: Названия строк | B37: Сумма по полю Кол-во | C37: Сумма по полю Сумма скидки
A38: 1069 Актау TOO «DCG Aktau» (KIA) | B38: 1 | C38: 359800
A39: 1151 Алматы ТОО «DCG Qulja» (KIA) | B39: 3 | C39: 6980000
A40: 331 Шымкент ТОО «DCG ONTUSTIK» (KIA) | B40: 1 | C40: 216000
A41: 363 Алматы ТОО «DCG ALMATY» (KIA) | B41: 6 | C41: 2018400
A42: 365 Тараз ТОО «DCGTARAZ» (KIA) | B42: 1 | C42: 600000
A43: 371 Астана ТОО «DCG ASTANA» (KIA) | B43: 1 | C43: 290000
A44: 735 Усть-Каменогорск ТОО «DCG VOSTOK» (KIA) | B44: 2 | C44: 1800000
A45: Общий итог | B45: 15 | C45: 12264200
A49: Названия строк | B49: Маржаа | C49: Мар инвест
A50: 1069 Актау TOO «DCG Aktau» (KIA) | B50: 12225939 | C50: 1264899
A51: 1151 Алматы ТОО «DCG Qulja» (KIA) | B51: 34998400 | C51: 4181150
A52: 331 Шымкент ТОО «DCG ONTUSTIK» (KIA) | B52: 85144200 | C52: 8772250
A53: 363 Алматы ТОО «DCG ALMATY» (KIA) | B53: 33615250 | C53: 4066550
A54: 365 Тараз ТОО «DCGTARAZ» (KIA) | B54: 13632300 | C54: 1600350
A55: 371 Астана ТОО «DCG ASTANA» (KIA) | B55: 40679400 | C55: 4667750
A56: 735 Усть-Каменогорск ТОО «DCG VOSTOK» (KIA) | B56: 18242050 | C56: 2265800
A57: 863 Павлодар ТОО «DCG ERTIS» (KIA) | B57: 19465600 | C57: 1886650
A58: Общий итог | B58: 258003139 | C58: 28705399

Sheet Киа для аналитики
A1: Кол-во | B1: Название ДЦ | C1: Модель KIA | D1: Комплектация KIA | E1: Код модели KIA | F1: VIN KZ | G1: Цвет УС KIA | H1: Модификация | I1: Привод | J1: КПП | K1: Объем двигателя, см3 | L1: Год выпуска | M1: Номер договора | N1: Дата договора | O1: Ответственный | P1: ФИО | Q1: Контакт: ИИН/БИН | R1: Компания: Название компании | S1: Компания: БИН | T1: Цена реализации | U1: Рекомендуемая розничная цена | V1: Сумма скидки | W1: Скидка дистрибуции | X1: Стоимость доп. оборудования | Y1: Максимальное вознаграждение дилера | Z1: Вознаграждение без скидки | AA1: 1s/3s | AB1: Маркетинг | AC1: % | AD1: Маржа | AE1: Маржа после скидок | AF1: Сумма предоплаты, тенге | AG1: Дата подписания акта п/п | AH1: Место реализации (город) | AI1: !Тип продажи а/м | AJ1: Способ приобретения | AK1: Кредит в банке | AL1: Срок кредита в месяцах | AM1: Размер первоначального взноса по кредиту (В процентах) | AN1: Число попаданий на замечания | AO1: Название ДЦ. откуда забрали машину | AP1: Вознаграждение дилера (за перемещённую машину) | AQ1: Компенсация дилера | AR1: Номер карты Технической поддержки Litro | AS1: Дополнительная компенсация дилера | AT1: ID | AU1: Номер телефона | AV1: Завод производитель
A2: 1 | B2: 331 Шымкент ТОО «DCG ONTUSTIK» (KIA) | C2: Seltos | D2: Style | E2: THW52G61Q | F2: MX1ER81AKRK673769 | G2: B3A Neptune Blue / Синий | H2: G0BQ | I2: 4WD | J2: AT | K2: 1999 | L2: 2024 | M2: 331_292944 | N2: 46125 | O2: Ернар Жайдарбек | P2: Селифанова Инна Викторовна | Q2: 780928402396 | T2: 12990000 | U2: 12990000 | V2: 0 | W2: 0 | X2: 0 | Y2: 0 | Z2: 0 | AA2: 3s | AB2: =U2*0.5% -> 64950 | AC2: 0.04 | AD2: =U2*AC2 -> 519600 | AE2: =AD2-V2 -> 519600 | AG2: 46126.917 | AH2: Шымкент | AI2: Безналичный расчет | AJ2: Безналичный | AK2: Без привлечения кредита | AN2: 0 | AP2: 0 | AQ2: 0 | AR2: 132075139 | AT2: 10448600 | AU2: 77015603204 | AV2: САП
A3: 1 | B3: 331 Шымкент ТОО «DCG ONTUSTIK» (KIA) | C3: Sportage | D3: X-Line+ | E3: GYWDL9A1K | F3: MX1PX81FDRK011802 | G3: UD Clear White / Белый | H3: H0D1 | I3: 4WD | J3: AT | K3: 2497 | L3: 2024 | M3: 331_294098 | N3: 46141 | O3: Абдукарим Абдукаим | P3: Ройтман Рустам | Q3: 760211302101 | T3: 15784000 | U3: 16190000 | V3: 216000 | W3: 190000 | X3: 0 | Y3: 0 | Z3: -216000 | AA3: 3s | AB3: =U3*0.5% -> 80950 | AC3: 0.04 | AD3: =U3*AC3 -> 647600 | AE3: =AD3-V3 -> 431600 | AG3: 46142 | AH3: Шымкент | AI3: Безналичный расчет | AJ3: Безналичный | AK3: Без привлечения кредита | AN3: 0 | AP3: 0 | AQ3: 0 | AR3: 132076748 | AT3: 10448618 | AU3: 77077000991 | AV3: САП
A4: 1 | B4: 331 Шымкент ТОО «DCG ONTUSTIK» (KIA) | C4: Ceed | D4: Luxe | E4: J7S6D261F | F4: MX1H2516BSK236164 | G4: H8G Penta Metal / Серый | H4: D2U5 | I4: 2WD | J4: AT | K4: 0 | L4: 2024 | M4: 331_292604 | N4: 46119 | O4: Жандаулет Жұмалиев | P4: Кредина Юлия Александровна | Q4: 871006401238 | T4: 8890000 | U4: 8890000 | V4: 0 | W4: 0 | X4: 0 | Y4: 0 | Z4: 0 | AA4: 3s | AB4: =U4*0.5% -> 44450 | AC4: 0.04 | AD4: =U4*AC4 -> 355600 | AE4: =AD4-V4 -> 355600 | AG4: 46133 | AH4: Шымкент | AI4: Безналичный расчет | AJ4: Безналичный | AK4: Без привлечения кредита | AN4: 0 | AP4: 0 | AQ4: 0 | AR4: 132075639 | AS4: 129900 | AT4: 10685796 | AU4: 77058500030 | AV4: САП
A5: 1 | B5: 331 Шымкент ТОО «DCG ONTUSTIK» (KIA) | C5: Ceed | D5: Comfort | E5: J7S6D261F | F5: MX1H1516BSK239964 | G5: WD Casa White / Белый | H5: S10W | I5: 2WD | J5: AT | K5: 1591 | L5: 2025 | M5: 331_292796 | N5: 46122 | O5: Қаныбек Рахманәлі | P5: Утегенова Кулзат Шаймовна | Q5: 670912402356 | T5: 9690000 | U5: 9690000 | V5: 0 | W5: 0 | X5: 0 | Y5: 436050 | Z5: 436050 | AA5: 3s | AB5: =U5*0.5% -> 48450 | AC5: 0.045 | AD5: =U5*AC5 -> 436050 | AE5: =AD5-V5 -> 436050 | AF5: 2 590 000.00 | AG5: 46128 | AH5: Шымкент | AI5: Кредит | AJ5: Льготное кредитование | AK5: Halyk Bank | AL5: 84 месяца | AM5: 20 | AN5: 0 | AP5: 0 | AQ5: 0 | AR5: 132075335 | AS5: 122900 | AT5: 11010655 | AU5: 77710199162 | AV5: САП
A6: 1 | B6: 331 Шымкент ТОО «DCG ONTUSTIK» (KIA) | C6: Seltos | D6: Luxe | E6: THW52G61V | F6: MX1ER81AESK765870 | G6: KLG Steel Gray / Стальной | H6: G0BM | I6: 2WD | J6: AT | K6: 1999 | L6: 2025 | M6: 331_293611 | N6: 46134 | O6: Абылайхан Нагибек | P6: Файзиев Елнур Хамзаевич | Q6: 840317301462 | T6: 11990000 | U6: 11990000 | V6: 0 | W6: 0 | X6: 0 | Y6: 634050 | Z6: 634050 | AA6: 3s | AB6: =U6*0.5% -> 59950 | AC6: 0.045 | AD6: =U6*AC6 -> 539550 | AE6: =AD6-V6 -> 539550 | AG6: 46135 | AH6: Шымкент | AI6: Безналичный расчет | AJ6: Безналичный | AK6: Без привлечения кредита | AN6: 0 | AP6: 0 | AQ6: 0 | AR6: 132075931 | AS6: 153900 | AT6: 11037821 | AU6: 77077064040 | AV6: САП
A7: 1 | B7: 863 Павлодар ТОО «DCG ERTIS» (KIA) | C7: Ceed | D7: Luxe | E7: J7S6D261F | F7: MX1H2516BSK247884 | G7: H8G Penta Metal / Серый | H7: D2U5 | I7: 2WD | J7: AT | K7: 0 | L7: 2025 | M7: 863_293026 | N7: 46126 | O7: ЕРЖАН КАРАМЕНДИНОВ | P7: Толеу Олжас Жантасулы | Q7: 930224350672 | T7: 10690000 | U7: 10690000 | V7: 0 | W7: 0 | X7: 0 | Y7: 481050 | Z7: 481050 | AA7: 3s | AB7: =U7*0.5% -> 53450 | AC7: 0.045 | AD7: =U7*AC7 -> 481050 | AE7: =AD7-V7 -> 481050 | AF7: 10 690 000.00 | AG7: 46126 | AH7: Павлодар | AI7: Наличный расчет | AJ7: Наличный расчет | AK7: Без привлечения кредита | AM7: 100 | AN7: 0 | AP7: 0 | AQ7: 0 | AR7: 132075156 | AS7: 129900 | AT7: 11090787 | AU7: 77471136340 | AV7: САП
A8: 1 | B8: 363 Алматы ТОО «DCG ALMATY» (KIA) | C8: Ceed SW | D8: Comfort | E8: J7W5D261F | F8: MX1H4816BSK239650 | G8: HW2 Deluxe White / Белый перламутр | H8: K0OP | I8: 2WD | J8: AT | K8: 1591 | L8: 2025 | M8: 363_292472 | N8: 46118 | O8: Бахытжан Смагулов | P8: Нурмухамет Ербол | Q8: 890524301239 | T8: 10990000 | U8: 10990000 | V8: 0 | W8: 0 | X8: 0 | Y8: 494550 | Z8: 494550 | AA8: 1s | AB8: =U8*0.5% -> 54950 | AC8: 0.045 | AD8: =U8*AC8 -> 494550 | AE8: =AD8-V8 -> 494550 | AF8: 10 990 000.00 | AG8: 46120 | AH8: Алматы | AI8: Наличный расчет | AJ8: Наличный расчет | AK8: Без привлечения кредита | AN8: 0 | AP8: 0 | AQ8: 0 | AR8: 132074818 | AS8: 127900 | AT8: 11583852 | AU8: 77777765777 | AV8: САП
A9: 1 | B9: 331 Шымкент ТОО «DCG ONTUSTIK» (KIA) | C9: Seltos | D9: Comfort | E9: THW52G61V | F9: MX1EP81AESK776725 | G9: KDG Gravity Gray / Серый | H9: D395 | I9: 2WD | J9: AT | K9: 1999 | L9: 2025 | M9: 331_294107 | N9: 46141 | O9: Арман Сабыров | P9: Рахимжанов Булат Мырзахметович | Q9: 680127302453 | T9: 10990000 | U9: 10990000 | V9: 0 | W9: 0 | X9: 0 | Y9: 494550 | Z9: 494550 | AA9: 3s | AB9: =U9*0.5% -> 54950 | AC9: 0.045 | AD9: =U9*AC9 -> 494550 | AE9: =AD9-V9 -> 494550 | AF9: 2 198 000.00 | AG9: 46142 | AH9: Шымкент | AI9: Кредит | AJ9: Стандартное кредитование | AK9: Halyk Bank | AL9: 84 месяца | AM9: 20 | AN9: 0 | AO9: 215 Шымкент TOO «NOMAD MOTORS SHYM» (KIA) | AP9: 0 | AQ9: 0 | AR9: 132076704 | AS9: 145900 | AT9: 11608275 | AU9: 77754060101 | AV9: САП
A10: 1 | B10: 331 Шымкент ТОО «DCG ONTUSTIK» (KIA) | C10: Sorento 2025 | D10: Comfort | E10: GZW5L961G | F10: MX1RH81DDSK343433 | G10: AGT Graphite Gray / Серый | H10: G2IF | I10: 4WD | J10: AT | K10: 2497 | L10: 2025 | M10: 331_292593 | N10: 46119 | O10: Нұрсұлтан Көкежан | P10: Сахыбекова Айнур Жаксылыковна | Q10: 760702400654 | T10: 17240000 | U10: 16990000 | V10: 0 | W10: 0 | X10: 250000 | Y10: 934450 | Z10: 934450 | AA10: 3s | AB10: =U10*0.5% -> 84950 | AC10: 0.045 | AD10: =U10*AC10 -> 764550 | AE10: =AD10-V10 -> 764550 | AF10: 3 000 000.00 | AG10: 46127 | AH10: Шымкент | AI10: Кредит | AJ10: Стандартное кредитование | AK10: Банк ЦентрКредит | AL10: 84 месяца | AM10: 20 | AN10: 0 | AO10: 365 Тараз ТОО «DCGTARAZ» (KIA) | AP10: 0 | AQ10: 0 | AS10: 216900 | AT10: 11608558 | AU10: 77073589208 | AV10: САП
A11: 1 | B11: 331 Шымкент ТОО «DCG ONTUSTIK» (KIA) | C11: Cerato | D11: Comfort | E11: DJS4D261F | F11: MX1F3416BSK003073 | G11: KLG Steel Gray / Стальной | H11: D0A6 | I11: 2WD | J11: AT | K11: 1591 | L11: 2025 | M11: 331_292471 | N11: 46118 | O11: Абылайхан Нагибек | P11: Жонеуов Канатбек Жаксылыкбаевич | Q11: 851103301572 | T11: 10310000 | U11: 9990000 | V11: 0 | W11: 0 | X11: 320000 | Y11: 399600 | Z11: 399600 | AA11: 3s | AB11: =U11*0.5% -> 49950 | AC11: 0.04 | AD11: =U11*AC11 -> 399600 | AE11: =AD11-V11 -> 399600 | AF11: 1 031 000.00 | AG11: 46120 | AH11: Шымкент | AI11: Кредит | AJ11: Стандартное кредитование | AK11: Банк ЦентрКредит | AL11: 84 месяца | AM11: 10 | AN11: 0 | AP11: 0 | AQ11: 0 | AR11: 132074816 | AT11: 11608876 | AU11: 77076840585 | AV11: САП
A12: 1 | B12: 735 Усть-Каменогорск ТОО «DCG VOSTOK» (KIA) | C12: K5 | D12: Prestige | E12: EUS42JG1J | F12: MX16A414BSK044694 | G12: SWP Snow White Pearl / Белый перламутр | H12: G156 | I12: 2WD | J12: AT | K12: 1975 | L12: 2025 | M12: 735_293367 | N12: 46131 | O12: Дарын Әмірбеков | P12: Болатов Алмас Болатұлы | Q12: 950309351468 | T12: 14240000 | U12: 13990000 | V12: 0 | W12: 0 | X12: 250000 | Y12: 769450 | Z12: 769450 | AA12: 1s | AB12: =U12*0.5% -> 69950 | AC12: 0.045 | AD12: =U12*AC12 -> 629550 | AE12: =AD12-V12 -> 629550 | AF12: 2 848 000.00 | AG12: 46135 | AH12: Усть-Каменогорск | AI12: Кредит | AJ12: Стандартное кредитование | AK12: Halyk Bank | AL12: 84 месяца | AM12: 20 | AN12: 0 | AP12: 0 | AQ12: 0 | AR12: 132075936 | AS12: 196900 | AT12: 11620509 | AU12: 77027679437 | AV12: САП
A13: 1 | B13: 365 Тараз ТОО «DCGTARAZ» (KIA) | C13: Ceed | D13: Comfort | E13: J7S6D261F | F13: MX1H1516BSK253995 | G13: H8G Penta Metal / Серый | H13: S10W | I13: 2WD | J13: AT | K13: 1591 | L13: 2025 | M13: 365_292181 | N13: 46112 | O13: Тұрар Жеңіс | P13: Сарбаев Ескендір Жұмабайұлы | Q13: 940124301602 | T13: 10240000 | U13: 9690000 | V13: 0 | W13: 0 | X13: 550000 | Y13: 436050 | Z13: 436050 | AA13: 1s | AB13: =U13*0.5% -> 48450 | AC13: 0.045 | AD13: =U13*AC13 -> 436050 | AE13: =AD13-V13 -> 436050 | AF13: 3 500 000.00 | AG13: 46119 | AH13: Тараз | AI13: Кредит | AJ13: Стандартное кредитование | AK13: Евразийский банк | AL13: 84 месяца | AM13: 35 | AN13: 0 | AO13: 331 Шымкент ТОО «DCG ONTUSTIK» (KIA) | AP13: 0 | AQ13: 0 | AR13: 132074730 | AS13: 122900 | AT13: 11704211 | AU13: 77075958349 | AV13: САП
A14: 1 | B14: 863 Павлодар ТОО «DCG ERTIS» (KIA) | C14: Seltos | D14: Luxe | E14: THW52G61V | F14: MX1ER81AESK791864 | G14: KDG Gravity Gray / Серый | H14: G0BM | I14: 2WD | J14: AT | K14: 1999 | L14: 2025 | M14: 863_293237 | N14: 46129 | O14: Алишер Сериков | P14: Сон Виталий Валерьевич | Q14: 820320350314 | T14: 11990000 | U14: 11990000 | V14: 0 | W14: 0 | X14: 0 | Y14: 634050 | Z14: 634050 | AA14: 3s | AB14: =U14*0.5% -> 59950 | AC14: 0.045 | AD14: =U14*AC14 -> 539550 | AE14: =AD14-V14 -> 539550 | AF14: 2 398 000.00 | AG14: 46135 | AH14: Павлодар | AI14: Кредит | AJ14: Льготное кредитование | AK14: Halyk Bank | AL14: 84 месяца | AM14: 20 | AN14: 0 | AP14: 0 | AQ14: 0 | AR14: 132075928 | AS14: 153900 | AT14: 11720930 | AU14: 77015520128 | AV14: САП
A15: 1 | B15: 1151 Алматы ТОО «DCG Qulja» (KIA) | C15: Seltos | D15: Luxe | E15: THW52G61V | F15: MX1ER81AESK792400 | G15: SWP Snow White Pearl / Белый перламутр | H15: G0BM | I15: 2WD | J15: AT | K15: 1999 | L15: 2025 | M15: 1151_293792 | N15: 46140 | O15: Мади Мынбаев | P15: БЕРДЫБАЕВ МУРАТ ЕГИЗБАЕВИЧ | Q15: 670608301765 | T15: 11990000 | U15: 11990000 | V15: 0 | W15: 0 | X15: 0 | Y15: 634050 | Z15: 634050 | AA15: 3s | AB15: =U15*0.5% -> 59950 | AC15: 0.045 | AD15: =U15*AC15 -> 539550 | AE15: =AD15-V15 -> 539550 | AG15: 46142 | AH15: Алматы | AI15: Наличный расчет | AJ15: Наличный расчет | AK15: Без привлечения кредита | AN15: 0 | AO15: 331 Шымкент ТОО «DCG ONTUSTIK» (KIA) | AP15: 0 | AQ15: 0 | AS15: 153900 | AT15: 11720969 | AU15: 77025388525 | AV15: САП
A16: 1 | B16: 365 Тараз ТОО «DCGTARAZ» (KIA) | C16: Seltos | D16: Luxe | E16: THW52G61V | F16: MX1ER81AESK790601 | G16: FSB Modern Black / Черный | H16: G0BM | I16: 2WD | J16: AT | K16: 1999 | L16: 2025 | M16: 365_293027 | N16: 46126 | O16: Сұлтан Пойызбаев | P16: Мамышева Бекзат Бауржановна | Q16: 861106400453 | T16: 11990000 | U16: 11990000 | V16: 0 | W16: 0 | X16: 0 | Y16: 634050 | Z16: 634050 | AA16: 1s | AB16: =U16*0.5% -> 59950 | AC16: 0.045 | AD16: =U16*AC16 -> 539550 | AE16: =AD16-V16 -> 539550 | AF16: 2 398 000.00 | AG16: 46133 | AH16: Тараз | AI16: Кредит | AJ16: Льготное кредитование | AK16: Halyk Bank | AL16: 84 месяца | AM16: 20 | AN16: 0 | AP16: 0 | AQ16: 0 | AR16: 132075670 | AS16: 153900 | AT16: 11721007 | AU16: 77011301532 | AV16: САП
A17: 1 | B17: 1151 Алматы ТОО «DCG Qulja» (KIA) | C17: K5 | D17: Prestige | E17: EUS42JG1J | F17: MX16A414BSK045226 | G17: AG2 Graphite Gray / Серый | H17: G156 | I17: 2WD | J17: AT | K17: 1975 | L17: 2025 | M17: 1151_292671 | N17: 46120 | O17: НУРСУЛТАН КУРПЕТАЕВ | P17: Елюбаев Асхат Болатович | Q17: 931031300644 | T17: 14390000 | U17: 13990000 | V17: 0 | W17: 0 | X17: 400000 | Y17: 769450 | Z17: 769450 | AA17: 3s | AB17: =U17*0.5% -> 69950 | AC17: 0.055 | AD17: =U17*AC17 -> 769450 | AE17: =AD17-V17 -> 769450 | AF17: 1 439 000.00 | AG17: 46127 | AH17: Алматы | AI17: Кредит | AJ17: Льготное кредитование | AK17: Банк ЦентрКредит | AL17: 84 месяца | AM17: 10 | AN17: 0 | AO17: 343 Талдыкорган ТОО «Taldykorgan Auto Group» (KIA) | AP17: 0 | AQ17: 0 | AR17: 132075227 | AS17: 196900 | AT17: 11722414 | AU17: 77017227200 | AV17: САП
A18: 1 | B18: 863 Павлодар ТОО «DCG ERTIS» (KIA) | C18: K5 | D18: Prestige | E18: EUS42JG1J | F18: MX16A414BSK045214 | G18: AG2 Graphite Gray / Серый | H18: G156 | I18: 2WD | J18: AT | K18: 1975 | L18: 2025 | M18: 863_293722 | N18: 46136 | O18: КАНАТ АЛЬЖАНОВ | P18: Сатвалдинов Айтуган Закирьянович | Q18: 660124300308 | T18: 13990000 | U18: 13990000 | V18: 0 | W18: 0 | X18: 0 | Y18: 769450 | Z18: 769450 | AA18: 3s | AB18: =U18*0.5% -> 69950 | AC18: 0.055 | AD18: =U18*AC18 -> 769450 | AE18: =AD18-V18 -> 769450 | AF18: 11 000 000.00 | AG18: 46142 | AH18: Павлодар | AI18: Кредит | AJ18: Стандартное кредитование | AK18: Банк ЦентрКредит | AL18: 36 месяцев | AM18: 79 | AN18: 0 | AP18: 0 | AQ18: 0 | AR18: 132076523 | AS18: 196900 | AT18: 11724906 | AU18: 77778640891 | AV18: САП
A19: 1 | B19: 1151 Алматы ТОО «DCG Qulja» (KIA) | C19: Sportage | D19: Luxe | E19: GYWD2J61G | F19: MX1PV81DDSK016882 | G19: FSB Modern Black / Черный | H19: G0P1 | I19: 4WD | J19: AT | K19: 1999 | L19: 2025 | M19: 1151_293318 | N19: 46132 | O19: Дайана Калиаскар | P19: ЕРБОЛАТОВА ДАНА РИШАДОВНА | Q19: 960516450532 | T19: 13490000 | U19: 13490000 | V19: 0 | W19: 0 | X19: 0 | Y19: 741950 | Z19: 741950 | AA19: 3s | AB19: =U19*0.5% -> 67450 | AC19: 0.055 | AD19: =U19*AC19 -> 741950 | AE19: =AD19-V19 -> 741950 | AF19: 2 690 000.00 | AG19: 46139 | AH19: Алматы | AI19: Льготный кредит | AJ19: Льготное кредитование | AK19: Банк ЦентрКредит | AL19: 84 месяца | AM19: 19 | AN19: 0 | AO19: 363 Алматы ТОО «DCG ALMATY» (KIA) | AP19: 0 | AQ19: 0 | AR19: 132076104 | AS19: 181900 | AT19: 11740393 | AU19: 77054991469 | AV19: САП
A20: 1 | B20: 371 Астана ТОО «DCG ASTANA» (KIA) | C20: K5 | D20: Prestige | E20: EUS42JG1J | F20: MX16A414BSK045168 | G20: ABP Aurora Black Pearl / Чёрный перламутр | H20: G156 | I20: 2WD | J20: AT | K20: 1975 | L20: 2025 | M20: 371_292248 | N20: 46114 | O20: Даурен Манкулов | P20: Музафаров Дархан Шарафиденович | Q20: 920708350552 | T20: 13990000 | U20: 13990000 | V20: 0 | W20: 0 | X20: 0 | Y20: 769450 | Z20: 769450 | AA20: 1s | AB20: =U20*0.5% -> 69950 | AC20: 0.045 | AD20: =U20*AC20 -> 629550 | AE20: =AD20-V20 -> 629550 | AF20: 7 000 000.00 | AG20: 46125 | AH20: Астана | AI20: Кредит | AJ20: Стандартное кредитование | AK20: Береке Банк | AL20: 84 месяца | AM20: 50 | AN20: 0 | AP20: 0 | AQ20: 0 | AR20: 132075060 | AS20: 196900 | AT20: 11741552 | AU20: 77055882200 | AV20: САП
A21: 1 | B21: 371 Астана ТОО «DCG ASTANA» (KIA) | C21: Cerato | D21: Luxe+ | E21: DJS4D261F | F21: MX1F4416BSK003629 | G21: UD Clear White / Белый | H21: G02O | I21: 2WD | J21: AT | K21: 1591 | L21: 2025 | M21: 371_292337 | N21: 46116 | O21: Жансерик Туркменов | P21: Негделхан Макпал | Q21: 900313451195 | T21: 10490000 | U21: 10490000 | V21: 0 | W21: 0 | X21: 0 | Y21: 419600 | Z21: 419600 | AA21: 1s | AB21: =U21*0.5% -> 52450 | AC21: 0.04 | AD21: =U21*AC21 -> 419600 | AE21: =AD21-V21 -> 419600 | AF21: 7 394 228.00 | AG21: 46119 | AH21: Астана | AI21: Кредит | AJ21: Стандартное кредитование | AK21: Банк ЦентрКредит | AL21: 84 месяца | AM21: 75 | AN21: 0 | AP21: 0 | AQ21: 0 | AR21: 132074721 | AT21: 11748607 | AU21: 77752940222 | AV21: САП
A22: 1 | B22: 331 Шымкент ТОО «DCG ONTUSTIK» (KIA) | C22: Cerato | D22: Comfort | E22: DJS4D261F | F22: MX1F3416BSK003954 | G22: KLG Steel Gray / Стальной | H22: D0A6 | I22: 2WD | J22: AT | K22: 1591 | L22: 2025 | M22: 331_291802 | N22: 46109 | O22: Арман Сабыров | P22: Усманов Максат Заркинович | Q22: 850818303157 | T22: 10540000 | U22: 9990000 | V22: 0 | W22: 0 | X22: 550000 | Y22: 399600 | Z22: 399600 | AA22: 3s | AB22: =U22*0.5% -> 49950 | AC22: 0.04 | AD22: =U22*AC22 -> 399600 | AE22: =AD22-V22 -> 399600 | AF22: 2 000 000.00 | AG22: 46120 | AH22: Шымкент | AI22: Кредит | AJ22: Стандартное кредитование | AK22: МФО Sapa Digital Finance | AL22: 84 месяца | AM22: 10 | AN22: 0 | AO22: 215 Шымкент TOO «NOMAD MOTORS SHYM» (KIA) | AP22: 0 | AQ22: 0 | AR22: 132074841 | AT22: 11754055 | AU22: 77780568595 | AV22: САП
A23: 1 | B23: 863 Павлодар ТОО «DCG ERTIS» (KIA) | C23: K5 | D23: Prestige | E23: EUS42JG1J | F23: MX16A414BSK045429 | G23: ABP Aurora Black Pearl / Чёрный перламутр | H23: G156 | I23: 2WD | J23: AT | K23: 1975 | L23: 2025 | M23: 863_293012 | N23: 46126 | O23: ЕРЖАН КАРАМЕНДИНОВ | P23: Шаймырза Мадияр Нуржанулы | Q23: 991124350117 | T23: 13990000 | U23: 13990000 | V23: 0 | W23: 0 | X23: 0 | Y23: 769450 | Z23: 769450 | AA23: 3s | AB23: =U23*0.5% -> 69950 | AC23: 0.055 | AD23: =U23*AC23 -> 769450 | AE23: =AD23-V23 -> 769450 | AF23: 6 000 000.00 | AG23: 46129 | AH23: Павлодар | AI23: Кредит | AJ23: Стандартное кредитование | AK23: Altyn Bank | AL23: 84 месяца | AM23: 43 | AN23: 0 | AP23: 0 | AQ23: 0 | AR23: 132075411 | AS23: 196900 | AT23: 11768708 | AU23: 77471912805 | AV23: САП
A24: 1 | B24: 331 Шымкент ТОО «DCG ONTUSTIK» (KIA) | C24: K5 | D24: Prestige | E24: EUS42JG1J | F24: MX16A414BSK045492 | G24: SWP Snow White Pearl / Белый перламутр | H24: G156 | I24: 2WD | J24: AT | K24: 1975 | L24: 2025 | M24: 331_292523 | N24: 46118 | O24: Абылайхан Нагибек | P24: Аширова Гулмира Барзуовна | Q24: 681230400802 | T24: 13990000 | U24: 13990000 | V24: 0 | W24: 0 | X24: 0 | Y24: 769450 | Z24: 769450 | AA24: 3s | AB24: =U24*0.5% -> 69950 | AC24: 0.055 | AD24: =U24*AC24 -> 769450 | AE24: =AD24-V24 -> 769450 | AG24: 46120 | AH24: Шымкент | AI24: Безналичный расчет | AJ24: Безналичный | AK24: Без привлечения кредита | AN24: 0 | AP24: 0 | AQ24: 0 | AR24: 132074716 | AS24: 196900 | AT24: 11774590 | AU24: 77780506870 | AV24: САП
A25: 1 | B25: 371 Астана ТОО «DCG ASTANA» (KIA) | C25: Cerato | D25: Luxe+ | E25: DJS4D261F | F25: MX1F4416BSK004210 | G25: UD Clear White / Белый | H25: G02O | I25: 2WD | J25: AT | K25: 1591 | L25: 2025 | M25: 371_293244 | N25: 46129 | O25: Артур Пак | P25: Жунусов Алихан Жасуланович | Q25: 901226350393 | T25: 10740000 | U25: 10490000 | V25: 0 | W25: 0 | X25: 250000 | Y25: 419600 | Z25: 419600 | AA25: 1s | AB25: =U25*0.5% -> 52450 | AC25: 0.04 | AD25: =U25*AC25 -> 419600 | AE25: =AD25-V25 -> 419600 | AF25: 5 250 000.00 | AG25: 46136 | AH25: Астана | AI25: Кредит | AJ25: Стандартное кредитование | AK25: Евразийский банк | AL25: 84 месяца | AM25: 50 | AN25: 0 | AP25: 0 | AQ25: 0 | AR25: 132075977 | AT25: 11785166 | AU25: 77011057917 | AV25: САП
A26: 1 | B26: 735 Усть-Каменогорск ТОО «DCG VOSTOK» (KIA) | C26: K5 | D26: Luxe | E26: EUS42JG1J | F26: MX16A414BSK045131 | G26: AG2 Graphite Gray / Серый | H26: G155 | J26: AT | K26: 1975 | L26: 2025 | M26: 735_293887 | N26: 46139 | O26: Максим Косихин | P26: Мендыбаева Салтанат Сайлаугазовна | Q26: 780806402789 | T26: 12690000 | U26: 12690000 | V26: 0 | W26: 0 | X26: 0 | Y26: 697950 | Z26: 697950 | AA26: 1s | AB26: =U26*0.5% -> 63450 | AC26: 0.045 | AD26: =U26*AC26 -> 571050 | AE26: =AD26-V26 -> 571050 | AF26: 12 690 000.00 | AG26: 46140 | AH26: Усть-Каменогорск | AI26: Безналичный расчет | AJ26: Безналичный | AK26: Без привлечения кредита | AN26: 0 | AO26: 381 Allur Auto Group KIA | AP26: 0 | AQ26: 0 | AR26: 132076195 | AT26: 11792267 | AU26: 77051205357 | AV26: САП
A27: 1 | B27: 331 Шымкент ТОО «DCG ONTUSTIK» (KIA) | C27: Ceed | D27: Comfort | E27: J7S6D261F | F27: MX1H1516BSK257863 | G27: HW2 Deluxe White / Белый перламутр | H27: S10W | I27: 2WD | J27: AT | K27: 1591 | L27: 2025 | M27: 331_292503 | N27: 46118 | O27: Ернар Жайдарбек | P27: Онласбеков Алмас Атирханович | Q27: 830223302676 | T27: 9690000 | U27: 9690000 | V27: 0 | W27: 0 | X27: 0 | Y27: 436050 | Z27: 436050 | AA27: 3s | AB27: =U27*0.5% -> 48450 | AC27: 0.045 | AD27: =U27*AC27 -> 436050 | AE27: =AD27-V27 -> 436050 | AG27: 46119 | AH27: Шымкент | AI27: Безналичный расчет | AJ27: Безналичный | AK27: Без привлечения кредита | AN27: 0 | AP27: 0 | AQ27: 0 | AR27: 132074728 | AS27: 122900 | AT27: 11802657 | AU27: 77717951777 | AV27: САП
A28: 1 | B28: 735 Усть-Каменогорск ТОО «DCG VOSTOK» (KIA) | C28: Ceed SW | D28: Comfort | E28: J7W5D261F | F28: MX1H4816BSK253924 | G28: HW2 Deluxe White / Белый перламутр | H28: K0OP | I28: 2WD | J28: AT | K28: 1591 | L28: 2025 | M28: 735_293260 | N28: 46129 | O28: Азамат Тоқтарбеков | P28: Әбиев Расул Қырықбайұлы | Q28: 40216550843 | T28: 11240000 | U28: 10990000 | V28: 0 | W28: 0 | X28: 250000 | Y28: 494550 | Z28: 494550 | AA28: 1s | AB28: =U28*0.5% -> 54950 | AC28: 0.045 | AD28: =U28*AC28 -> 494550 | AE28: =AD28-V28 -> 494550 | AF28: 1 273 135.00 | AG28: 46132 | AH28: Усть-Каменогорск | AI28: Кредит | AJ28: Стандартное кредитование | AK28: Банк ЦентрКредит | AL28: 84 месяца | AM28: 40 | AN28: 0 | AP28: 0 | AQ28: 0 | AR28: 132075524 | AS28: 127900 | AT28: 11815914 | AU28: 77476242119 | AV28: САП
A29: 1 | B29: 371 Астана ТОО «DCG ASTANA» (KIA) | C29: Ceed SW | D29: Luxe | E29: J7W5D261F | F29: MX1H5816BSK253985 | G29: 1K Black Pearl / Чёрный перламутр | H29: H33I | I29: 2WD | J29: AT | K29: 1591 | L29: 2025 | M29: 371_292608 | N29: 46119 | O29: Даурен Манкулов | P29: Усенбаев Нуршат Ергешович | Q29: 830807300218 | T29: 11490000 | U29: 11490000 | V29: 0 | W29: 0 | X29: 0 | Y29: 517050 | Z29: 517050 | AA29: 1s | AB29: =U29*0.5% -> 57450 | AC29: 0.045 | AD29: =U29*AC29 -> 517050 | AE29: =AD29-V29 -> 517050 | AF29: 11 490 000.00 | AG29: 46120 | AH29: Астана | AI29: Наличный расчет | AJ29: Наличный расчет | AK29: Без привлечения кредита | AN29: 0 | AP29: 0 | AQ29: 0 | AR29: 132074775 | AT29: 11836538 | AU29: 77788386665 | AV29: САП
A30: 1 | B30: 371 Астана ТОО «DCG ASTANA» (KIA) | C30: Ceed SW | D30: Luxe | E30: J7W5D261F | F30: MX1H5816BSK253620 | G30: USG Yuca Steel Gray/Стальной | H30: H33I | I30: 2WD | J30: AT | K30: 1591 | L30: 2025 | M30: 371_293137 | N30: 46127 | O30: Виктория Чубинец | P30: Жаканов Есбол Еркингалиевич | Q30: 900325301043 | T30: 11490000 | U30: 11490000 | V30: 0 | W30: 0 | X30: 0 | Y30: 517050 | Z30: 517050 | AA30: 1s | AB30: =U30*0.5% -> 57450 | AC30: 0.045 | AD30: =U30*AC30 -> 517050 | AE30: =AD30-V30 -> 517050 | AF30: 2 298 000.00 | AG30: 46134 | AH30: Астана | AI30: Льготный кредит | AJ30: Льготное кредитование | AK30: Halyk Bank | AL30: 84 месяца | AM30: 20 | AN30: 0 | AP30: 0 | AQ30: 0 | AR30: 132075833 | AT30: 11836552 | AU30: 77055550785 | AV30: САП
A31: 1 | B31: 331 Шымкент ТОО «DCG ONTUSTIK» (KIA) | C31: K5 | D31: Tulpar | E31: EUS42JG1J | F31: MX16A414BSK045972 | G31: ABP Aurora Black Pearl / Чёрный перламутр | H31: G174 | I31: 2WD | J31: AT | K31: 0 | L31: 2025 | M31: 331_292850 | N31: 46124 | O31: Нұрсұлтан Көкежан | P31: Жайлымыс Гулвира Қаныбекқызы | Q31: 940821401549 | T31: 13940000 | U31: 13390000 | V31: 0 | W31: 0 | X31: 550000 | Y31: 736450 | Z31: 736450 | AA31: 3s | AB31: =U31*0.5% -> 66950 | AC31: 0.055 | AD31: =U31*AC31 -> 736450 | AE31: =AD31-V31 -> 736450 | AF31: 7 000 000.00 | AG31: 46127 | AH31: Шымкент | AI31: Кредит | AJ31: Стандартное кредитование | AK31: Halyk Bank | AL31: 84 месяца | AM31: 45 | AN31: 0 | AP31: 0 | AQ31: 0 | AR31: 132075245 | AS31: 189900 | AT31: 11869042 | AU31: 77074131020 | AV31: САП
A32: 1 | B32: 331 Шымкент ТОО «DCG ONTUSTIK» (KIA) | C32: K5 | D32: Prestige | E32: EUS42JG1J | F32: MX16A414BSK045862 | G32: AG2 Graphite Gray / Серый | H32: G156 | I32: 2WD | J32: AT | K32: 1975 | L32: 2025 | M32: 331_293905 | N32: 46139 | O32: Арман Сабыров | P32: Алашбаев Барат Мамаханович | Q32: 721027300654 | T32: 13990000 | U32: 13990000 | V32: 0 | W32: 0 | X32: 0 | Y32: 769450 | Z32: 769450 | AA32: 3s | AB32: =U32*0.5% -> 69950 | AC32: 0.055 | AD32: =U32*AC32 -> 769450 | AE32: =AD32-V32 -> 769450 | AF32: 3 990 000.00 | AG32: 46142 | AH32: Шымкент | AI32: Кредит | AJ32: Льготное кредитование | AK32: Halyk Bank | AL32: 84 месяца | AM32: 30 | AN32: 0 | AP32: 0 | AQ32: 0 | AR32: 132076553 | AS32: 196900 | AT32: 11869045 | AU32: 77076554172 | AV32: САП
A33: 1 | B33: 863 Павлодар ТОО «DCG ERTIS» (KIA) | C33: K5 | D33: Luxe | E33: EUS42JG1J | F33: MX16A414BSK046190 | G33: AG2 Graphite Gray / Серый | H33: G155 | J33: AT | K33: 1975 | L33: 2025 | M33: 863_292937 | N33: 46125 | O33: ЕРЖАН КАРАМЕНДИНОВ | P33: Мусабеков Ринат Серикказыевич | Q33: 820411301112 | T33: 12690000 | U33: 12690000 | V33: 0 | W33: 0 | X33: 0 | Y33: 697950 | Z33: 697950 | AA33: 3s | AB33: =U33*0.5% -> 63450 | AC33: 0.055 | AD33: =U33*AC33 -> 697950 | AE33: =AD33-V33 -> 697950 | AF33: 6 345 000.00 | AG33: 46140 | AH33: Павлодар | AI33: Кредит | AJ33: Стандартное кредитование | AK33: Halyk Bank | AL33: 36 месяцев | AM33: 50 | AN33: 0 | AP33: 0 | AQ33: 0 | AR33: 132076234 | AT33: 11869205 | AU33: 77054440001 | AV33: САП
A34: 1 | B34: 1151 Алматы ТОО «DCG Qulja» (KIA) | C34: K5 | D34: Tulpar | E34: EUS42JG1J | F34: MX16A414BSK046128 | G34: SWP Snow White Pearl / Белый перламутр | H34: G176 | I34: 2WD | J34: AT | K34: 1975 | L34: 2025 | M34: 1151_292374 | N34: 46118 | O34: Магилан Махамет | P34: АХИЛЬГОВ ИЛЬЯС СУЛТАНОВИЧ | Q34: 891019302353 | T34: 13390000 | U34: 13390000 | V34: 0 | W34: 0 | X34: 0 | Y34: 791450 | Z34: 791450 | AA34: 3s | AB34: =U34*0.5% -> 66950 | AC34: 0.055 | AD34: =U34*AC34 -> 736450 | AE34: =AD34-V34 -> 736450 | AF34: 100 000.00 | AG34: 46136 | AH34: Алматы | AI34: Наличный расчет | AJ34: Наличный расчет | AK34: Без привлечения кредита | AN34: 0 | AP34: 0 | AQ34: 0 | AR34: 132075986 | AS34: 189900 | AT34: 11870591 | AU34: 77017666627 | AV34: САП
A35: 1 | B35: 735 Усть-Каменогорск ТОО «DCG VOSTOK» (KIA) | C35: K5 | D35: Tulpar | E35: EUS42JG1J | F35: MX16A414BSK045967 | G35: SWP Snow White Pearl / Белый перламутр | H35: G174 | I35: 2WD | J35: AT | K35: 0 | L35: 2025 | M35: 735_292362 | N35: 46116 | O35: Дарын Әмірбеков | P35: Бектибаев Саяхат Аитмухаметулы | Q35: 810108300402 | T35: 13640000 | U35: 14390000 | V35: 0 | W35: 1000000 | X35: 250000 | Y35: 791450 | Z35: 791450 | AA35: 1s | AB35: =U35*0.5% -> 71950 | AC35: 0.045 | AD35: =U35*AC35 -> 647550 | AE35: =AD35-V35 -> 647550 | AF35: 2 728 000.00 | AG35: 46120 | AH35: Усть-Каменогорск | AI35: Кредит | AJ35: Стандартное кредитование | AK35: Halyk Bank | AL35: 84 месяца | AM35: 20 | AN35: 0 | AP35: 0 | AQ35: 0 | AR35: 132074782 | AS35: 189900 | AT35: 11871863 | AU35: 77055321642 | AV35: САП
A36: 1 | B36: 1069 Актау TOO «DCG Aktau» (KIA) | C36: Sorento 2025 | D36: Tulpar | E36: GZW7L961G | F36: MX1RH81DDSK366026 | G36: BN4 New Gray / Серый | H36: G2YU | I36: 4WD | J36: AT | K36: 2497 | L36: 2025 | M36: 1069_293640 | N36: 46135 | O36: Нурали Садыбаев | P36: Хайрмеденов Кайрбек Ушкишбекович | Q36: 850928302197 | T36: 18990000 | U36: 18990000 | V36: 0 | W36: 0 | X36: 0 | Y36: 1044450 | Z36: 1044450 | AA36: 3s | AB36: =U36*0.5% -> 94950 | AC36: 0.055 | AD36: =U36*AC36 -> 1044450 | AE36: =AD36-V36 -> 1044450 | AF36: 9 500 000.00 | AG36: 46140 | AH36: Актау | AI36: Кредит | AJ36: Стандартное кредитование | AK36: Halyk Bank | AL36: 36 месяцев | AM36: 50 | AN36: 0 | AP36: 0 | AQ36: 0 | AR36: 132076218 | AS36: 241900 | AT36: 11896502 | AU36: 77073996969 | AV36: САП
A37: 1 | B37: 1069 Актау TOO «DCG Aktau» (KIA) | C37: Cerato | D37: Luxe+ | E37: DJS4D261F | F37: MX1F4416BSK005443 | G37: UD Clear White / Белый | H37: G02O | I37: 2WD | J37: AT | K37: 1591 | L37: 2025 | M37: 1069_293140 | N37: 46127 | O37: Тимур Нурибаев | P37: Сматов Исатай Маратұлы | Q37: 780712300160 | T37: 10490000 | U37: 10490000 | V37: 0 | W37: 0 | X37: 0 | Y37: 419600 | Z37: 419600 | AA37: 3s | AB37: =U37*0.5% -> 52450 | AC37: 0.04 | AD37: =U37*AC37 -> 419600 | AE37: =AD37-V37 -> 419600 | AF37: 2 098 000.00 | AG37: 46133 | AH37: Актау | AI37: Льготный кредит | AJ37: Льготное кредитование | AK37: Halyk Bank | AL37: 84 месяца | AM37: 20 | AN37: 0 | AP37: 0 | AQ37: 0 | AR37: 132075606 | AT37: 11896509 | AU37: 77022201191 | AV37: САП
A38: 1 | B38: 331 Шымкент ТОО «DCG ONTUSTIK» (KIA) | C38: Soul | D38: Style | E38: SKW52G61V | F38: MX1J381UESK272812 | G38: AH1 Clear White / Inferno Red / Белый с красной крышей | H38: G906 | I38: 2WD | J38: AT | K38: 1999 | L38: 2025 | M38: 331_292740 | N38: 46121 | O38: Абдукарим Абдукаим | P38: Тулеумбетов Нурсултан Махмутович | Q38: 891005302357 | T38: 12990000 | U38: 12990000 | V38: 0 | W38: 0 | X38: 0 | Y38: 584550 | Z38: 584550 | AA38: 3s | AB38: =U38*0.5% -> 64950 | AC38: 0.045 | AD38: =U38*AC38 -> 584550 | AE38: =AD38-V38 -> 584550 | AF38: 2 990 000.00 | AG38: 46139 | AH38: Шымкент | AI38: Кредит | AJ38: Льготное кредитование | AK38: Halyk Bank | AL38: 84 месяца | AM38: 20 | AN38: 0 | AP38: 0 | AQ38: 0 | AR38: 132076108 | AS38: 149900 | AT38: 11898117 | AU38: 77710180066 | AV38: САП
A39: 1 | B39: 1069 Актау TOO «DCG Aktau» (KIA) | C39: Sorento 2025 | D39: Tulpar | E39: GZW7L961G | F39: MX1RH81DDSK370432 | G39: SWP Snow White Pearl / Белый перламутр | H39: G2YU | I39: 4WD | J39: AT | K39: 2497 | L39: 2025 | M39: 1069_293047 | N39: 46126 | O39: Тимур Нурибаев | P39: Конусова Гулшат Жайылгановна | Q39: 930419000032 | T39: 18990000 | U39: 18990000 | V39: 0 | W39: 0 | X39: 0 | Y39: 1044450 | Z39: 1044450 | AA39: 3s | AB39: =U39*0.5% -> 94950 | AC39: 0.045 | AD39: =U39*AC39 -> 854550 | AE39: =AD39-V39 -> 854550 | AF39: 18 990 000.00 | AG39: 46129 | AH39: Актау | AI39: Наличный расчет | AJ39: Наличный расчет | AK39: Без привлечения кредита | AN39: 0 | AP39: 0 | AQ39: 0 | AR39: 132075442 | AS39: 241900 | AT39: 11931916 | AU39: 77020617288 | AV39: САП
A40: 1 | B40: 363 Алматы ТОО «DCG ALMATY» (KIA) | C40: Seltos | D40: Style | E40: THW52G61Q | F40: MX1ER81AKTK833516 | G40: FSB Modern Black / Черный | H40: G0DK | I40: 4WD | J40: CVT | K40: 1999 | L40: 2025 | M40: 363_294076 | N40: 46141 | O40: Даур Құттыбай | P40: Максимова Ақбота Максимқызы | Q40: 920705401673 | T40: 13490000 | U40: 13490000 | V40: 0 | W40: 0 | X40: 0 | Y40: 607050 | Z40: 607050 | AA40: 1s | AB40: =U40*0.5% -> 67450 | AC40: 0.045 | AD40: =U40*AC40 -> 607050 | AE40: =AD40-V40 -> 607050 | AF40: 3 304 000.00 | AG40: 46142 | AH40: Алматы | AI40: Кредит | AJ40: Стандартное кредитование | AK40: Halyk Bank | AL40: 84 месяца | AM40: 10 | AN40: 0 | AP40: 0 | AQ40: 0 | AR40: 132076501 | AS40: 176900 | AT40: 11944944 | AU40: 77470647847 | AV40: САП
A41: 1 | B41: 331 Шымкент ТОО «DCG ONTUSTIK» (KIA) | C41: K5 | D41: Luxe | E41: EUS42JG1J | F41: MX16A414BSK045307 | G41: SWP Snow White Pearl / Белый перламутр | H41: G155 | J41: AT | K41: 1975 | L41: 2025 | M41: 331_292561 | N41: 46119 | O41: Ернар Жайдарбек | P41: Спатаев Аскарбек Рустембекович | Q41: 891022300849 | T41: 13690000 | U41: 12690000 | V41: 0 | W41: 0 | X41: 1000000 | Y41: 697950 | Z41: 697950 | AA41: 3s | AB41: =U41*0.5% -> 63450 | AC41: 0.055 | AD41: =U41*AC41 -> 697950 | AE41: =AD41-V41 -> 697950 | AF41: 3 690 000.00 | AG41: 46127 | AH41: Шымкент | AI41: Кредит | AJ41: Льготное кредитование | AK41: Halyk Bank | AL41: 84 месяца | AM41: 20 | AN41: 0 | AP41: 0 | AQ41: 0 | AR41: 132075237 | AT41: 11965893 | AU41: 77029061131 | AV41: САП
A42: 1 | B42: 331 Шымкент ТОО «DCG ONTUSTIK» (KIA) | C42: K8 | D42: Prestige | E42: GGS4J9A1K | F42: MX1M441DDSK085835 | G42: ISG / Ivory Silver/Серебро слоновой кости / Серый | H42: K20I | I42: 4WD | J42: AT | K42: 3470 | L42: 2025 | M42: 331_292575 | N42: 46119 | O42: Ерболат Балабас | P42: Калгинбаева Айгерим Талгатовна | Q42: 881126401391 | T42: 26490000 | U42: 26490000 | V42: 0 | W42: 0 | X42: 0 | Y42: 1721850 | Z42: 1721850 | AA42: 3s | AB42: =U42*0.5% -> 132450 | AC42: 0.065 | AD42: =U42*AC42 -> 1721850 | AE42: =AD42-V42 -> 1721850 | AF42: 13 995 000.00 | AG42: 46122 | AH42: Шымкент | AI42: Кредит | AJ42: Стандартное кредитование | AK42: Halyk Bank | AL42: 84 месяца | AM42: 50 | AN42: 0 | AP42: 0 | AQ42: 0 | AR42: 132074941 | AS42: 274900 | AT42: 11972510 | AU42: 77019000088 | AV42: САП
A43: 1 | B43: 331 Шымкент ТОО «DCG ONTUSTIK» (KIA) | C43: Cerato | D43: Luxe+ | E43: DJS4D261F | F43: MX1F4416BSK005554 | G43: KLG Steel Gray / Стальной | H43: G02O | I43: 2WD | J43: AT | K43: 1591 | L43: 2025 | M43: 331_293491 | N43: 46133 | O43: Арман Сабыров | P43: Жапан Данияр Сәрсенбайұлы | Q43: 920820302383 | T43: 10740000 | U43: 10490000 | V43: 0 | W43: 0 | X43: 250000 | Y43: 419600 | Z43: 419600 | AA43: 3s | AB43: =U43*0.5% -> 52450 | AC43: 0.04 | AD43: =U43*AC43 -> 419600 | AE43: =AD43-V43 -> 419600 | AF43: 6 000 000.00 | AG43: 46134 | AH43: Шымкент | AI43: Кредит | AJ43: Стандартное кредитование | AK43: Halyk Bank | AL43: 84 месяца | AM43: 55 | AN43: 0 | AO43: 215 Шымкент TOO «NOMAD MOTORS SHYM» (KIA) | AP43: 0 | AQ43: 0 | AR43: 132075801 | AT43: 11975458 | AU43: 77757108458 | AV43: САП
A44: 1 | B44: 1151 Алматы ТОО «DCG Qulja» (KIA) | C44: Sorento 2025 | D44: Tulpar | E44: GZW7J961K | F44: MX1RH81EDSK372506 | G44: SWP Snow White Pearl / Белый перламутр | H44: G2YU | I44: 4WD | J44: AT | K44: 3470 | L44: 2025 | M44: 1151_291223 | N44: 46101 | O44: Дайана Калиаскар | P44: Советбек Нұрғали Нұрланұлы | Q44: 930722300722 | T44: 15000000 | U44: 21690000 | V44: 6690000 | W44: 0 | X44: 0 | Y44: 976050 | Z44: -5713950 | AA44: 3s | AB44: =U44*0.5% -> 108450 | AC44: 0.045 | AD44: =U44*AC44 -> 976050 | AE44: =AD44-V44 -> -5713950 | AF44: 1 500 000.00 | AG44: 46128 | AH44: Алматы | AI44: Льготный кредит | AJ44: Льготное кредитование | AK44: Евразийский банк | AL44: 84 месяца | AM44: 10 | AN44: 0 | AO44: 1089 Костанай TOO «Allur Auto Qostanay» (KIA) | AP44: 0 | AQ44: 0 | AR44: 132075364 | AS44: 258900 | AT44: 11994472 | AU44: 77079222688 | AV44: САП
A45: 1 | B45: 735 Усть-Каменогорск ТОО «DCG VOSTOK» (KIA) | C45: Sorento 2025 | D45: Luxe | E45: GZW7L961G | F45: MX1RH81DDSK377025 | G45: KLG Steel Gray / Стальной | H45: G2IJ | I45: 4WD | J45: AT | K45: 2497 | L45: 2025 | M45: 735_292297 | N45: 46115 | O45: Дарын Әмірбеков | P45: Кәдірбекова Арай Талғатқызы | Q45: 960727451459 | T45: 18390000 | U45: 19390000 | V45: 1000000 | W45: 0 | X45: 0 | Y45: 872550 | Z45: -127450 | AA45: 1s | AB45: =U45*0.5% -> 96950 | AC45: 0.045 | AD45: =U45*AC45 -> 872550 | AE45: =AD45-V45 -> -127450 | AG45: 46118 | AH45: Усть-Каменогорск | AI45: Безналичный расчет | AJ45: Безналичный | AK45: Без привлечения кредита | AN45: 0 | AP45: 0 | AQ45: 0 | AR45: 132074673 | AS45: 229900 | AT45: 11994747 | AU45: 77764401030 | AV45: САП
A46: 1 | B46: 1069 Актау TOO «DCG Aktau» (KIA) | C46: Ceed SW | D46: Prestige | E46: J7W5D261F | F46: MX1H5816BSK253703 | G46: CSS Lunar Silver / Стальной | H46: H33J | I46: 2WD | J46: AT | K46: 1591 | L46: 2025 | M46: 1069_293443 | N46: 46132 | O46: Тимур Нурибаев | P46: Бисенов Абай Базартаевич | Q46: 811116300835 | T46: 12490000 | U46: 12490000 | V46: 0 | W46: 0 | X46: 0 | Y46: 562050 | Z46: 562050 | AA46: 3s | AB46: =U46*0.5% -> 62450 | AC46: 0.045 | AD46: =U46*AC46 -> 562050 | AE46: =AD46-V46 -> 562050 | AF46: 12 490 000.00 | AG46: 46133 | AH46: Актау | AI46: Наличный расчет | AJ46: Наличный расчет | AK46: Без привлечения кредита | AN46: 0 | AP46: 0 | AQ46: 0 | AR46: 132075716 | AS46: 145900 | AT46: 12005126 | AU46: 77714075702 | AV46: САП
A47: 1 | B47: 735 Усть-Каменогорск ТОО «DCG VOSTOK» (KIA) | C47: Ceed SW | D47: Comfort | E47: J7W5D261F | F47: MX1H4816BSK253707 | G47: HW2 Deluxe White / Белый перламутр | H47: K0OP | I47: 2WD | J47: AT | K47: 1591 | L47: 2025 | M47: 735_293366 | N47: 46131 | O47: Азамат Тоқтарбеков | P47: Денебаева Адемы Ержановна | Q47: 820223402948 | T47: 10990000 | U47: 10990000 | V47: 0 | W47: 0 | X47: 0 | Y47: 494550 | Z47: 494550 | AA47: 1s | AB47: =U47*0.5% -> 54950 | AC47: 0.045 | AD47: =U47*AC47 -> 494550 | AE47: =AD47-V47 -> 494550 | AF47: 1 100 000.00 | AG47: 46134 | AH47: Усть-Каменогорск | AI47: Кредит | AJ47: Стандартное кредитование | AK47: Береке Банк | AL47: 84 месяца | AM47: 10 | AN47: 0 | AP47: 0 | AQ47: 0 | AR47: 132075774 | AS47: 127900 | AT47: 12007161 | AU47: 77772808223 | AV47: САП
A48: 1 | B48: 371 Астана ТОО «DCG ASTANA» (KIA) | C48: Ceed SW | D48: Luxe | E48: J7W5D261F | F48: MX1H5816BSK253777 | G48: H8G Penta Metal / Серый | H48: H33I | I48: 2WD | J48: AT | K48: 1591 | L48: 2025 | M48: 371_292860 | N48: 46125 | O48: Александр Кочетков | P48: Исаберген Мейіржан Бауыржанұлы | Q48: 930127302635 | T48: 11590000 | U48: 11490000 | V48: 0 | W48: 0 | X48: 100000 | Y48: 517050 | Z48: 517050 | AA48: 1s | AB48: =U48*0.5% -> 57450 | AC48: 0.045 | AD48: =U48*AC48 -> 517050 | AE48: =AD48-V48 -> 517050 | AF48: 2 318 000.00 | AG48: 46129 | AH48: Астана | AI48: Льготный кредит | AJ48: Льготное кредитование | AK48: Halyk Bank | AL48: 84 месяца | AM48: 20 | AN48: 0 | AP48: 0 | AQ48: 0 | AR48: 132075421 | AT48: 12025426 | AU48: 77751646639 | AV48: САП
A49: 1 | B49: 371 Астана ТОО «DCG ASTANA» (KIA) | C49: Ceed SW | D49: Luxe | E49: J7W5D261F | F49: MX1H5816BSK253927 | G49: 1K Black Pearl / Чёрный перламутр | H49: H33I | I49: 2WD | J49: AT | K49: 1591 | L49: 2025 | M49: 371_292759 | N49: 46121 | O49: Владимир Ульянов | P49: Абильмажинов Айдархан Муратович | Q49: 820916351045 | T49: 11990000 | U49: 11490000 | V49: 0 | W49: 0 | X49: 500000 | Y49: 517050 | Z49: 517050 | AA49: 1s | AB49: =U49*0.5% -> 57450 | AC49: 0.045 | AD49: =U49*AC49 -> 517050 | AE49: =AD49-V49 -> 517050 | AF49: 1 199 000.00 | AG49: 46134 | AH49: Астана | AI49: Кредит | AJ49: Льготное кредитование | AK49: Банк ЦентрКредит | AL49: 84 месяца | AM49: 10 | AN49: 0 | AP49: 0 | AQ49: 0 | AR49: 132075834 | AT49: 12025427 | AU49: 77015998080 | AV49: САП
A50: 1 | B50: 331 Шымкент ТОО «DCG ONTUSTIK» (KIA) | C50: Cerato | D50: Luxe+ | E50: DJS4D261F | F50: MX1F4416BSK005574 | G50: KLG Steel Gray / Стальной | H50: G02O | I50: 2WD | J50: AT | K50: 1591 | L50: 2025 | M50: 331_293135 | N50: 46127 | O50: Серик Адильбеков | P50: Карабекова Асемгул Онгарбековна | Q50: 950930401018 | T50: 10740000 | U50: 10490000 | V50: 0 | W50: 0 | X50: 250000 | Y50: 419600 | Z50: 419600 | AA50: 3s | AB50: =U50*0.5% -> 52450 | AC50: 0.04 | AD50: =U50*AC50 -> 419600 | AE50: =AD50-V50 -> 419600 | AF50: 1 075 000.00 | AG50: 46132 | AH50: Шымкент | AI50: Кредит | AJ50: Стандартное кредитование | AK50: Береке Банк | AL50: 84 месяца | AM50: 10 | AN50: 0 | AO50: 215 Шымкент TOO «NOMAD MOTORS SHYM» (KIA) | AP50: 0 | AQ50: 0 | AR50: 132075509 | AT50: 12035559 | AU50: 77771967956 | AV50: САП
A51: 1 | B51: 1151 Алматы ТОО «DCG Qulja» (KIA) | C51: Ceed | D51: Luxe | E51: J7S6D261F | F51: MX1H2516BSK257902 | G51: H8G Penta Metal / Серый | H51: D2U5 | I51: 2WD | J51: AT | K51: 0 | L51: 2025 | M51: 1151_291952 | N51: 46111 | O51: Дайана Калиаскар | R51: ТОО "Микрофинансовая организация"Тойота Файнаншл Сервисез Казахстан" | S51: 130440002721 | T51: 10390000 | U51: 10690000 | V51: 0 | W51: 300000 | X51: 0 | Y51: 481050 | Z51: 481050 | AA51: 3s | AB51: =U51*0.5% -> 53450 | AC51: 0.045 | AD51: =U51*AC51 -> 481050 | AE51: =AD51-V51 -> 481050 | AF51: 10 390 000.00 | AG51: 46119 | AH51: Алматы | AI51: Безналичный расчет | AJ51: Безналичный | AK51: Без привлечения кредита | AN51: 0 | AP51: 0 | AQ51: 0 | AR51: 132074755 | AS51: 129900 | AT51: 12035581 | AU51: 77717904545 | AV51: САП
A52: 1 | B52: 735 Усть-Каменогорск ТОО «DCG VOSTOK» (KIA) | C52: Ceed SW | D52: Comfort | E52: J7W5D261F | F52: MX1H4816BSK253788 | G52: CSS Lunar Silver / Стальной | H52: K0OP | I52: 2WD | J52: AT | K52: 1591 | L52: 2025 | M52: 735_292760 | N52: 46121 | O52: Азамат Тоқтарбеков | P52: Касымханов Мурат Токтаулович | Q52: 690422300869 | T52: 11690000 | U52: 10990000 | V52: 0 | W52: 0 | X52: 700000 | Y52: 494550 | Z52: 494550 | AA52: 1s | AB52: =U52*0.5% -> 54950 | AC52: 0.045 | AD52: =U52*AC52 -> 494550 | AE52: =AD52-V52 -> 494550 | AF52: 1 200 000.00 | AG52: 46126 | AH52: Усть-Каменогорск | AI52: Кредит | AJ52: Стандартное кредитование | AK52: МФО Sapa Digital Finance | AL52: 84 месяца | AM52: 10 | AN52: 0 | AP52: 0 | AQ52: 0 | AR52: 132075078 | AS52: 127900 | AT52: 12036869 | AU52: 77778573737 | AV52: САП
A53: 1 | B53: 735 Усть-Каменогорск ТОО «DCG VOSTOK» (KIA) | C53: Ceed SW | D53: Luxe | E53: J7W5D261F | F53: MX1H5816BSK253881 | G53: CSS Lunar Silver / Стальной | H53: H33I | I53: 2WD | J53: AT | K53: 1591 | L53: 2025 | M53: 735_293044 | N53: 46126 | O53: Максим Косихин | P53: Ворошилов Василий Николаевич | Q53: 610726301766 | T53: 11490000 | U53: 11490000 | V53: 0 | W53: 0 | X53: 0 | Y53: 517050 | Z53: 517050 | AA53: 1s | AB53: =U53*0.5% -> 57450 | AC53: 0.045 | AD53: =U53*AC53 -> 517050 | AE53: =AD53-V53 -> 517050 | AG53: 46127 | AH53: Усть-Каменогорск | AI53: Безналичный расчет | AJ53: Безналичный | AK53: Без привлечения кредита | AN53: 0 | AP53: 0 | AQ53: 0 | AR53: 132075205 | AT53: 12036872 | AU53: 77772645297 | AV53: САП
A54: 1 | B54: 331 Шымкент ТОО «DCG ONTUSTIK» (KIA) | C54: Sorento 2025 | D54: Comfort | E54: GZW5L961G | F54: MXRRH81DDTY000175 | G54: KLG Steel Gray / Стальной | H54: G2IF | I54: 4WD | J54: AUTOT/M | K54: 2497 | L54: 2025 | M54: 1190_293592 | N54: 46134 | O54: Нұрсұлтан Көкежан | P54: Нурмагамбетова Гульнур Айбековна | Q54: 851215400430 | T54: 16990000 | U54: 16990000 | V54: 0 | W54: 0 | X54: 0 | Y54: 934450 | Z54: 934450 | AA54: 3s | AB54: =U54*0.5% -> 84950 | AC54: 0.055 | AD54: =U54*AC54 -> 934450 | AE54: =AD54-V54 -> 934450 | AG54: 46135 | AH54: Шымкент | AI54: Безналичный расчет | AJ54: Безналичный | AK54: Без привлечения кредита | AN54: 0 | AO54: 1191 Шымкент TOO «NOMAD MOTORS SHYM» (KIA) AMQ | AP54: 0 | AQ54: 0 | AR54: 132075901 | AS54: 216900 | AT54: 12065253 | AU54: 77710658121 | AV54: KKZ
A55: 1 | B55: 1069 Актау TOO «DCG Aktau» (KIA) | C55: Sorento 2025 | D55: Comfort | E55: GZW5L961G | F55: MXRRH81DDTY000180 | G55: KLG Steel Gray / Стальной | H55: G2IF | I55: 4WD | J55: AUTOT/M | K55: 2497 | L55: 2025 | M55: 1184_293736 | N55: 46136 | O55: Нурали Садыбаев | P55: Қалдыбаев Серік Жолдыбайұлы | Q55: 750704302366 | T55: 17690000 | U55: 16990000 | V55: 0 | W55: 0 | X55: 700000 | Y55: 934450 | Z55: 934450 | AA55: 3s | AB55: =U55*0.5% -> 84950 | AC55: 0.055 | AD55: =U55*AC55 -> 934450 | AE55: =AD55-V55 -> 934450 | AF55: 8 000 000.00 | AG55: 46141 | AH55: Актау | AI55: Кредит | AJ55: Стандартное кредитование | AK55: Halyk Bank | AL55: 48 месяцев | AM55: 47 | AN55: 0 | AP55: 0 | AQ55: 0 | AR55: 132076437 | AS55: 216900 | AT55: 12066079 | AU55: 77025616175 | AV55: KKZ
A56: 1 | B56: 735 Усть-Каменогорск ТОО «DCG VOSTOK» (KIA) | C56: Sorento 2025 | D56: Comfort | E56: GZW5L961G | F56: MXRRH81DDTY000167 | G56: AGT Graphite Gray / Серый | H56: G2IF | I56: 4WD | J56: AUTOT/M | K56: 2497 | L56: 2025 | M56: 1181_292815 | N56: 46122 | O56: Максим Косихин | P56: Айтказин Оралбек Айтказыулы | Q56: 590409300024 | T56: 16990000 | U56: 16990000 | V56: 0 | W56: 0 | X56: 0 | Y56: 934450 | Z56: 934450 | AA56: 1s | AB56: =U56*0.5% -> 84950 | AC56: 0.045 | AD56: =U56*AC56 -> 764550 | AE56: =AD56-V56 -> 764550 | AG56: 46125 | AH56: Усть-Каменогорск | AI56: Безналичный расчет | AJ56: Безналичный | AK56: Без привлечения кредита | AN56: 0 | AP56: 0 | AQ56: 0 | AR56: 132075038 | AS56: 216900 | AT56: 12066363 | AU56: 77052822439 | AV56: KKZ
A57: 1 | B57: 1069 Актау TOO «DCG Aktau» (KIA) | C57: Sportage | D57: Style | E57: GYWDL9A1K | F57: MX1PV81FDSK020847 | G57: KLG Steel Gray / Стальной | H57: G0P2 | I57: 4WD | J57: AT | K57: 2497 | L57: 2025 | M57: 1069_293563 | N57: 46134 | O57: Нурали Садыбаев | P57: Аманьязов Ерлан Муратович | Q57: 880812302845 | T57: 15340000 | U57: 15090000 | V57: 0 | W57: 0 | X57: 250000 | Y57: 829950 | Z57: 829950 | AA57: 3s | AB57: =U57*0.5% -> 75450 | AC57: 0.055 | AD57: =U57*AC57 -> 829950 | AE57: =AD57-V57 -> 829950 | AF57: 4 530 000.00 | AG57: 46140 | AH57: Актау | AI57: Кредит | AJ57: Стандартное кредитование | AK57: Шинхань Банк | AL57: 60 месяцев | AM57: 30 | AN57: 0 | AP57: 0 | AQ57: 0 | AR57: 132076233 | AS57: 201900 | AT57: 12073111 | AU57: 77089186689 | AV57: САП
A58: 1 | B58: 863 Павлодар ТОО «DCG ERTIS» (KIA) | C58: K5 | D58: Luxe | E58: EUS42JG1J | F58: MXR6AA248TY900203 | G58: AG2 Graphite Gray / Серый | H58: G155 | I58: 2WD | J58: AUTOT/M | K58: 1975 | L58: 2025 | M58: 1192_292673 | N58: 46120 | O58: КАНАТ АЛЬЖАНОВ | P58: Бессинбенова Асель Джамбуловна | Q58: 860804450408 | T58: 12690000 | U58: 12690000 | V58: 0 | W58: 0 | X58: 0 | Y58: 697950 | Z58: 697950 | AA58: 3s | AB58: =U58*0.5% -> 63450 | AC58: 0.055 | AD58: =U58*AC58 -> 697950 | AE58: =AD58-V58 -> 697950 | AF58: 3 933 900.00 | AG58: 46134 | AH58: Павлодар | AI58: Кредит | AJ58: Стандартное кредитование | AK58: МФО Sapa Digital Finance | AL58: 84 месяца | AM58: 31 | AN58: 0 | AP58: 0 | AQ58: 0 | AR58: 132075822 | AT58: 12073603 | AU58: 77015550985 | AV58: KKZ
A59: 1 | B59: 331 Шымкент ТОО «DCG ONTUSTIK» (KIA) | C59: Sorento 2025 | D59: Style | E59: GZW7L961G | F59: MXRRH81DDTY000263 | G59: BN4 New Gray / Серый | H59: G2Z2 | I59: 4WD | J59: AUTOT/M | K59: 2497 | L59: 2025 | M59: 1190_292517 | N59: 46118 | O59: Ернар Жайдарбек | P59: Тультаев Берик Асильханович | Q59: 851114301532 | T59: 19990000 | U59: 19990000 | V59: 0 | W59: 0 | X59: 0 | Y59: 1099450 | Z59: 1099450 | AA59: 3s | AB59: =U59*0.5% -> 99950 | AC59: 0.045 | AD59: =U59*AC59 -> 899550 | AE59: =AD59-V59 -> 899550 | AF59: 6 000 000.00 | AG59: 46120 | AH59: Шымкент | AI59: Кредит | AJ59: Стандартное кредитование | AK59: Береке Банк | AL59: 84 месяца | AM59: 30 | AN59: 0 | AP59: 0 | AQ59: 0 | AR59: 132074830 | AS59: 251900 | AT59: 12076071 | AU59: 77017378585 | AV59: KKZ
A60: 1 | B60: 1151 Алматы ТОО «DCG Qulja» (KIA) | C60: Sorento 2025 | D60: Comfort | E60: GZW5L961G | F60: MXRRH81DDTY000151 | G60: ABP Aurora Black Pearl / Чёрный перламутр | H60: G2IF | I60: 4WD | J60: AUTOT/M | K60: 2497 | L60: 2025 | M60: 1173_293631 | N60: 46135 | O60: Мади Мынбаев | P60: ОСПАНОВ АСЕТ МУХАМЕТХАНОВИЧ | Q60: 740101304957 | T60: 17290000 | U60: 16990000 | V60: 0 | W60: 0 | X60: 300000 | Y60: 934450 | Z60: 934450 | AA60: 3s | AB60: =U60*0.5% -> 84950 | AC60: 0.055 | AD60: =U60*AC60 -> 934450 | AE60: =AD60-V60 -> 934450 | AF60: 10 000 000.00 | AG60: 46139 | AH60: Алматы | AI60: Кредит | AJ60: Стандартное кредитование | AK60: Евразийский банк | AL60: 36 месяцев | AM60: 57 | AN60: 0 | AP60: 0 | AQ60: 0 | AR60: 132076100 | AS60: 216900 | AT60: 12084904 | AU60: 77772323950 | AV60: KKZ
A61: 1 | B61: 331 Шымкент ТОО «DCG ONTUSTIK» (KIA) | C61: Sorento 2025 | D61: Comfort | E61: GZW5L961G | F61: MXRRH81DDTY000146 | G61: SWP Snow White Pearl / Белый перламутр | H61: G2IF | I61: 4WD | J61: AUTOT/M | K61: 2497 | L61: 2025 | M61: 1190_292775 | N61: 46122 | O61: Нұрсұлтан Көкежан | P61: Керимбекова Айман Богенбаевна | Q61: 880818401806 | T61: 16990000 | U61: 16990000 | V61: 0 | W61: 0 | X61: 0 | Y61: 934450 | Z61: 934450 | AA61: 3s | AB61: =U61*0.5% -> 84950 | AC61: 0.045 | AD61: =U61*AC61 -> 764550 | AE61: =AD61-V61 -> 764550 | AG61: 46128 | AH61: Шымкент | AI61: Безналичный расчет | AJ61: Безналичный | AK61: Без привлечения кредита | AN61: 0 | AO61: 363 Алматы ТОО «DCG ALMATY» (KIA) | AP61: 0 | AQ61: 0 | AR61: 132075329 | AS61: 216900 | AT61: 12086642 | AU61: 77011171166 | AV61: KKZ
A62: 1 | B62: 331 Шымкент ТОО «DCG ONTUSTIK» (KIA) | C62: K5 | D62: Luxe | E62: EUS42JG1J | F62: MX16A414BTK047173 | G62: AG2 Graphite Gray / Серый | H62: G155 | I62: 2WD | J62: AT | K62: 1975 | L62: 2025 | M62: 331_292232 | N62: 46113 | O62: Нұрсұлтан Көкежан | P62: Қалдыбек Аружан Ғалымжанқызы | Q62: 20712600846 | T62: 13990000 | U62: 13690000 | V62: 0 | W62: 0 | X62: 300000 | Y62: 752950 | Z62: 752950 | AA62: 3s | AB62: =U62*0.5% -> 68450 | AC62: 0.055 | AD62: =U62*AC62 -> 752950 | AE62: =AD62-V62 -> 752950 | AF62: 1 450 000.00 | AG62: 46118 | AH62: Шымкент | AI62: Кредит | AJ62: Стандартное кредитование | AK62: Банк ЦентрКредит | AL62: 84 месяца | AM62: 10 | AN62: 0 | AP62: 0 | AQ62: 0 | AR62: 132074682 | AT62: 12098324 | AU62: 77472307919 | AV62: САП
A63: 1 | B63: 331 Шымкент ТОО «DCG ONTUSTIK» (KIA) | C63: K5 | D63: Luxe | E63: EUS42JG1J | F63: MX16A414BTK047176 | G63: AG2 Graphite Gray / Серый | H63: G155 | J63: AT | K63: 1975 | L63: 2025 | M63: 331_292704 | N63: 46120 | O63: Абдукарим Абдукаим | P63: Жамелов Баглан Алтаевич | Q63: 860703302175 | T63: 12690000 | U63: 12690000 | V63: 0 | W63: 0 | X63: 0 | Y63: 697950 | Z63: 697950 | AA63: 3s | AB63: =U63*0.5% -> 63450 | AC63: 0.055 | AD63: =U63*AC63 -> 697950 | AE63: =AD63-V63 -> 697950 | AF63: 2 690 000.00 | AG63: 46142 | AH63: Шымкент | AI63: Кредит | AJ63: Льготное кредитование | AK63: Halyk Bank | AL63: 84 месяца | AM63: 10 | AN63: 0 | AP63: 0 | AQ63: 0 | AR63: 132076498 | AT63: 12098325 | AU63: 77024582777 | AV63: САП
A64: 1 | B64: 863 Павлодар ТОО «DCG ERTIS» (KIA) | C64: K5 | D64: Luxe | E64: EUS42JG1J | F64: MX16A414BTK047315 | G64: SWP Snow White Pearl / Белый перламутр | H64: G155 | J64: AT | K64: 1975 | L64: 2025 | M64: 863_293148 | N64: 46128 | O64: ЕРЖАН КАРАМЕНДИНОВ | P64: Раздыков Руслан Алексеевич | Q64: 820519300528 | T64: 12690000 | U64: 12690000 | V64: 0 | W64: 0 | X64: 0 | Y64: 697950 | Z64: 697950 | AA64: 3s | AB64: =U64*0.5% -> 63450 | AC64: 0.055 | AD64: =U64*AC64 -> 697950 | AE64: =AD64-V64 -> 697950 | AF64: 4 500 000.00 | AG64: 46129 | AH64: Павлодар | AI64: Кредит | AJ64: Стандартное кредитование | AK64: Altyn Bank | AL64: 84 месяца | AM64: 35 | AN64: 0 | AP64: 0 | AQ64: 0 | AR64: 132075409 | AT64: 12098362 | AU64: 77772728801 | AV64: САП
A65: 1 | B65: 365 Тараз ТОО «DCGTARAZ» (KIA) | C65: Sorento 2025 | D65: Luxe | E65: GZW7L961G | F65: MX1RH81DDTK379210 | G65: BN4 New Gray / Серый | H65: G2IJ | I65: 4WD | J65: AT | K65: 2497 | L65: 2025 | M65: 365_293312 | N65: 46130 | O65: Даниял Мурат | P65: Сыздыков Бахытбек Умирбекович | Q65: 680823300699 | T65: 18940000 | U65: 18390000 | V65: 0 | W65: 0 | X65: 550000 | Y65: 1011450 | Z65: 1011450 | AA65: 1s | AB65: =U65*0.5% -> 91950 | AC65: 0.045 | AD65: =U65*AC65 -> 827550 | AE65: =AD65-V65 -> 827550 | AF65: 3 000 000.00 | AG65: 46133 | AH65: Тараз | AI65: Кредит | AJ65: Стандартное кредитование | AK65: Банк ЦентрКредит | AL65: 84 месяца | AM65: 20 | AN65: 0 | AP65: 0 | AQ65: 0 | AR65: 132075664 | AS65: 229900 | AT65: 12099432 | AU65: 77003563945 | AV65: САП
A66: 1 | B66: 1151 Алматы ТОО «DCG Qulja» (KIA) | C66: K5 | D66: Luxe | E66: EUS42JG1J | F66: MX16A414BTK047175 | G66: AG2 Graphite Gray / Серый | H66: G155 | J66: AT | K66: 1975 | L66: 2025 | M66: 1151_293331 | N66: 46132 | O66: Ерик Серкешбаев | P66: Дикомбаева Гульмира Аргымбаевна | Q66: 730216401625 | T66: 12690000 | U66: 12690000 | V66: 0 | W66: 0 | X66: 0 | Y66: 697950 | Z66: 697950 | AA66: 3s | AB66: =U66*0.5% -> 63450 | AC66: 0.055 | AD66: =U66*AC66 -> 697950 | AE66: =AD66-V66 -> 697950 | AF66: 1 300 000.00 | AG66: 46136 | AH66: Алматы | AI66: Кредит | AJ66: Стандартное кредитование | AK66: МФО Sapa Digital Finance | AL66: 84 месяца | AM66: 10 | AN66: 0 | AP66: 0 | AQ66: 0 | AR66: 132075982 | AT66: 12099879 | AU66: 77788655633 | AV66: САП
A67: 1 | B67: 1069 Актау TOO «DCG Aktau» (KIA) | C67: Sorento 2025 | D67: Luxe | E67: GZW7L961G | F67: MX1RH81DDTK379731 | G67: SWP Snow White Pearl / Белый перламутр | H67: G2IJ | I67: 4WD | J67: AT | K67: 2497 | L67: 2025 | M67: 1069_292640 | N67: 46120 | O67: Нурали Садыбаев | P67: Булекенов Гани Газизович | Q67: 861130300414 | T67: 18946000 | U67: 18390000 | V67: 0 | W67: 0 | X67: 556000 | Y67: 1011450 | Z67: 1011450 | AA67: 3s | AB67: =U67*0.5% -> 91950 | AC67: 0.045 | AD67: =U67*AC67 -> 827550 | AE67: =AD67-V67 -> 827550 | AF67: 3 000 000.00 | AG67: 46122 | AH67: Актау | AI67: Кредит | AJ67: Стандартное кредитование | AK67: Банк ЦентрКредит | AL67: 84 месяца | AM67: 16 | AN67: 0 | AP67: 0 | AQ67: 0 | AR67: 132075003 | AS67: 229900 | AT67: 12118163 | AU67: 77015526252 | AV67: САП
A68: 1 | B68: 331 Шымкент ТОО «DCG ONTUSTIK» (KIA) | C68: Sorento 2025 | D68: Comfort | E68: GZW5L961G | F68: MX1RH81DDTK378664 | G68: BN4 New Gray / Серый | H68: G2IF | I68: 4WD | J68: AT | K68: 2497 | L68: 2025 | M68: 331_293004 | N68: 46125 | O68: Нұрсұлтан Көкежан | P68: Атенов Абзал Абидилаевич | Q68: 910124301855 | T68: 16990000 | U68: 16990000 | V68: 0 | W68: 0 | X68: 0 | Y68: 934450 | Z68: 934450 | AA68: 3s | AB68: =U68*0.5% -> 84950 | AC68: 0.045 | AD68: =U68*AC68 -> 764550 | AE68: =AD68-V68 -> 764550 | AF68: 1 700 000.00 | AG68: 46132 | AH68: Шымкент | AI68: Кредит | AJ68: Стандартное кредитование | AK68: Банк ЦентрКредит | AL68: 84 месяца | AM68: 10 | AN68: 0 | AO68: 365 Тараз ТОО «DCGTARAZ» (KIA) | AP68: 0 | AQ68: 0 | AR68: 132075532 | AS68: 216900 | AT68: 12122597 | AU68: 77753210992 | AV68: САП
A69: 1 | B69: 363 Алматы ТОО «DCG ALMATY» (KIA) | C69: Seltos | D69: Comfort | E69: THW52G61Q | F69: MX1EP81AKTK844000 | G69: KDG Gravity Gray / Серый | H69: D420 | I69: 4WD | J69: CVT | K69: 1999 | L69: 2025 | M69: 363_292466 | N69: 46118 | O69: Бахытжан Смагулов | P69: Пак Екатерина Андреевна | Q69: 960220400943 | T69: 11590000 | U69: 11590000 | V69: 0 | W69: 0 | X69: 0 | Y69: 521550 | Z69: 521550 | AA69: 1s | AB69: =U69*0.5% -> 57950 | AC69: 0.045 | AD69: =U69*AC69 -> 521550 | AE69: =AD69-V69 -> 521550 | AF69: 11 590 000.00 | AG69: 46121 | AH69: Алматы | AI69: Наличный расчет | AJ69: Наличный расчет | AK69: Без привлечения кредита | AN69: 0 | AP69: 0 | AQ69: 0 | AR69: 132074887 | AS69: 152900 | AT69: 12122601 | AU69: 77012451115 | AV69: САП
A70: 1 | B70: 1151 Алматы ТОО «DCG Qulja» (KIA) | C70: Seltos | D70: Luxe | E70: THW52G61V | F70: MX1ER81AETK843552 | G70: F1A Pluton Blue / Fusion Black / Голубой с чёрной крышей | H70: G0DG | I70: 2WD | J70: CVT | K70: 1999 | L70: 2025 | M70: 1151_293032 | N70: 46126 | O70: Рахима Габдуллина | P70: МИМИКЕНОВ ИРАНГАИП ДУНЕНБАЕВИЧ | Q70: 641125300015 | T70: 11990000 | U70: 11990000 | V70: 0 | W70: 0 | X70: 0 | Y70: 539550 | Z70: 539550 | AA70: 3s | AB70: =U70*0.5% -> 59950 | AC70: 0.045 | AD70: =U70*AC70 -> 539550 | AE70: =AD70-V70 -> 539550 | AF70: 11 990 000.00 | AG70: 46126 | AH70: Алматы | AI70: Наличный расчет | AJ70: Наличный расчет | AK70: Без привлечения кредита | AN70: 0 | AP70: 0 | AQ70: 0 | AR70: 132075155 | AS70: 153900 | AT70: 12122642 | AU70: 77019290161 | AV70: САП
A71: 1 | B71: 331 Шымкент ТОО «DCG ONTUSTIK» (KIA) | C71: Seltos | D71: Luxe | E71: THW52G61V | F71: MX1ER81AETK829970 | G71: KLG Steel Gray / Стальной | H71: G0DG | I71: 2WD | J71: CVT | K71: 1999 | L71: 2025 | M71: 331_292798 | N71: 46122 | O71: Нұрсұлтан Көкежан | P71: Камалова Әсем Тоғызбайқызы | Q71: 940120402101 | T71: 11990000 | U71: 11990000 | V71: 0 | W71: 0 | X71: 0 | Y71: 539550 | Z71: 539550 | AA71: 3s | AB71: =U71*0.5% -> 59950 | AC71: 0.045 | AD71: =U71*AC71 -> 539550 | AE71: =AD71-V71 -> 539550 | AF71: 2 490 000.00 | AG71: 46128 | AH71: Шымкент | AI71: Кредит | AJ71: Льготное кредитование | AK71: Halyk Bank | AL71: 84 месяца | AM71: 20 | AN71: 0 | AP71: 0 | AQ71: 0 | AR71: 132075309 | AS71: 153900 | AT71: 12125665 | AU71: 77029515655 | AV71: САП
A72: 1 | B72: 363 Алматы ТОО «DCG ALMATY» (KIA) | C72: Seltos | D72: Comfort | E72: THW52G61Q | F72: MX1EP81AKTK843834 | G72: SWP Snow White Pearl / Белый перламутр | H72: D420 | I72: 4WD | J72: CVT | K72: 1999 | L72: 2025 | M72: 363_292722 | N72: 46121 | O72: Бахытжан Смагулов | P72: Ким Людмила Леонидовна | Q72: 830515401760 | T72: 11590000 | U72: 11590000 | V72: 0 | W72: 0 | X72: 0 | Y72: 521550 | Z72: 521550 | AA72: 1s | AB72: =U72*0.5% -> 57950 | AC72: 0.045 | AD72: =U72*AC72 -> 521550 | AE72: =AD72-V72 -> 521550 | AF72: 11 590 000.00 | AG72: 46122 | AH72: Алматы | AI72: Наличный расчет | AJ72: Наличный расчет | AK72: Без привлечения кредита | AN72: 0 | AO72: 1219 Алматы ТОО «ASTER Автомобили» (KIA) | AP72: 0 | AQ72: 0 | AR72: 132075016 | AS72: 152900 | AT72: 12128578 | AU72: 77012451110 | AV72: САП
A73: 1 | B73: 363 Алматы ТОО «DCG ALMATY» (KIA) | C73: Seltos | D73: Comfort | E73: THW52G61Q | F73: MXREP81AKTY900617 | G73: SWP Snow White Pearl / Белый перламутр | H73: D420 | I73: 4WD | J73: CVT | K73: 1999 | L73: 2025 | M73: 1169_292806 | N73: 46122 | O73: Бахытжан Смагулов | P73: Ким Светлана Леонидовна | Q73: 810802401678 | T73: 11590000 | U73: 11590000 | V73: 0 | W73: 0 | X73: 0 | Y73: 521550 | Z73: 521550 | AA73: 1s | AB73: =U73*0.5% -> 57950 | AC73: 0.045 | AD73: =U73*AC73 -> 521550 | AE73: =AD73-V73 -> 521550 | AF73: 11 590 000.00 | AG73: 46127 | AH73: Алматы | AI73: Наличный расчет | AJ73: Наличный расчет | AK73: Без привлечения кредита | AN73: 0 | AO73: 365 Тараз ТОО «DCGTARAZ» (KIA) | AP73: 0 | AQ73: 0 | AR73: 132075254 | AS73: 152900 | AT73: 12128981 | AU73: 77008078077 | AV73: KKZ
A74: 1 | B74: 1151 Алматы ТОО «DCG Qulja» (KIA) | C74: Seltos | D74: Tulpar | E74: THW52G61Q | F74: MXRER81AKTY900552 | G74: FSB Modern Black / Черный | H74: G0EZ | I74: 4WD | J74: CVT | K74: 1999 | L74: 2025 | M74: 1173_293754 | N74: 46136 | O74: Дайана Калиаскар | P74: ШИРБЕКОВА ЕЛИНУР ХАМИТОВНА | Q74: 30105601152 | T74: 12990000 | U74: 12990000 | V74: 0 | W74: 0 | X74: 0 | Y74: 584550 | Z74: 584550 | AA74: 3s | AB74: =U74*0.5% -> 64950 | AC74: 0.045 | AD74: =U74*AC74 -> 584550 | AE74: =AD74-V74 -> 584550 | AG74: 46141 | AH74: Алматы | AI74: Наличный расчет | AJ74: Наличный расчет | AK74: Без привлечения кредита | AN74: 0 | AP74: 0 | AQ74: 0 | AR74: 132076305 | AS74: 165900 | AT74: 12130376 | AU74: 77089697993 | AV74: KKZ
A75: 1 | B75: 735 Усть-Каменогорск ТОО «DCG VOSTOK» (KIA) | C75: Seltos | D75: Luxe | E75: THW52G61Q | F75: MXRER81AKTY900167 | G75: KDG Gravity Gray / Серый | H75: G0DI | I75: 4WD | J75: CVT | K75: 1999 | L75: 2025 | M75: 1181_292514 | N75: 46118 | O75: Азамат Тоқтарбеков | P75: Әбілқайыров Абай Ержанұлы | Q75: 960305350727 | T75: 12840000 | U75: 12590000 | V75: 0 | W75: 0 | X75: 250000 | Y75: 566550 | Z75: 566550 | AA75: 1s | AB75: =U75*0.5% -> 62950 | AC75: 0.045 | AD75: =U75*AC75 -> 566550 | AE75: =AD75-V75 -> 566550 | AF75: 3 000 000.00 | AG75: 46120 | AH75: Усть-Каменогорск | AI75: Кредит | AJ75: Стандартное кредитование | AK75: Halyk Bank | AL75: 84 месяца | AM75: 40 | AN75: 0 | AP75: 0 | AQ75: 0 | AR75: 132074828 | AS75: 160900 | AT75: 12130673 | AU75: 77776229688 | AV75: KKZ
A76: 1 | B76: 365 Тараз ТОО «DCGTARAZ» (KIA) | C76: Seltos | D76: Luxe | E76: THW52G61V | F76: MXRER81AETY900130 | G76: F1D Clear White / Fusion Black | H76: G0DG | I76: 2WD | J76: CVT | K76: 1999 | L76: 2025 | M76: 1174_292777 | N76: 46121 | O76: Сұлтан Пойызбаев | P76: Сауранбаева Гульнур Сатыбалдиевна | Q76: 880405401157 | T76: 11990000 | U76: 11990000 | V76: 0 | W76: 0 | X76: 0 | Y76: 539550 | Z76: 539550 | AA76: 1s | AB76: =U76*0.5% -> 59950 | AC76: 0.045 | AD76: =U76*AC76 -> 539550 | AE76: =AD76-V76 -> 539550 | AF76: 7 500 000.00 | AG76: 46126 | AH76: Тараз | AI76: Кредит | AJ76: Стандартное кредитование | AK76: Altyn Bank | AL76: 84 месяца | AM76: 60 | AN76: 0 | AO76: 363 Алматы ТОО «DCG ALMATY» (KIA) | AP76: 0 | AQ76: 0 | AR76: 132075141 | AS76: 153900 | AT76: 12131877 | AU76: 77078580024 | AV76: KKZ
A77: 1 | B77: 331 Шымкент ТОО «DCG ONTUSTIK» (KIA) | C77: Seltos | D77: Luxe | E77: THW52G61Q | F77: MXRER81AKTY900169 | G77: KLG Steel Gray / Стальной | H77: G0DI | I77: 4WD | J77: CVT | K77: 1999 | L77: 2025 | M77: 1190_293610 | N77: 46134 | O77: Абылайхан Нагибек | P77: Файзиева Айгуль Кожановна | Q77: 740210401486 | T77: 12590000 | U77: 12590000 | V77: 0 | W77: 0 | X77: 0 | Y77: 566550 | Z77: 566550 | AA77: 3s | AB77: =U77*0.5% -> 62950 | AC77: 0.045 | AD77: =U77*AC77 -> 566550 | AE77: =AD77-V77 -> 566550 | AG77: 46135 | AH77: Шымкент | AI77: Безналичный расчет | AJ77: Безналичный | AK77: Без привлечения кредита | AN77: 0 | AP77: 0 | AQ77: 0 | AR77: 132075932 | AS77: 160900 | AT77: 12136062 | AU77: 77756869503 | AV77: KKZ
A78: 1 | B78: 331 Шымкент ТОО «DCG ONTUSTIK» (KIA) | C78: Seltos | D78: Tulpar | E78: THW52G61Q | F78: MXRER81AKTY900585 | G78: KLG Steel Gray / Стальной | H78: G0EZ | I78: 4WD | J78: CVT | K78: 1999 | L78: 2025 | M78: 1190_294170 | N78: 46142 | O78: Нұрсұлтан Көкежан | P78: Сарсенбаева Равия Кудайбергеновна | Q78: 480815401427 | T78: 12990000 | U78: 12990000 | V78: 0 | W78: 0 | X78: 0 | Y78: 584550 | Z78: 584550 | AA78: 3s | AB78: =U78*0.5% -> 64950 | AC78: 0.045 | AD78: =U78*AC78 -> 584550 | AE78: =AD78-V78 -> 584550 | AG78: 46142 | AH78: Шымкент | AI78: Безналичный расчет | AJ78: Безналичный | AK78: Без привлечения кредита | AN78: 0 | AP78: 0 | AQ78: 0 | AR78: 132076701 | AS78: 165900 | AT78: 12136065 | AU78: 77028480611 | AV78: KKZ
A79: 1 | B79: 331 Шымкент ТОО «DCG ONTUSTIK» (KIA) | C79: Seltos | D79: Comfort | E79: THW52G61Q | F79: MXREP81AKTY900616 | G79: SWP Snow White Pearl / Белый перламутр | H79: D420 | I79: 4WD | J79: CVT | K79: 1999 | L79: 2025 | M79: 1190_293007 | N79: 46125 | O79: Арман Сабыров | P79: Мухтарханова Наргиза Абдирасуловна | Q79: 850408402047 | T79: 11840000 | U79: 11590000 | V79: 0 | W79: 0 | X79: 250000 | Y79: 521550 | Z79: 521550 | AA79: 3s | AB79: =U79*0.5% -> 57950 | AC79: 0.045 | AD79: =U79*AC79 -> 521550 | AE79: =AD79-V79 -> 521550 | AF79: 2 368 000.00 | AG79: 46128 | AH79: Шымкент | AI79: Кредит | AJ79: Стандартное кредитование | AK79: Altyn Bank | AL79: 84 месяца | AM79: 20 | AN79: 0 | AP79: 0 | AQ79: 0 | AR79: 132075299 | AS79: 152900 | AT79: 12136066 | AU79: 77758855033 | AV79: KKZ
A80: 1 | B80: 331 Шымкент ТОО «DCG ONTUSTIK» (KIA) | C80: Soluto | D80: Prestige | E80: H7S4K461B | F80: MXR0AA29XTY901076 | G80: GY1 / Distinct Yellow / желтый | H80: G623 | J80: AUTOT/M | K80: 1368 | L80: 2025 | M80: 1190_292230 | N80: 46113 | O80: Нұрсұлтан Көкежан | R80: ИП "Keruen" | S80: 960103000298 | T80: 7590000 | U80: 7590000 | V80: 0 | W80: 0 | X80: 0 | Y80: 300000 | Z80: 300000 | AA80: 3s | AB80: =U80*0.5% -> 37950 | AC80: 300000 | AD80: =AC80 -> 300000 | AE80: =AD80-V80 -> 300000 | AG80: 46114 | AH80: Шымкент | AI80: Безналичный расчет | AJ80: Безналичный | AK80: Без привлечения кредита | AN80: 0 | AP80: 0 | AQ80: 0 | AT80: 12136068 | AU80: 77028499364 | AV80: KKZ
A81: 1 | B81: 363 Алматы ТОО «DCG ALMATY» (KIA) | C81: Carnival | D81: Luxe+ | E81: HSB8J961J | F81: MX1NB814BTK591313 | G81: ISG / Ivory Silver/Серебро слоновой кости / Серый | H81: D324 | I81: 2WD | J81: AT | K81: 3470 | L81: 2025 | M81: 363_292868 | N81: 46125 | O81: Адема Алибекова | P81: Бабахунов Ришад Сыдыкович | Q81: 820506300329 | T81: 22290000 | U81: 21990000 | V81: 0 | W81: 0 | X81: 300000 | Y81: 1429350 | Z81: 1429350 | AA81: 1s | AB81: =U81*0.5% -> 109950 | AC81: 0.055 | AD81: =U81*AC81 -> 1209450 | AE81: =AD81-V81 -> 1209450 | AF81: 6 800 000.00 | AG81: 46126 | AH81: Алматы | AI81: Кредит | AJ81: Стандартное кредитование | AK81: Altyn Bank | AL81: 48 месяцев | AM81: 30 | AN81: 0 | AP81: 0 | AQ81: 0 | AR81: 132075161 | AS81: 229900 | AT81: 12141014 | AU81: 77017019991 | AV81: САП
A82: 1 | B82: 735 Усть-Каменогорск ТОО «DCG VOSTOK» (KIA) | C82: Sorento 2025 | D82: Luxe | E82: GZW7L961G | F82: MX1RH81DDTK379413 | G82: KLG Steel Gray / Стальной | H82: G2IJ | I82: 4WD | J82: AT | K82: 2497 | L82: 2025 | M82: 735_293652 | N82: 46135 | O82: Азамат Тоқтарбеков | P82: Айтамбаев Нурбол Нурбекович | Q82: 611211300949 | T82: 18390000 | U82: 18390000 | V82: 0 | W82: 0 | X82: 0 | Y82: 1011450 | Z82: 1011450 | AA82: 1s | AB82: =U82*0.5% -> 91950 | AC82: 0.045 | AD82: =U82*AC82 -> 827550 | AE82: =AD82-V82 -> 827550 | AF82: 10 000 000.00 | AG82: 46140 | AH82: Усть-Каменогорск | AI82: Кредит | AJ82: Стандартное кредитование | AK82: Банк ЦентрКредит | AL82: 84 месяца | AM82: 55 | AN82: 0 | AP82: 0 | AQ82: 0 | AR82: 132076190 | AS82: 229900 | AT82: 12145739 | AU82: 77764438855 | AV82: САП
A83: 1 | B83: 1151 Алматы ТОО «DCG Qulja» (KIA) | C83: Sorento 2025 | D83: Comfort | E83: GZW5L961G | F83: MX1RH81DDTK374746 | G83: SWP Snow White Pearl / Белый перламутр | H83: G2IF | I83: 4WD | J83: AT | K83: 2497 | L83: 2025 | M83: 1151_292768 | N83: 46121 | O83: Дайана Калиаскар | P83: Байтенов Ерболат Абдикалиевич | Q83: 920112300165 | T83: 16990000 | U83: 16990000 | V83: 0 | W83: 0 | X83: 0 | Y83: 934450 | Z83: 934450 | AA83: 3s | AB83: =U83*0.5% -> 84950 | AC83: 0.045 | AD83: =U83*AC83 -> 764550 | AE83: =AD83-V83 -> 764550 | AF83: 3 990 000.00 | AG83: 46126 | AH83: Алматы | AI83: Кредит | AJ83: Стандартное кредитование | AK83: МФО Sapa Digital Finance | AL83: 84 месяца | AM83: 23 | AN83: 0 | AP83: 0 | AQ83: 0 | AR83: 132075099 | AS83: 216900 | AT83: 12147766 | AU83: 77778474602 | AV83: САП
A84: 1 | B84: 1151 Алматы ТОО «DCG Qulja» (KIA) | C84: Sorento 2025 | D84: Comfort | E84: GZW5L961G | F84: MX1RH81DDTK376595 | G84: ABP Aurora Black Pearl / Чёрный перламутр | H84: G2IF | I84: 4WD | J84: AT | K84: 2497 | L84: 2025 | M84: 1151_293171 | N84: 46128 | O84: Мади Мынбаев | P84: КУАНДЫКОВ МУХТАР АБДУАЛЫУЛЫ | Q84: 920321300106 | T84: 17290000 | U84: 16990000 | V84: 0 | W84: 0 | X84: 300000 | Y84: 934450 | Z84: 934450 | AA84: 3s | AB84: =U84*0.5% -> 84950 | AC84: 0.045 | AD84: =U84*AC84 -> 764550 | AE84: =AD84-V84 -> 764550 | AF84: 12 000 000.00 | AG84: 46132 | AH84: Алматы | AI84: Кредит | AJ84: Стандартное кредитование | AK84: Береке Банк | AL84: 60 месяцев | AM84: 70 | AN84: 0 | AP84: 0 | AQ84: 0 | AR84: 132075542 | AS84: 216900 | AT84: 12147768 | AU84: 77019289222 | AV84: САП
A85: 1 | B85: 863 Павлодар ТОО «DCG ERTIS» (KIA) | C85: K5 | D85: Comfort | E85: EUS4D6G1U | F85: MXR6AA2D5TY900296 | G85: SWP Snow White Pearl / Белый перламутр | H85: D055 | I85: 2WD | J85: DCT | K85: 1497 | L85: 2025 | M85: 1192_294036 | N85: 46140 | O85: Алишер Сериков | P85: Якименко Оксана Сергеевна | Q85: 800728402226 | T85: 10990000 | U85: 10990000 | V85: 0 | W85: 0 | X85: 0 | Y85: 604450 | Z85: 604450 | AA85: 3s | AB85: =U85*0.5% -> 54950 | AC85: 0.055 | AD85: =U85*AC85 -> 604450 | AE85: =AD85-V85 -> 604450 | AF85: 1 500 000.00 | AG85: 46142 | AH85: Павлодар | AI85: Кредит | AJ85: Стандартное кредитование | AK85: Береке Банк | AL85: 84 месяца | AM85: 13 | AN85: 0 | AO85: 1236 Астана Филиал ТОО «ASTER Автомобили» (KIA) AMQ | AP85: 0 | AQ85: 0 | AR85: 132076638 | AS85: 157900 | AT85: 12155439 | AU85: 77025894830 | AV85: KKZ
A86: 1 | B86: 863 Павлодар ТОО «DCG ERTIS» (KIA) | C86: K5 | D86: Luxe | E86: EUS42JG1J | F86: MXR6AA24XTY900209 | G86: AG2 Graphite Gray / Серый | H86: G155 | I86: 2WD | J86: AUTOT/M | K86: 1975 | L86: 2025 | M86: 1192_292540 | N86: 46119 | O86: ЕРЖАН КАРАМЕНДИНОВ | P86: Баймурунова Гульнара Сабировна | Q86: 760819401430 | T86: 12690000 | U86: 12690000 | V86: 0 | W86: 0 | X86: 0 | Y86: 697950 | Z86: 697950 | AA86: 3s | AB86: =U86*0.5% -> 63450 | AC86: 0.055 | AD86: =U86*AC86 -> 697950 | AE86: =AD86-V86 -> 697950 | AF86: 1 903 500.00 | AG86: 46125 | AH86: Павлодар | AI86: Кредит | AJ86: Стандартное кредитование | AK86: Банк ЦентрКредит | AL86: 60 месяцев | AM86: 15 | AN86: 0 | AP86: 0 | AQ86: 0 | AR86: 132075031 | AT86: 12155440 | AU86: 77777103050 | AV86: KKZ
A87: 1 | B87: 363 Алматы ТОО «DCG ALMATY» (KIA) | C87: K5 | D87: Luxe | E87: EUS42JG1J | F87: MXR6AA242TY900238 | G87: SWP Snow White Pearl / Белый перламутр | H87: G155 | J87: AUTOT/M | K87: 1975 | L87: 2025 | M87: 1169_292303 | N87: 46115 | O87: Азамат Жұмахметов | P87: Болебаев Азат Жумагазыевич | Q87: 921224350049 | T87: 12990000 | U87: 12690000 | V87: 0 | W87: 0 | X87: 300000 | Y87: 752950 | Z87: 752950 | AA87: 1s | AB87: =U87*0.5% -> 63450 | AC87: 0.045 | AD87: =U87*AC87 -> 571050 | AE87: =AD87-V87 -> 571050 | AF87: 1 300 000.00 | AG87: 46118 | AH87: Алматы | AI87: Кредит | AJ87: Стандартное кредитование | AK87: Банк ЦентрКредит | AL87: 84 месяца | AM87: 10 | AN87: 0 | AP87: 0 | AQ87: 0 | AR87: 132074675 | AT87: 12164059 | AU87: 77070191202 | AV87: KKZ
A88: 1 | B88: 1151 Алматы ТОО «DCG Qulja» (KIA) | C88: K5 | D88: Luxe | E88: EUS42JG1J | F88: MXR6AA244TY900208 | G88: AG2 Graphite Gray / Серый | H88: G155 | I88: 2WD | J88: AUTOT/M | K88: 1975 | L88: 2025 | M88: 1173_292945 | N88: 46125 | O88: Ерик Серкешбаев | P88: Тапаев Жаксылык Кенесович | Q88: 760414301735 | T88: 12940000 | U88: 12690000 | V88: 0 | W88: 0 | X88: 250000 | Y88: 697950 | Z88: 697950 | AA88: 3s | AB88: =U88*0.5% -> 63450 | AC88: 0.055 | AD88: =U88*AC88 -> 697950 | AE88: =AD88-V88 -> 697950 | AF88: 10 000 000.00 | AG88: 46128 | AH88: Алматы | AI88: Кредит | AJ88: Стандартное кредитование | AK88: Банк ЦентрКредит | AL88: 84 месяца | AM88: 79 | AN88: 0 | AP88: 0 | AQ88: 0 | AR88: 132075320 | AT88: 12165236 | AU88: 77074990334 | AV88: KKZ
A89: 1 | B89: 1069 Актау TOO «DCG Aktau» (KIA) | C89: Sportage | D89: Luxe | E89: GYWDL9A1K | F89: MX1PV81FDTK021857 | G89: KLG Steel Gray / Стальной | H89: G0P1 | I89: 4WD | J89: AT | K89: 2497 | L89: 2025 | M89: 1069_293210 | N89: 46128 | O89: Тимур Нурибаев | P89: Асанова Светлана Шукирбаевна | Q89: 760227401244 | T89: 13990000 | U89: 13990000 | V89: 0 | W89: 0 | X89: 0 | Y89: 769450 | Z89: 769450 | AA89: 3s | AB89: =U89*0.5% -> 69950 | AC89: 0.055 | AD89: =U89*AC89 -> 769450 | AE89: =AD89-V89 -> 769450 | AF89: 13 990 000.00 | AG89: 46132 | AH89: Актау | AI89: Наличный расчет | AJ89: Наличный расчет | AK89: Без привлечения кредита | AN89: 0 | AP89: 0 | AQ89: 0 | AR89: 132075549 | AS89: 187900 | AT89: 12169811 | AU89: 77016636613 | AV89: САП
A90: 1 | B90: 331 Шымкент ТОО «DCG ONTUSTIK» (KIA) | C90: Soul | D90: Luxe | E90: SKW5D261F | F90: MX1J381EBSK274621 | G90: F1D Clear White / Fusion Black | H90: G904 | I90: 2WD | J90: AT | K90: 1591 | L90: 2025 | M90: 331_293913 | N90: 46139 | O90: Ернар Жайдарбек | P90: Кучкарова Меруерт Барысбековна | Q90: 851219400918 | T90: 12240000 | U90: 11690000 | V90: 0 | W90: 0 | X90: 550000 | Y90: 526050 | Z90: 526050 | AA90: 3s | AB90: =U90*0.5% -> 58450 | AC90: 0.045 | AD90: =U90*AC90 -> 526050 | AE90: =AD90-V90 -> 526050 | AF90: 2 000 000.00 | AG90: 46142 | AH90: Шымкент | AI90: Кредит | AJ90: Стандартное кредитование | AK90: МФО Sapa Digital Finance | AL90: 84 месяца | AM90: 20 | AN90: 0 | AO90: 343 Талдыкорган ТОО «Taldykorgan Auto Group» (KIA) | AP90: 0 | AQ90: 0 | AR90: 132076785 | AS90: 130900 | AT90: 12171459 | AU90: 77087576545 | AV90: САП
A91: 1 | B91: 371 Астана ТОО «DCG ASTANA» (KIA) | C91: Soul | D91: Luxe | E91: SKW5D261F | F91: MX1J381EBSK273139 | G91: F1D Clear White / Fusion Black | H91: G904 | I91: 2WD | J91: AT | K91: 1591 | L91: 2025 | M91: 371_293468 | N91: 46132 | O91: Виктория Чубинец | P91: Галиева Динара Бауыржановна | Q91: 841126450293 | T91: 11940000 | U91: 11690000 | V91: 0 | W91: 0 | X91: 250000 | Y91: 526050 | Z91: 526050 | AA91: 1s | AB91: =U91*0.5% -> 58450 | AC91: 0.045 | AD91: =U91*AC91 -> 526050 | AE91: =AD91-V91 -> 526050 | AF91: 1 200 000.00 | AG91: 46134 | AH91: Астана | AI91: Кредит | AJ91: Стандартное кредитование | AK91: Евразийский банк | AL91: 84 месяца | AM91: 10 | AN91: 0 | AP91: 0 | AQ91: 0 | AR91: 132075831 | AS91: 130900 | AT91: 12171759 | AU91: 77013060678 | AV91: САП
A92: 1 | B92: 363 Алматы ТОО «DCG ALMATY» (KIA) | C92: Sportage | D92: Luxe | E92: GYWD2J61G | F92: MX1PV81DDTK021235 | G92: FSB Modern Black / Черный | H92: G0P1 | I92: 4WD | J92: AT | K92: 1999 | L92: 2025 | M92: 363_292933 | N92: 46125 | O92: Адема Алибекова | P92: Султамуратова Әсия Қанатқызы | Q92: 810928402106 | T92: 13490000 | U92: 13490000 | V92: 0 | W92: 0 | X92: 0 | Y92: 741950 | Z92: 741950 | AA92: 1s | AB92: =U92*0.5% -> 67450 | AC92: 0.045 | AD92: =U92*AC92 -> 607050 | AE92: =AD92-V92 -> 607050 | AF92: 1 349 000.00 | AG92: 46127 | AH92: Алматы | AI92: Льготный кредит | AJ92: Льготное кредитование | AK92: Банк ЦентрКредит | AL92: 84 месяца | AM92: 10 | AN92: 0 | AP92: 0 | AQ92: 0 | AR92: 132075266 | AS92: 181900 | AT92: 12179876 | AU92: 77012881616 | AV92: САП
A93: 1 | B93: 1151 Алматы ТОО «DCG Qulja» (KIA) | C93: Soul | D93: Luxe | E93: SKW5D261F | F93: MX1J381EBTK274171 | G93: KDG Gravity Gray / Серый | H93: G904 | I93: 2WD | J93: AT | K93: 1591 | L93: 2025 | M93: 1151_292967 | N93: 46126 | O93: Амир Мамедов | P93: АТАНБЕКОВА ЛАУРА ДАРУБАЙҚЫЗЫ | Q93: 780618400087 | T93: 11990000 | U93: 11690000 | V93: 0 | W93: 0 | X93: 300000 | Y93: 526050 | Z93: 526050 | AA93: 3s | AB93: =U93*0.5% -> 58450 | AC93: 0.045 | AD93: =U93*AC93 -> 526050 | AE93: =AD93-V93 -> 526050 | AF93: 8 000 000.00 | AG93: 46127 | AH93: Алматы | AI93: Кредит | AJ93: Стандартное кредитование | AK93: МФО Sapa Digital Finance | AL93: 24 месяца | AM93: 67 | AN93: 0 | AP93: 0 | AQ93: 0 | AR93: 132075247 | AS93: 130900 | AT93: 12179887 | AU93: 77011813378 | AV93: САП
A94: 1 | B94: 1151 Алматы ТОО «DCG Qulja» (KIA) | C94: Cerato | D94: Luxe+ | E94: DJS42G61F | F94: MX1F441CBTK006485 | G94: UD Clear White / Белый | H94: G02O | I94: 2WD | J94: AT | K94: 2 | L94: 2025 | M94: 1151_294044 | N94: 46141 | O94: Ерик Серкешбаев | P94: Уәтаев Елнұр Ғизатұлы | Q94: 51025550275 | T94: 10990000 | U94: 10990000 | V94: 0 | W94: 0 | X94: 0 | Y94: 439600 | Z94: 439600 | AA94: 3s | AB94: =U94*0.5% -> 54950 | AC94: 0.04 | AD94: =U94*AC94 -> 439600 | AE94: =AD94-V94 -> 439600 | AG94: 46142 | AH94: Алматы | AI94: Наличный расчет | AJ94: Наличный расчет | AK94: Без привлечения кредита | AN94: 0 | AO94: 363 Алматы ТОО «DCG ALMATY» (KIA) | AP94: 0 | AQ94: 0 | AR94: 132076675 | AT94: 12185769 | AU94: 77786347407 | AV94: САП
A95: 1 | B95: 363 Алматы ТОО «DCG ALMATY» (KIA) | C95: Sportage | D95: Luxe | E95: GYWDL9A1K | F95: MX1PV81FDTK021834 | G95: KLG Steel Gray / Стальной | H95: G0P1 | I95: 4WD | J95: AT | K95: 2497 | L95: 2025 | M95: 363_293276 | N95: 46129 | O95: Азамат Жұмахметов | P95: Алданова Гулбиби Оразхановна | Q95: 801217402300 | T95: 13990000 | U95: 13990000 | V95: 0 | W95: 0 | X95: 0 | Y95: 769450 | Z95: 769450 | AA95: 1s | AB95: =U95*0.5% -> 69950 | AC95: 0.045 | AD95: =U95*AC95 -> 629550 | AE95: =AD95-V95 -> 629550 | AF95: 2 798 000.00 | AG95: 46139 | AH95: Алматы | AI95: Льготный кредит | AJ95: Льготное кредитование | AK95: Fortebank | AL95: 84 месяца | AM95: 20 | AN95: 0 | AP95: 0 | AQ95: 0 | AR95: 132076155 | AS95: 187900 | AT95: 12187607 | AU95: 77071195643 | AV95: САП
A96: 1 | B96: 363 Алматы ТОО «DCG ALMATY» (KIA) | C96: Sportage | D96: Luxe | E96: GYWDL9A1K | F96: MX1PV81FDTK021828 | G96: KLG Steel Gray / Стальной | H96: G0P1 | I96: 4WD | J96: AT | K96: 2497 | L96: 2025 | M96: 363_293019 | N96: 46126 | O96: Адема Алибекова | P96: Жолмурзаев Адилет Нуртасович | Q96: 900416300268 | T96: 14240000 | U96: 13990000 | V96: 0 | W96: 0 | X96: 250000 | Y96: 769450 | Z96: 769450 | AA96: 1s | AB96: =U96*0.5% -> 69950 | AC96: 0.045 | AD96: =U96*AC96 -> 629550 | AE96: =AD96-V96 -> 629550 | AF96: 6 500 000.00 | AG96: 46127 | AH96: Алматы | AI96: Кредит | AJ96: Стандартное кредитование | AK96: Halyk Bank | AL96: 60 месяцев | AM96: 45 | AN96: 0 | AP96: 0 | AQ96: 0 | AR96: 132075261 | AS96: 187900 | AT96: 12187609 | AU96: 77056663670 | AV96: САП
A97: 1 | B97: 363 Алматы ТОО «DCG ALMATY» (KIA) | C97: Cerato | D97: Comfort | E97: DJS4D261F | F97: MX1F3416BTK006548 | G97: UD Clear White / Белый | H97: D0A6 | I97: 2WD | J97: AT | K97: 1591 | L97: 2025 | M97: 363_292459 | N97: 46118 | O97: Абылай Куттыбай | P97: Зайитов Мухлис Мундашович | Q97: 740321301364 | T97: 9990000 | U97: 9990000 | V97: 0 | W97: 0 | X97: 0 | Y97: 399600 | Z97: 399600 | AA97: 1s | AB97: =U97*0.5% -> 49950 | AC97: 0.04 | AD97: =U97*AC97 -> 399600 | AE97: =AD97-V97 -> 399600 | AF97: 9 990 000.00 | AG97: 46122 | AH97: Алматы | AI97: Наличный расчет | AJ97: Наличный расчет | AK97: Без привлечения кредита | AN97: 0 | AP97: 0 | AQ97: 0 | AR97: 132075007 | AT97: 12187638 | AU97: 77012451110 | AV97: САП
A98: 1 | B98: 1151 Алматы ТОО «DCG Qulja» (KIA) | C98: Sportage | D98: Luxe | E98: GYWDL9A1K | F98: MX1PV81FDTK021897 | G98: KDG Gravity Gray / Серый | H98: G0P1 | I98: 4WD | J98: AT | K98: 2497 | L98: 2025 | M98: 1151_293213 | N98: 46129 | O98: Ерик Серкешбаев | P98: Турдиева Асемгул Кайнелденовна | Q98: 770706401329 | T98: 13990000 | U98: 13990000 | V98: 0 | W98: 0 | X98: 0 | Y98: 769450 | Z98: 769450 | AA98: 3s | AB98: =U98*0.5% -> 69950 | AC98: 0.055 | AD98: =U98*AC98 -> 769450 | AE98: =AD98-V98 -> 769450 | AF98: 3 990 000.00 | AG98: 46135 | AH98: Алматы | AI98: Льготный кредит | AJ98: Льготное кредитование | AK98: Halyk Bank | AL98: 84 месяца | AM98: 25 | AN98: 0 | AP98: 0 | AQ98: 0 | AR98: 132075953 | AS98: 187900 | AT98: 12189860 | AU98: 77472648252 | AV98: САП
A99: 1 | B99: 1151 Алматы ТОО «DCG Qulja» (KIA) | C99: Sportage | D99: Luxe | E99: GYWDL9A1K | F99: MX1PV81FDTK021898 | G99: KDG Gravity Gray / Серый | H99: G0P1 | I99: 4WD | J99: AT | K99: 2497 | L99: 2025 | M99: 1151_293530 | N99: 46133 | O99: Ерик Серкешбаев | P99: Айдосқызы Айша | Q99: 509601956 | T99: 13990000 | U99: 13990000 | V99: 0 | W99: 0 | X99: 0 | Y99: 769450 | Z99: 769450 | AA99: 3s | AB99: =U99*0.5% -> 69950 | AC99: 0.055 | AD99: =U99*AC99 -> 769450 | AE99: =AD99-V99 -> 769450 | AF99: 1 400 000.00 | AG99: 46136 | AH99: Алматы | AI99: Кредит | AJ99: Стандартное кредитование | AK99: Банк ЦентрКредит | AL99: 84 месяца | AM99: 10 | AN99: 0 | AP99: 0 | AQ99: 0 | AR99: 132076011 | AS99: 187900 | AT99: 12189870 | AU99: 77478447253 | AV99: САП
A100: 1 | B100: 363 Алматы ТОО «DCG ALMATY» (KIA) | C100: Cerato | D100: Luxe+ | E100: DJS42G61F | F100: MX1F441CBSK003698 | G100: KDG Gravity Gray / Серый | H100: G02O | I100: 2WD | J100: AT | K100: 2 | L100: 2025 | M100: 363_293689 | N100: 46135 | O100: Даур Құттыбай | P100: Тұрғанбаев Мерей Мейрамханұлы | Q100: 940917301831 | T100: 11290000 | U100: 10990000 | V100: 0 | W100: 0 | X100: 300000 | Y100: 439600 | Z100: 439600 | AA100: 1s | AB100: =U100*0.5% -> 54950 | AC100: 0.04 | AD100: =U100*AC100 -> 439600 | AE100: =AD100-V100 -> 439600 | AF100: 1 130 000.00 | AG100: 46140 | AH100: Алматы | AI100: Кредит | AJ100: Стандартное кредитование | AK100: МФО Sapa Digital Finance | AL100: 84 месяца | AM100: 10 | AN100: 0 | AP100: 0 | AQ100: 0 | AR100: 132076187 | AT100: 12197443 | AU100: 77767769595 | AV100: САП
...

Sheet Киа
A1: Кол-во | B1: Название ДЦ | C1: Модель KIA | D1: Комплектация KIA | E1: Код модели KIA | F1: VIN KZ | G1: Цвет УС KIA | H1: Модификация | I1: Привод | J1: КПП | K1: Объем двигателя, см3 | L1: Год выпуска | M1: Номер договора | N1: Дата договора | O1: Ответственный | P1: ФИО | Q1: Контакт: ИИН/БИН | R1: Компания: Название компании | S1: Компания: БИН | T1: Цена реализации | U1: Рекомендуемая розничная цена | V1: Сумма скидки | W1: Скидка дистрибуции | X1: Стоимость доп. оборудования | Y1: Максимальное вознаграждение дилера | Z1: Вознаграждение без скидки | AA1: 1s/3s | AB1: % | AC1: Маржа | AD1: Маржа после скидок | AE1: Сумма предоплаты, тенге | AF1: Дата подписания акта п/п | AG1: Место реализации (город) | AH1: !Тип продажи а/м | AI1: Способ приобретения | AJ1: Кредит в банке | AK1: Срок кредита в месяцах | AL1: Размер первоначального взноса по кредиту (В процентах) | AM1: Число попаданий на замечания | AN1: Название ДЦ. откуда забрали машину | AO1: Вознаграждение дилера (за перемещённую машину) | AP1: Компенсация дилера | AQ1: Номер карты Технической поддержки Litro | AR1: Дополнительная компенсация дилера | AS1: ID | AT1: Номер телефона | AU1: Завод производитель
A2: 1 | B2: 331 Шымкент ТОО «DCG ONTUSTIK» (KIA) | C2: Seltos | D2: Style | E2: THW52G61Q | F2: MX1ER81AKRK673769 | G2: B3A Neptune Blue / Синий | H2: G0BQ | I2: 4WD | J2: AT | K2: 1999 | L2: 2024 | M2: 331_292944 | N2: 46125 | O2: Ернар Жайдарбек | P2: Селифанова Инна Викторовна | Q2: 780928402396 | T2: 12990000 | U2: 12990000 | V2: 0 | W2: 0 | X2: 0 | Y2: 0 | Z2: 0 | AA2: 3s | AB2: 0.045 | AC2: =U2*AB2 -> 584550 | AD2: =AC2-V2 -> 584550 | AF2: 46126.917 | AG2: Шымкент | AH2: Безналичный расчет | AI2: Безналичный | AJ2: Без привлечения кредита | AM2: 0 | AO2: 0 | AP2: 0 | AQ2: 132075139 | AS2: 10448600 | AT2: 77015603204 | AU2: САП
A3: 1 | B3: 331 Шымкент ТОО «DCG ONTUSTIK» (KIA) | C3: Sportage | D3: X-Line+ | E3: GYWDL9A1K | F3: MX1PX81FDRK011802 | G3: UD Clear White / Белый | H3: H0D1 | I3: 4WD | J3: AT | K3: 2497 | L3: 2024 | M3: 331_294098 | N3: 46141 | O3: Абдукарим Абдукаим | P3: Ройтман Рустам | Q3: 760211302101 | T3: 15784000 | U3: 16190000 | V3: 216000 | W3: 190000 | X3: 0 | Y3: 0 | Z3: -216000 | AA3: 3s | AB3: 0.055 | AC3: =U3*AB3 -> 890450 | AD3: =AC3-V3 -> 674450 | AF3: 46142 | AG3: Шымкент | AH3: Безналичный расчет | AI3: Безналичный | AJ3: Без привлечения кредита | AM3: 0 | AO3: 0 | AP3: 0 | AQ3: 132076748 | AS3: 10448618 | AT3: 77077000991 | AU3: САП
A4: 1 | B4: 331 Шымкент ТОО «DCG ONTUSTIK» (KIA) | C4: Ceed | D4: Luxe | E4: J7S6D261F | F4: MX1H2516BSK236164 | G4: H8G Penta Metal / Серый | H4: D2U5 | I4: 2WD | J4: AT | K4: 0 | L4: 2024 | M4: 331_292604 | N4: 46119 | O4: Жандаулет Жұмалиев | P4: Кредина Юлия Александровна | Q4: 871006401238 | T4: 8890000 | U4: 8890000 | V4: 0 | W4: 0 | X4: 0 | Y4: 0 | Z4: 0 | AA4: 3s | AB4: 0.045 | AC4: =U4*AB4 -> 400050 | AD4: =AC4-V4 -> 400050 | AF4: 46133 | AG4: Шымкент | AH4: Безналичный расчет | AI4: Безналичный | AJ4: Без привлечения кредита | AM4: 0 | AO4: 0 | AP4: 0 | AQ4: 132075639 | AR4: 129900 | AS4: 10685796 | AT4: 77058500030 | AU4: САП
A5: 1 | B5: 331 Шымкент ТОО «DCG ONTUSTIK» (KIA) | C5: Ceed | D5: Comfort | E5: J7S6D261F | F5: MX1H1516BSK239964 | G5: WD Casa White / Белый | H5: S10W | I5: 2WD | J5: AT | K5: 1591 | L5: 2025 | M5: 331_292796 | N5: 46122 | O5: Қаныбек Рахманәлі | P5: Утегенова Кулзат Шаймовна | Q5: 670912402356 | T5: 9690000 | U5: 9690000 | V5: 0 | W5: 0 | X5: 0 | Y5: 436050 | Z5: 436050 | AA5: 3s | AB5: 0.045 | AC5: =U5*AB5 -> 436050 | AD5: =AC5-V5 -> 436050 | AE5: 2 590 000.00 | AF5: 46128 | AG5: Шымкент | AH5: Кредит | AI5: Льготное кредитование | AJ5: Halyk Bank | AK5: 84 месяца | AL5: 20 | AM5: 0 | AO5: 0 | AP5: 0 | AQ5: 132075335 | AR5: 122900 | AS5: 11010655 | AT5: 77710199162 | AU5: САП
A6: 1 | B6: 331 Шымкент ТОО «DCG ONTUSTIK» (KIA) | C6: Seltos | D6: Luxe | E6: THW52G61V | F6: MX1ER81AESK765870 | G6: KLG Steel Gray / Стальной | H6: G0BM | I6: 2WD | J6: AT | K6: 1999 | L6: 2025 | M6: 331_293611 | N6: 46134 | O6: Абылайхан Нагибек | P6: Файзиев Елнур Хамзаевич | Q6: 840317301462 | T6: 11990000 | U6: 11990000 | V6: 0 | W6: 0 | X6: 0 | Y6: 634050 | Z6: 634050 | AA6: 3s | AB6: 0.045 | AC6: =U6*AB6 -> 539550 | AD6: =AC6-V6 -> 539550 | AF6: 46135 | AG6: Шымкент | AH6: Безналичный расчет | AI6: Безналичный | AJ6: Без привлечения кредита | AM6: 0 | AO6: 0 | AP6: 0 | AQ6: 132075931 | AR6: 153900 | AS6: 11037821 | AT6: 77077064040 | AU6: САП
A7: 1 | B7: 863 Павлодар ТОО «DCG ERTIS» (KIA) | C7: Ceed | D7: Luxe | E7: J7S6D261F | F7: MX1H2516BSK247884 | G7: H8G Penta Metal / Серый | H7: D2U5 | I7: 2WD | J7: AT | K7: 0 | L7: 2025 | M7: 863_293026 | N7: 46126 | O7: ЕРЖАН КАРАМЕНДИНОВ | P7: Толеу Олжас Жантасулы | Q7: 930224350672 | T7: 10690000 | U7: 10690000 | V7: 0 | W7: 0 | X7: 0 | Y7: 481050 | Z7: 481050 | AA7: 3s | AB7: 0.045 | AC7: =U7*AB7 -> 481050 | AD7: =AC7-V7 -> 481050 | AE7: 10 690 000.00 | AF7: 46126 | AG7: Павлодар | AH7: Наличный расчет | AI7: Наличный расчет | AJ7: Без привлечения кредита | AL7: 100 | AM7: 0 | AO7: 0 | AP7: 0 | AQ7: 132075156 | AR7: 129900 | AS7: 11090787 | AT7: 77471136340 | AU7: САП
A8: 1 | B8: 363 Алматы ТОО «DCG ALMATY» (KIA) | C8: Ceed SW | D8: Comfort | E8: J7W5D261F | F8: MX1H4816BSK239650 | G8: HW2 Deluxe White / Белый перламутр | H8: K0OP | I8: 2WD | J8: AT | K8: 1591 | L8: 2025 | M8: 363_292472 | N8: 46118 | O8: Бахытжан Смагулов | P8: Нурмухамет Ербол | Q8: 890524301239 | T8: 10990000 | U8: 10990000 | V8: 0 | W8: 0 | X8: 0 | Y8: 494550 | Z8: 494550 | AA8: 1s | AB8: 0.045 | AC8: =U8*AB8 -> 494550 | AD8: =AC8-V8 -> 494550 | AE8: 10 990 000.00 | AF8: 46120 | AG8: Алматы | AH8: Наличный расчет | AI8: Наличный расчет | AJ8: Без привлечения кредита | AM8: 0 | AO8: 0 | AP8: 0 | AQ8: 132074818 | AR8: 127900 | AS8: 11583852 | AT8: 77777765777 | AU8: САП
A9: 1 | B9: 331 Шымкент ТОО «DCG ONTUSTIK» (KIA) | C9: Seltos | D9: Comfort | E9: THW52G61V | F9: MX1EP81AESK776725 | G9: KDG Gravity Gray / Серый | H9: D395 | I9: 2WD | J9: AT | K9: 1999 | L9: 2025 | M9: 331_294107 | N9: 46141 | O9: Арман Сабыров | P9: Рахимжанов Булат Мырзахметович | Q9: 680127302453 | T9: 10990000 | U9: 10990000 | V9: 0 | W9: 0 | X9: 0 | Y9: 494550 | Z9: 494550 | AA9: 3s | AB9: 0.045 | AC9: =U9*AB9 -> 494550 | AD9: =AC9-V9 -> 494550 | AE9: 2 198 000.00 | AF9: 46142 | AG9: Шымкент | AH9: Кредит | AI9: Стандартное кредитование | AJ9: Halyk Bank | AK9: 84 месяца | AL9: 20 | AM9: 0 | AN9: 215 Шымкент TOO «NOMAD MOTORS SHYM» (KIA) | AO9: 0 | AP9: 0 | AQ9: 132076704 | AR9: 145900 | AS9: 11608275 | AT9: 77754060101 | AU9: САП
A10: 1 | B10: 331 Шымкент ТОО «DCG ONTUSTIK» (KIA) | C10: Sorento 2025 | D10: Comfort | E10: GZW5L961G | F10: MX1RH81DDSK343433 | G10: AGT Graphite Gray / Серый | H10: G2IF | I10: 4WD | J10: AT | K10: 2497 | L10: 2025 | M10: 331_292593 | N10: 46119 | O10: Нұрсұлтан Көкежан | P10: Сахыбекова Айнур Жаксылыковна | Q10: 760702400654 | T10: 17240000 | U10: 16990000 | V10: 0 | W10: 0 | X10: 250000 | Y10: 934450 | Z10: 934450 | AA10: 3s | AB10: 0.045 | AC10: =U10*AB10 -> 764550 | AD10: =AC10-V10 -> 764550 | AE10: 3 000 000.00 | AF10: 46127 | AG10: Шымкент | AH10: Кредит | AI10: Стандартное кредитование | AJ10: Банк ЦентрКредит | AK10: 84 месяца | AL10: 20 | AM10: 0 | AN10: 365 Тараз ТОО «DCGTARAZ» (KIA) | AO10: 0 | AP10: 0 | AR10: 216900 | AS10: 11608558 | AT10: 77073589208 | AU10: САП
A11: 1 | B11: 331 Шымкент ТОО «DCG ONTUSTIK» (KIA) | C11: Cerato | D11: Comfort | E11: DJS4D261F | F11: MX1F3416BSK003073 | G11: KLG Steel Gray / Стальной | H11: D0A6 | I11: 2WD | J11: AT | K11: 1591 | L11: 2025 | M11: 331_292471 | N11: 46118 | O11: Абылайхан Нагибек | P11: Жонеуов Канатбек Жаксылыкбаевич | Q11: 851103301572 | T11: 10310000 | U11: 9990000 | V11: 0 | W11: 0 | X11: 320000 | Y11: 399600 | Z11: 399600 | AA11: 3s | AB11: 0.04 | AC11: =U11*AB11 -> 399600 | AD11: =AC11-V11 -> 399600 | AE11: 1 031 000.00 | AF11: 46120 | AG11: Шымкент | AH11: Кредит | AI11: Стандартное кредитование | AJ11: Банк ЦентрКредит | AK11: 84 месяца | AL11: 10 | AM11: 0 | AO11: 0 | AP11: 0 | AQ11: 132074816 | AS11: 11608876 | AT11: 77076840585 | AU11: САП
A12: 1 | B12: 735 Усть-Каменогорск ТОО «DCG VOSTOK» (KIA) | C12: K5 | D12: Prestige | E12: EUS42JG1J | F12: MX16A414BSK044694 | G12: SWP Snow White Pearl / Белый перламутр | H12: G156 | I12: 2WD | J12: AT | K12: 1975 | L12: 2025 | M12: 735_293367 | N12: 46131 | O12: Дарын Әмірбеков | P12: Болатов Алмас Болатұлы | Q12: 950309351468 | T12: 14240000 | U12: 13990000 | V12: 0 | W12: 0 | X12: 250000 | Y12: 769450 | Z12: 769450 | AA12: 1s | AB12: 0.045 | AC12: =U12*AB12 -> 629550 | AD12: =AC12-V12 -> 629550 | AE12: 2 848 000.00 | AF12: 46135 | AG12: Усть-Каменогорск | AH12: Кредит | AI12: Стандартное кредитование | AJ12: Halyk Bank | AK12: 84 месяца | AL12: 20 | AM12: 0 | AO12: 0 | AP12: 0 | AQ12: 132075936 | AR12: 196900 | AS12: 11620509 | AT12: 77027679437 | AU12: САП
A13: 1 | B13: 365 Тараз ТОО «DCGTARAZ» (KIA) | C13: Ceed | D13: Comfort | E13: J7S6D261F | F13: MX1H1516BSK253995 | G13: H8G Penta Metal / Серый | H13: S10W | I13: 2WD | J13: AT | K13: 1591 | L13: 2025 | M13: 365_292181 | N13: 46112 | O13: Тұрар Жеңіс | P13: Сарбаев Ескендір Жұмабайұлы | Q13: 940124301602 | T13: 10240000 | U13: 9690000 | V13: 0 | W13: 0 | X13: 550000 | Y13: 436050 | Z13: 436050 | AA13: 1s | AB13: 0.045 | AC13: =U13*AB13 -> 436050 | AD13: =AC13-V13 -> 436050 | AE13: 3 500 000.00 | AF13: 46119 | AG13: Тараз | AH13: Кредит | AI13: Стандартное кредитование | AJ13: Евразийский банк | AK13: 84 месяца | AL13: 35 | AM13: 0 | AN13: 331 Шымкент ТОО «DCG ONTUSTIK» (KIA) | AO13: 0 | AP13: 0 | AQ13: 132074730 | AR13: 122900 | AS13: 11704211 | AT13: 77075958349 | AU13: САП
A14: 1 | B14: 863 Павлодар ТОО «DCG ERTIS» (KIA) | C14: Seltos | D14: Luxe | E14: THW52G61V | F14: MX1ER81AESK791864 | G14: KDG Gravity Gray / Серый | H14: G0BM | I14: 2WD | J14: AT | K14: 1999 | L14: 2025 | M14: 863_293237 | N14: 46129 | O14: Алишер Сериков | P14: Сон Виталий Валерьевич | Q14: 820320350314 | T14: 11990000 | U14: 11990000 | V14: 0 | W14: 0 | X14: 0 | Y14: 634050 | Z14: 634050 | AA14: 3s | AB14: 0.045 | AC14: =U14*AB14 -> 539550 | AD14: =AC14-V14 -> 539550 | AE14: 2 398 000.00 | AF14: 46135 | AG14: Павлодар | AH14: Кредит | AI14: Льготное кредитование | AJ14: Halyk Bank | AK14: 84 месяца | AL14: 20 | AM14: 0 | AO14: 0 | AP14: 0 | AQ14: 132075928 | AR14: 153900 | AS14: 11720930 | AT14: 77015520128 | AU14: САП
A15: 1 | B15: 1151 Алматы ТОО «DCG Qulja» (KIA) | C15: Seltos | D15: Luxe | E15: THW52G61V | F15: MX1ER81AESK792400 | G15: SWP Snow White Pearl / Белый перламутр | H15: G0BM | I15: 2WD | J15: AT | K15: 1999 | L15: 2025 | M15: 1151_293792 | N15: 46140 | O15: Мади Мынбаев | P15: БЕРДЫБАЕВ МУРАТ ЕГИЗБАЕВИЧ | Q15: 670608301765 | T15: 11990000 | U15: 11990000 | V15: 0 | W15: 0 | X15: 0 | Y15: 634050 | Z15: 634050 | AA15: 3s | AB15: 0.045 | AC15: =U15*AB15 -> 539550 | AD15: =AC15-V15 -> 539550 | AF15: 46142 | AG15: Алматы | AH15: Наличный расчет | AI15: Наличный расчет | AJ15: Без привлечения кредита | AM15: 0 | AN15: 331 Шымкент ТОО «DCG ONTUSTIK» (KIA) | AO15: 0 | AP15: 0 | AR15: 153900 | AS15: 11720969 | AT15: 77025388525 | AU15: САП
A16: 1 | B16: 365 Тараз ТОО «DCGTARAZ» (KIA) | C16: Seltos | D16: Luxe | E16: THW52G61V | F16: MX1ER81AESK790601 | G16: FSB Modern Black / Черный | H16: G0BM | I16: 2WD | J16: AT | K16: 1999 | L16: 2025 | M16: 365_293027 | N16: 46126 | O16: Сұлтан Пойызбаев | P16: Мамышева Бекзат Бауржановна | Q16: 861106400453 | T16: 11990000 | U16: 11990000 | V16: 0 | W16: 0 | X16: 0 | Y16: 634050 | Z16: 634050 | AA16: 1s | AB16: 0.045 | AC16: =U16*AB16 -> 539550 | AD16: =AC16-V16 -> 539550 | AE16: 2 398 000.00 | AF16: 46133 | AG16: Тараз | AH16: Кредит | AI16: Льготное кредитование | AJ16: Halyk Bank | AK16: 84 месяца | AL16: 20 | AM16: 0 | AO16: 0 | AP16: 0 | AQ16: 132075670 | AR16: 153900 | AS16: 11721007 | AT16: 77011301532 | AU16: САП
A17: 1 | B17: 1151 Алматы ТОО «DCG Qulja» (KIA) | C17: K5 | D17: Prestige | E17: EUS42JG1J | F17: MX16A414BSK045226 | G17: AG2 Graphite Gray / Серый | H17: G156 | I17: 2WD | J17: AT | K17: 1975 | L17: 2025 | M17: 1151_292671 | N17: 46120 | O17: НУРСУЛТАН КУРПЕТАЕВ | P17: Елюбаев Асхат Болатович | Q17: 931031300644 | T17: 14390000 | U17: 13990000 | V17: 0 | W17: 0 | X17: 400000 | Y17: 769450 | Z17: 769450 | AA17: 3s | AB17: 0.055 | AC17: =U17*AB17 -> 769450 | AD17: =AC17-V17 -> 769450 | AE17: 1 439 000.00 | AF17: 46127 | AG17: Алматы | AH17: Кредит | AI17: Льготное кредитование | AJ17: Банк ЦентрКредит | AK17: 84 месяца | AL17: 10 | AM17: 0 | AN17: 343 Талдыкорган ТОО «Taldykorgan Auto Group» (KIA) | AO17: 0 | AP17: 0 | AQ17: 132075227 | AR17: 196900 | AS17: 11722414 | AT17: 77017227200 | AU17: САП
A18: 1 | B18: 863 Павлодар ТОО «DCG ERTIS» (KIA) | C18: K5 | D18: Prestige | E18: EUS42JG1J | F18: MX16A414BSK045214 | G18: AG2 Graphite Gray / Серый | H18: G156 | I18: 2WD | J18: AT | K18: 1975 | L18: 2025 | M18: 863_293722 | N18: 46136 | O18: КАНАТ АЛЬЖАНОВ | P18: Сатвалдинов Айтуган Закирьянович | Q18: 660124300308 | T18: 13990000 | U18: 13990000 | V18: 0 | W18: 0 | X18: 0 | Y18: 769450 | Z18: 769450 | AA18: 3s | AB18: 0.055 | AC18: =U18*AB18 -> 769450 | AD18: =AC18-V18 -> 769450 | AE18: 11 000 000.00 | AF18: 46142 | AG18: Павлодар | AH18: Кредит | AI18: Стандартное кредитование | AJ18: Банк ЦентрКредит | AK18: 36 месяцев | AL18: 79 | AM18: 0 | AO18: 0 | AP18: 0 | AQ18: 132076523 | AR18: 196900 | AS18: 11724906 | AT18: 77778640891 | AU18: САП
A19: 1 | B19: 1151 Алматы ТОО «DCG Qulja» (KIA) | C19: Sportage | D19: Luxe | E19: GYWD2J61G | F19: MX1PV81DDSK016882 | G19: FSB Modern Black / Черный | H19: G0P1 | I19: 4WD | J19: AT | K19: 1999 | L19: 2025 | M19: 1151_293318 | N19: 46132 | O19: Дайана Калиаскар | P19: ЕРБОЛАТОВА ДАНА РИШАДОВНА | Q19: 960516450532 | T19: 13490000 | U19: 13490000 | V19: 0 | W19: 0 | X19: 0 | Y19: 741950 | Z19: 741950 | AA19: 3s | AB19: 0.055 | AC19: =U19*AB19 -> 741950 | AD19: =AC19-V19 -> 741950 | AE19: 2 690 000.00 | AF19: 46139 | AG19: Алматы | AH19: Льготный кредит | AI19: Льготное кредитование | AJ19: Банк ЦентрКредит | AK19: 84 месяца | AL19: 19 | AM19: 0 | AN19: 363 Алматы ТОО «DCG ALMATY» (KIA) | AO19: 0 | AP19: 0 | AQ19: 132076104 | AR19: 181900 | AS19: 11740393 | AT19: 77054991469 | AU19: САП
A20: 1 | B20: 371 Астана ТОО «DCG ASTANA» (KIA) | C20: K5 | D20: Prestige | E20: EUS42JG1J | F20: MX16A414BSK045168 | G20: ABP Aurora Black Pearl / Чёрный перламутр | H20: G156 | I20: 2WD | J20: AT | K20: 1975 | L20: 2025 | M20: 371_292248 | N20: 46114 | O20: Даурен Манкулов | P20: Музафаров Дархан Шарафиденович | Q20: 920708350552 | T20: 13990000 | U20: 13990000 | V20: 0 | W20: 0 | X20: 0 | Y20: 769450 | Z20: 769450 | AA20: 1s | AB20: 0.045 | AC20: =U20*AB20 -> 629550 | AD20: =AC20-V20 -> 629550 | AE20: 7 000 000.00 | AF20: 46125 | AG20: Астана | AH20: Кредит | AI20: Стандартное кредитование | AJ20: Береке Банк | AK20: 84 месяца | AL20: 50 | AM20: 0 | AO20: 0 | AP20: 0 | AQ20: 132075060 | AR20: 196900 | AS20: 11741552 | AT20: 77055882200 | AU20: САП
A21: 1 | B21: 371 Астана ТОО «DCG ASTANA» (KIA) | C21: Cerato | D21: Luxe+ | E21: DJS4D261F | F21: MX1F4416BSK003629 | G21: UD Clear White / Белый | H21: G02O | I21: 2WD | J21: AT | K21: 1591 | L21: 2025 | M21: 371_292337 | N21: 46116 | O21: Жансерик Туркменов | P21: Негделхан Макпал | Q21: 900313451195 | T21: 10490000 | U21: 10490000 | V21: 0 | W21: 0 | X21: 0 | Y21: 419600 | Z21: 419600 | AA21: 1s | AB21: 0.04 | AC21: =U21*AB21 -> 419600 | AD21: =AC21-V21 -> 419600 | AE21: 7 394 228.00 | AF21: 46119 | AG21: Астана | AH21: Кредит | AI21: Стандартное кредитование | AJ21: Банк ЦентрКредит | AK21: 84 месяца | AL21: 75 | AM21: 0 | AO21: 0 | AP21: 0 | AQ21: 132074721 | AS21: 11748607 | AT21: 77752940222 | AU21: САП
A22: 1 | B22: 331 Шымкент ТОО «DCG ONTUSTIK» (KIA) | C22: Cerato | D22: Comfort | E22: DJS4D261F | F22: MX1F3416BSK003954 | G22: KLG Steel Gray / Стальной | H22: D0A6 | I22: 2WD | J22: AT | K22: 1591 | L22: 2025 | M22: 331_291802 | N22: 46109 | O22: Арман Сабыров | P22: Усманов Максат Заркинович | Q22: 850818303157 | T22: 10540000 | U22: 9990000 | V22: 0 | W22: 0 | X22: 550000 | Y22: 399600 | Z22: 399600 | AA22: 3s | AB22: 0.04 | AC22: =U22*AB22 -> 399600 | AD22: =AC22-V22 -> 399600 | AE22: 2 000 000.00 | AF22: 46120 | AG22: Шымкент | AH22: Кредит | AI22: Стандартное кредитование | AJ22: МФО Sapa Digital Finance | AK22: 84 месяца | AL22: 10 | AM22: 0 | AN22: 215 Шымкент TOO «NOMAD MOTORS SHYM» (KIA) | AO22: 0 | AP22: 0 | AQ22: 132074841 | AS22: 11754055 | AT22: 77780568595 | AU22: САП
A23: 1 | B23: 863 Павлодар ТОО «DCG ERTIS» (KIA) | C23: K5 | D23: Prestige | E23: EUS42JG1J | F23: MX16A414BSK045429 | G23: ABP Aurora Black Pearl / Чёрный перламутр | H23: G156 | I23: 2WD | J23: AT | K23: 1975 | L23: 2025 | M23: 863_293012 | N23: 46126 | O23: ЕРЖАН КАРАМЕНДИНОВ | P23: Шаймырза Мадияр Нуржанулы | Q23: 991124350117 | T23: 13990000 | U23: 13990000 | V23: 0 | W23: 0 | X23: 0 | Y23: 769450 | Z23: 769450 | AA23: 3s | AB23: 0.055 | AC23: =U23*AB23 -> 769450 | AD23: =AC23-V23 -> 769450 | AE23: 6 000 000.00 | AF23: 46129 | AG23: Павлодар | AH23: Кредит | AI23: Стандартное кредитование | AJ23: Altyn Bank | AK23: 84 месяца | AL23: 43 | AM23: 0 | AO23: 0 | AP23: 0 | AQ23: 132075411 | AR23: 196900 | AS23: 11768708 | AT23: 77471912805 | AU23: САП
A24: 1 | B24: 331 Шымкент ТОО «DCG ONTUSTIK» (KIA) | C24: K5 | D24: Prestige | E24: EUS42JG1J | F24: MX16A414BSK045492 | G24: SWP Snow White Pearl / Белый перламутр | H24: G156 | I24: 2WD | J24: AT | K24: 1975 | L24: 2025 | M24: 331_292523 | N24: 46118 | O24: Абылайхан Нагибек | P24: Аширова Гулмира Барзуовна | Q24: 681230400802 | T24: 13990000 | U24: 13990000 | V24: 0 | W24: 0 | X24: 0 | Y24: 769450 | Z24: 769450 | AA24: 3s | AB24: 0.055 | AC24: =U24*AB24 -> 769450 | AD24: =AC24-V24 -> 769450 | AF24: 46120 | AG24: Шымкент | AH24: Безналичный расчет | AI24: Безналичный | AJ24: Без привлечения кредита | AM24: 0 | AO24: 0 | AP24: 0 | AQ24: 132074716 | AR24: 196900 | AS24: 11774590 | AT24: 77780506870 | AU24: САП
A25: 1 | B25: 371 Астана ТОО «DCG ASTANA» (KIA) | C25: Cerato | D25: Luxe+ | E25: DJS4D261F | F25: MX1F4416BSK004210 | G25: UD Clear White / Белый | H25: G02O | I25: 2WD | J25: AT | K25: 1591 | L25: 2025 | M25: 371_293244 | N25: 46129 | O25: Артур Пак | P25: Жунусов Алихан Жасуланович | Q25: 901226350393 | T25: 10740000 | U25: 10490000 | V25: 0 | W25: 0 | X25: 250000 | Y25: 419600 | Z25: 419600 | AA25: 1s | AB25: 0.04 | AC25: =U25*AB25 -> 419600 | AD25: =AC25-V25 -> 419600 | AE25: 5 250 000.00 | AF25: 46136 | AG25: Астана | AH25: Кредит | AI25: Стандартное кредитование | AJ25: Евразийский банк | AK25: 84 месяца | AL25: 50 | AM25: 0 | AO25: 0 | AP25: 0 | AQ25: 132075977 | AS25: 11785166 | AT25: 77011057917 | AU25: САП
A26: 1 | B26: 735 Усть-Каменогорск ТОО «DCG VOSTOK» (KIA) | C26: K5 | D26: Luxe | E26: EUS42JG1J | F26: MX16A414BSK045131 | G26: AG2 Graphite Gray / Серый | H26: G155 | J26: AT | K26: 1975 | L26: 2025 | M26: 735_293887 | N26: 46139 | O26: Максим Косихин | P26: Мендыбаева Салтанат Сайлаугазовна | Q26: 780806402789 | T26: 12690000 | U26: 12690000 | V26: 0 | W26: 0 | X26: 0 | Y26: 697950 | Z26: 697950 | AA26: 1s | AB26: 0.045 | AC26: =U26*AB26 -> 571050 | AD26: =AC26-V26 -> 571050 | AE26: 12 690 000.00 | AF26: 46140 | AG26: Усть-Каменогорск | AH26: Безналичный расчет | AI26: Безналичный | AJ26: Без привлечения кредита | AM26: 0 | AN26: 381 Allur Auto Group KIA | AO26: 0 | AP26: 0 | AQ26: 132076195 | AS26: 11792267 | AT26: 77051205357 | AU26: САП
A27: 1 | B27: 331 Шымкент ТОО «DCG ONTUSTIK» (KIA) | C27: Ceed | D27: Comfort | E27: J7S6D261F | F27: MX1H1516BSK257863 | G27: HW2 Deluxe White / Белый перламутр | H27: S10W | I27: 2WD | J27: AT | K27: 1591 | L27: 2025 | M27: 331_292503 | N27: 46118 | O27: Ернар Жайдарбек | P27: Онласбеков Алмас Атирханович | Q27: 830223302676 | T27: 9690000 | U27: 9690000 | V27: 0 | W27: 0 | X27: 0 | Y27: 436050 | Z27: 436050 | AA27: 3s | AB27: 0.045 | AC27: =U27*AB27 -> 436050 | AD27: =AC27-V27 -> 436050 | AF27: 46119 | AG27: Шымкент | AH27: Безналичный расчет | AI27: Безналичный | AJ27: Без привлечения кредита | AM27: 0 | AO27: 0 | AP27: 0 | AQ27: 132074728 | AR27: 122900 | AS27: 11802657 | AT27: 77717951777 | AU27: САП
A28: 1 | B28: 735 Усть-Каменогорск ТОО «DCG VOSTOK» (KIA) | C28: Ceed SW | D28: Comfort | E28: J7W5D261F | F28: MX1H4816BSK253924 | G28: HW2 Deluxe White / Белый перламутр | H28: K0OP | I28: 2WD | J28: AT | K28: 1591 | L28: 2025 | M28: 735_293260 | N28: 46129 | O28: Азамат Тоқтарбеков | P28: Әбиев Расул Қырықбайұлы | Q28: 40216550843 | T28: 11240000 | U28: 10990000 | V28: 0 | W28: 0 | X28: 250000 | Y28: 494550 | Z28: 494550 | AA28: 1s | AB28: 0.045 | AC28: =U28*AB28 -> 494550 | AD28: =AC28-V28 -> 494550 | AE28: 1 273 135.00 | AF28: 46132 | AG28: Усть-Каменогорск | AH28: Кредит | AI28: Стандартное кредитование | AJ28: Банк ЦентрКредит | AK28: 84 месяца | AL28: 40 | AM28: 0 | AO28: 0 | AP28: 0 | AQ28: 132075524 | AR28: 127900 | AS28: 11815914 | AT28: 77476242119 | AU28: САП
A29: 1 | B29: 371 Астана ТОО «DCG ASTANA» (KIA) | C29: Ceed SW | D29: Luxe | E29: J7W5D261F | F29: MX1H5816BSK253985 | G29: 1K Black Pearl / Чёрный перламутр | H29: H33I | I29: 2WD | J29: AT | K29: 1591 | L29: 2025 | M29: 371_292608 | N29: 46119 | O29: Даурен Манкулов | P29: Усенбаев Нуршат Ергешович | Q29: 830807300218 | T29: 11490000 | U29: 11490000 | V29: 0 | W29: 0 | X29: 0 | Y29: 517050 | Z29: 517050 | AA29: 1s | AB29: 0.045 | AC29: =U29*AB29 -> 517050 | AD29: =AC29-V29 -> 517050 | AE29: 11 490 000.00 | AF29: 46120 | AG29: Астана | AH29: Наличный расчет | AI29: Наличный расчет | AJ29: Без привлечения кредита | AM29: 0 | AO29: 0 | AP29: 0 | AQ29: 132074775 | AS29: 11836538 | AT29: 77788386665 | AU29: САП
A30: 1 | B30: 371 Астана ТОО «DCG ASTANA» (KIA) | C30: Ceed SW | D30: Luxe | E30: J7W5D261F | F30: MX1H5816BSK253620 | G30: USG Yuca Steel Gray/Стальной | H30: H33I | I30: 2WD | J30: AT | K30: 1591 | L30: 2025 | M30: 371_293137 | N30: 46127 | O30: Виктория Чубинец | P30: Жаканов Есбол Еркингалиевич | Q30: 900325301043 | T30: 11490000 | U30: 11490000 | V30: 0 | W30: 0 | X30: 0 | Y30: 517050 | Z30: 517050 | AA30: 1s | AB30: 0.045 | AC30: =U30*AB30 -> 517050 | AD30: =AC30-V30 -> 517050 | AE30: 2 298 000.00 | AF30: 46134 | AG30: Астана | AH30: Льготный кредит | AI30: Льготное кредитование | AJ30: Halyk Bank | AK30: 84 месяца | AL30: 20 | AM30: 0 | AO30: 0 | AP30: 0 | AQ30: 132075833 | AS30: 11836552 | AT30: 77055550785 | AU30: САП
A31: 1 | B31: 331 Шымкент ТОО «DCG ONTUSTIK» (KIA) | C31: K5 | D31: Tulpar | E31: EUS42JG1J | F31: MX16A414BSK045972 | G31: ABP Aurora Black Pearl / Чёрный перламутр | H31: G174 | I31: 2WD | J31: AT | K31: 0 | L31: 2025 | M31: 331_292850 | N31: 46124 | O31: Нұрсұлтан Көкежан | P31: Жайлымыс Гулвира Қаныбекқызы | Q31: 940821401549 | T31: 13940000 | U31: 13390000 | V31: 0 | W31: 0 | X31: 550000 | Y31: 736450 | Z31: 736450 | AA31: 3s | AB31: 0.055 | AC31: =U31*AB31 -> 736450 | AD31: =AC31-V31 -> 736450 | AE31: 7 000 000.00 | AF31: 46127 | AG31: Шымкент | AH31: Кредит | AI31: Стандартное кредитование | AJ31: Halyk Bank | AK31: 84 месяца | AL31: 45 | AM31: 0 | AO31: 0 | AP31: 0 | AQ31: 132075245 | AR31: 189900 | AS31: 11869042 | AT31: 77074131020 | AU31: САП
A32: 1 | B32: 331 Шымкент ТОО «DCG ONTUSTIK» (KIA) | C32: K5 | D32: Prestige | E32: EUS42JG1J | F32: MX16A414BSK045862 | G32: AG2 Graphite Gray / Серый | H32: G156 | I32: 2WD | J32: AT | K32: 1975 | L32: 2025 | M32: 331_293905 | N32: 46139 | O32: Арман Сабыров | P32: Алашбаев Барат Мамаханович | Q32: 721027300654 | T32: 13990000 | U32: 13990000 | V32: 0 | W32: 0 | X32: 0 | Y32: 769450 | Z32: 769450 | AA32: 3s | AB32: 0.055 | AC32: =U32*AB32 -> 769450 | AD32: =AC32-V32 -> 769450 | AE32: 3 990 000.00 | AF32: 46142 | AG32: Шымкент | AH32: Кредит | AI32: Льготное кредитование | AJ32: Halyk Bank | AK32: 84 месяца | AL32: 30 | AM32: 0 | AO32: 0 | AP32: 0 | AQ32: 132076553 | AR32: 196900 | AS32: 11869045 | AT32: 77076554172 | AU32: САП
A33: 1 | B33: 863 Павлодар ТОО «DCG ERTIS» (KIA) | C33: K5 | D33: Luxe | E33: EUS42JG1J | F33: MX16A414BSK046190 | G33: AG2 Graphite Gray / Серый | H33: G155 | J33: AT | K33: 1975 | L33: 2025 | M33: 863_292937 | N33: 46125 | O33: ЕРЖАН КАРАМЕНДИНОВ | P33: Мусабеков Ринат Серикказыевич | Q33: 820411301112 | T33: 12690000 | U33: 12690000 | V33: 0 | W33: 0 | X33: 0 | Y33: 697950 | Z33: 697950 | AA33: 3s | AB33: 0.055 | AC33: =U33*AB33 -> 697950 | AD33: =AC33-V33 -> 697950 | AE33: 6 345 000.00 | AF33: 46140 | AG33: Павлодар | AH33: Кредит | AI33: Стандартное кредитование | AJ33: Halyk Bank | AK33: 36 месяцев | AL33: 50 | AM33: 0 | AO33: 0 | AP33: 0 | AQ33: 132076234 | AS33: 11869205 | AT33: 77054440001 | AU33: САП
A34: 1 | B34: 1151 Алматы ТОО «DCG Qulja» (KIA) | C34: K5 | D34: Tulpar | E34: EUS42JG1J | F34: MX16A414BSK046128 | G34: SWP Snow White Pearl / Белый перламутр | H34: G176 | I34: 2WD | J34: AT | K34: 1975 | L34: 2025 | M34: 1151_292374 | N34: 46118 | O34: Магилан Махамет | P34: АХИЛЬГОВ ИЛЬЯС СУЛТАНОВИЧ | Q34: 891019302353 | T34: 13390000 | U34: 13390000 | V34: 0 | W34: 0 | X34: 0 | Y34: 791450 | Z34: 791450 | AA34: 3s | AB34: 0.055 | AC34: =U34*AB34 -> 736450 | AD34: =AC34-V34 -> 736450 | AE34: 100 000.00 | AF34: 46136 | AG34: Алматы | AH34: Наличный расчет | AI34: Наличный расчет | AJ34: Без привлечения кредита | AM34: 0 | AO34: 0 | AP34: 0 | AQ34: 132075986 | AR34: 189900 | AS34: 11870591 | AT34: 77017666627 | AU34: САП
A35: 1 | B35: 735 Усть-Каменогорск ТОО «DCG VOSTOK» (KIA) | C35: K5 | D35: Tulpar | E35: EUS42JG1J | F35: MX16A414BSK045967 | G35: SWP Snow White Pearl / Белый перламутр | H35: G174 | I35: 2WD | J35: AT | K35: 0 | L35: 2025 | M35: 735_292362 | N35: 46116 | O35: Дарын Әмірбеков | P35: Бектибаев Саяхат Аитмухаметулы | Q35: 810108300402 | T35: 13640000 | U35: 14390000 | V35: 0 | W35: 1000000 | X35: 250000 | Y35: 791450 | Z35: 791450 | AA35: 1s | AB35: 0.045 | AC35: =U35*AB35 -> 647550 | AD35: =AC35-V35 -> 647550 | AE35: 2 728 000.00 | AF35: 46120 | AG35: Усть-Каменогорск | AH35: Кредит | AI35: Стандартное кредитование | AJ35: Halyk Bank | AK35: 84 месяца | AL35: 20 | AM35: 0 | AO35: 0 | AP35: 0 | AQ35: 132074782 | AR35: 189900 | AS35: 11871863 | AT35: 77055321642 | AU35: САП
A36: 1 | B36: 1069 Актау TOO «DCG Aktau» (KIA) | C36: Sorento 2025 | D36: Tulpar | E36: GZW7L961G | F36: MX1RH81DDSK366026 | G36: BN4 New Gray / Серый | H36: G2YU | I36: 4WD | J36: AT | K36: 2497 | L36: 2025 | M36: 1069_293640 | N36: 46135 | O36: Нурали Садыбаев | P36: Хайрмеденов Кайрбек Ушкишбекович | Q36: 850928302197 | T36: 18990000 | U36: 18990000 | V36: 0 | W36: 0 | X36: 0 | Y36: 1044450 | Z36: 1044450 | AA36: 3s | AB36: 0.055 | AC36: =U36*AB36 -> 1044450 | AD36: =AC36-V36 -> 1044450 | AE36: 9 500 000.00 | AF36: 46140 | AG36: Актау | AH36: Кредит | AI36: Стандартное кредитование | AJ36: Halyk Bank | AK36: 36 месяцев | AL36: 50 | AM36: 0 | AO36: 0 | AP36: 0 | AQ36: 132076218 | AR36: 241900 | AS36: 11896502 | AT36: 77073996969 | AU36: САП
A37: 1 | B37: 1069 Актау TOO «DCG Aktau» (KIA) | C37: Cerato | D37: Luxe+ | E37: DJS4D261F | F37: MX1F4416BSK005443 | G37: UD Clear White / Белый | H37: G02O | I37: 2WD | J37: AT | K37: 1591 | L37: 2025 | M37: 1069_293140 | N37: 46127 | O37: Тимур Нурибаев | P37: Сматов Исатай Маратұлы | Q37: 780712300160 | T37: 10490000 | U37: 10490000 | V37: 0 | W37: 0 | X37: 0 | Y37: 419600 | Z37: 419600 | AA37: 3s | AB37: 0.04 | AC37: =U37*AB37 -> 419600 | AD37: =AC37-V37 -> 419600 | AE37: 2 098 000.00 | AF37: 46133 | AG37: Актау | AH37: Льготный кредит | AI37: Льготное кредитование | AJ37: Halyk Bank | AK37: 84 месяца | AL37: 20 | AM37: 0 | AO37: 0 | AP37: 0 | AQ37: 132075606 | AS37: 11896509 | AT37: 77022201191 | AU37: САП
A38: 1 | B38: 331 Шымкент ТОО «DCG ONTUSTIK» (KIA) | C38: Soul | D38: Style | E38: SKW52G61V | F38: MX1J381UESK272812 | G38: AH1 Clear White / Inferno Red / Белый с красной крышей | H38: G906 | I38: 2WD | J38: AT | K38: 1999 | L38: 2025 | M38: 331_292740 | N38: 46121 | O38: Абдукарим Абдукаим | P38: Тулеумбетов Нурсултан Махмутович | Q38: 891005302357 | T38: 12990000 | U38: 12990000 | V38: 0 | W38: 0 | X38: 0 | Y38: 584550 | Z38: 584550 | AA38: 3s | AB38: 0.045 | AC38: =U38*AB38 -> 584550 | AD38: =AC38-V38 -> 584550 | AE38: 2 990 000.00 | AF38: 46139 | AG38: Шымкент | AH38: Кредит | AI38: Льготное кредитование | AJ38: Halyk Bank | AK38: 84 месяца | AL38: 20 | AM38: 0 | AO38: 0 | AP38: 0 | AQ38: 132076108 | AR38: 149900 | AS38: 11898117 | AT38: 77710180066 | AU38: САП
A39: 1 | B39: 1069 Актау TOO «DCG Aktau» (KIA) | C39: Sorento 2025 | D39: Tulpar | E39: GZW7L961G | F39: MX1RH81DDSK370432 | G39: SWP Snow White Pearl / Белый перламутр | H39: G2YU | I39: 4WD | J39: AT | K39: 2497 | L39: 2025 | M39: 1069_293047 | N39: 46126 | O39: Тимур Нурибаев | P39: Конусова Гулшат Жайылгановна | Q39: 930419000032 | T39: 18990000 | U39: 18990000 | V39: 0 | W39: 0 | X39: 0 | Y39: 1044450 | Z39: 1044450 | AA39: 3s | AB39: 0.045 | AC39: =U39*AB39 -> 854550 | AD39: =AC39-V39 -> 854550 | AE39: 18 990 000.00 | AF39: 46129 | AG39: Актау | AH39: Наличный расчет | AI39: Наличный расчет | AJ39: Без привлечения кредита | AM39: 0 | AO39: 0 | AP39: 0 | AQ39: 132075442 | AR39: 241900 | AS39: 11931916 | AT39: 77020617288 | AU39: САП
A40: 1 | B40: 363 Алматы ТОО «DCG ALMATY» (KIA) | C40: Seltos | D40: Style | E40: THW52G61Q | F40: MX1ER81AKTK833516 | G40: FSB Modern Black / Черный | H40: G0DK | I40: 4WD | J40: CVT | K40: 1999 | L40: 2025 | M40: 363_294076 | N40: 46141 | O40: Даур Құттыбай | P40: Максимова Ақбота Максимқызы | Q40: 920705401673 | T40: 13490000 | U40: 13490000 | V40: 0 | W40: 0 | X40: 0 | Y40: 607050 | Z40: 607050 | AA40: 1s | AB40: 0.045 | AC40: =U40*AB40 -> 607050 | AD40: =AC40-V40 -> 607050 | AE40: 3 304 000.00 | AF40: 46142 | AG40: Алматы | AH40: Кредит | AI40: Стандартное кредитование | AJ40: Halyk Bank | AK40: 84 месяца | AL40: 10 | AM40: 0 | AO40: 0 | AP40: 0 | AQ40: 132076501 | AR40: 176900 | AS40: 11944944 | AT40: 77470647847 | AU40: САП
A41: 1 | B41: 331 Шымкент ТОО «DCG ONTUSTIK» (KIA) | C41: K5 | D41: Luxe | E41: EUS42JG1J | F41: MX16A414BSK045307 | G41: SWP Snow White Pearl / Белый перламутр | H41: G155 | J41: AT | K41: 1975 | L41: 2025 | M41: 331_292561 | N41: 46119 | O41: Ернар Жайдарбек | P41: Спатаев Аскарбек Рустембекович | Q41: 891022300849 | T41: 13690000 | U41: 12690000 | V41: 0 | W41: 0 | X41: 1000000 | Y41: 697950 | Z41: 697950 | AA41: 3s | AB41: 0.055 | AC41: =U41*AB41 -> 697950 | AD41: =AC41-V41 -> 697950 | AE41: 3 690 000.00 | AF41: 46127 | AG41: Шымкент | AH41: Кредит | AI41: Льготное кредитование | AJ41: Halyk Bank | AK41: 84 месяца | AL41: 20 | AM41: 0 | AO41: 0 | AP41: 0 | AQ41: 132075237 | AS41: 11965893 | AT41: 77029061131 | AU41: САП
A42: 1 | B42: 331 Шымкент ТОО «DCG ONTUSTIK» (KIA) | C42: K8 | D42: Prestige | E42: GGS4J9A1K | F42: MX1M441DDSK085835 | G42: ISG / Ivory Silver/Серебро слоновой кости / Серый | H42: K20I | I42: 4WD | J42: AT | K42: 3470 | L42: 2025 | M42: 331_292575 | N42: 46119 | O42: Ерболат Балабас | P42: Калгинбаева Айгерим Талгатовна | Q42: 881126401391 | T42: 26490000 | U42: 26490000 | V42: 0 | W42: 0 | X42: 0 | Y42: 1721850 | Z42: 1721850 | AA42: 3s | AB42: 0.065 | AC42: =U42*AB42 -> 1721850 | AD42: =AC42-V42 -> 1721850 | AE42: 13 995 000.00 | AF42: 46122 | AG42: Шымкент | AH42: Кредит | AI42: Стандартное кредитование | AJ42: Halyk Bank | AK42: 84 месяца | AL42: 50 | AM42: 0 | AO42: 0 | AP42: 0 | AQ42: 132074941 | AR42: 274900 | AS42: 11972510 | AT42: 77019000088 | AU42: САП
A43: 1 | B43: 331 Шымкент ТОО «DCG ONTUSTIK» (KIA) | C43: Cerato | D43: Luxe+ | E43: DJS4D261F | F43: MX1F4416BSK005554 | G43: KLG Steel Gray / Стальной | H43: G02O | I43: 2WD | J43: AT | K43: 1591 | L43: 2025 | M43: 331_293491 | N43: 46133 | O43: Арман Сабыров | P43: Жапан Данияр Сәрсенбайұлы | Q43: 920820302383 | T43: 10740000 | U43: 10490000 | V43: 0 | W43: 0 | X43: 250000 | Y43: 419600 | Z43: 419600 | AA43: 3s | AB43: 0.04 | AC43: =U43*AB43 -> 419600 | AD43: =AC43-V43 -> 419600 | AE43: 6 000 000.00 | AF43: 46134 | AG43: Шымкент | AH43: Кредит | AI43: Стандартное кредитование | AJ43: Halyk Bank | AK43: 84 месяца | AL43: 55 | AM43: 0 | AN43: 215 Шымкент TOO «NOMAD MOTORS SHYM» (KIA) | AO43: 0 | AP43: 0 | AQ43: 132075801 | AS43: 11975458 | AT43: 77757108458 | AU43: САП
A44: 1 | B44: 1151 Алматы ТОО «DCG Qulja» (KIA) | C44: Sorento 2025 | D44: Tulpar | E44: GZW7J961K | F44: MX1RH81EDSK372506 | G44: SWP Snow White Pearl / Белый перламутр | H44: G2YU | I44: 4WD | J44: AT | K44: 3470 | L44: 2025 | M44: 1151_291223 | N44: 46101 | O44: Дайана Калиаскар | P44: Советбек Нұрғали Нұрланұлы | Q44: 930722300722 | T44: 15000000 | U44: 21690000 | V44: 6690000 | W44: 0 | X44: 0 | Y44: 976050 | Z44: -5713950 | AA44: 3s | AB44: 0.045 | AC44: =U44*AB44 -> 976050 | AD44: =AC44-V44 -> -5713950 | AE44: 1 500 000.00 | AF44: 46128 | AG44: Алматы | AH44: Льготный кредит | AI44: Льготное кредитование | AJ44: Евразийский банк | AK44: 84 месяца | AL44: 10 | AM44: 0 | AN44: 1089 Костанай TOO «Allur Auto Qostanay» (KIA) | AO44: 0 | AP44: 0 | AQ44: 132075364 | AR44: 258900 | AS44: 11994472 | AT44: 77079222688 | AU44: САП
A45: 1 | B45: 735 Усть-Каменогорск ТОО «DCG VOSTOK» (KIA) | C45: Sorento 2025 | D45: Luxe | E45: GZW7L961G | F45: MX1RH81DDSK377025 | G45: KLG Steel Gray / Стальной | H45: G2IJ | I45: 4WD | J45: AT | K45: 2497 | L45: 2025 | M45: 735_292297 | N45: 46115 | O45: Дарын Әмірбеков | P45: Кәдірбекова Арай Талғатқызы | Q45: 960727451459 | T45: 18390000 | U45: 19390000 | V45: 1000000 | W45: 0 | X45: 0 | Y45: 872550 | Z45: -127450 | AA45: 1s | AB45: 0.045 | AC45: =U45*AB45 -> 872550 | AD45: =AC45-V45 -> -127450 | AF45: 46118 | AG45: Усть-Каменогорск | AH45: Безналичный расчет | AI45: Безналичный | AJ45: Без привлечения кредита | AM45: 0 | AO45: 0 | AP45: 0 | AQ45: 132074673 | AR45: 229900 | AS45: 11994747 | AT45: 77764401030 | AU45: САП
A46: 1 | B46: 1069 Актау TOO «DCG Aktau» (KIA) | C46: Ceed SW | D46: Prestige | E46: J7W5D261F | F46: MX1H5816BSK253703 | G46: CSS Lunar Silver / Стальной | H46: H33J | I46: 2WD | J46: AT | K46: 1591 | L46: 2025 | M46: 1069_293443 | N46: 46132 | O46: Тимур Нурибаев | P46: Бисенов Абай Базартаевич | Q46: 811116300835 | T46: 12490000 | U46: 12490000 | V46: 0 | W46: 0 | X46: 0 | Y46: 562050 | Z46: 562050 | AA46: 3s | AB46: 0.045 | AC46: =U46*AB46 -> 562050 | AD46: =AC46-V46 -> 562050 | AE46: 12 490 000.00 | AF46: 46133 | AG46: Актау | AH46: Наличный расчет | AI46: Наличный расчет | AJ46: Без привлечения кредита | AM46: 0 | AO46: 0 | AP46: 0 | AQ46: 132075716 | AR46: 145900 | AS46: 12005126 | AT46: 77714075702 | AU46: САП
A47: 1 | B47: 735 Усть-Каменогорск ТОО «DCG VOSTOK» (KIA) | C47: Ceed SW | D47: Comfort | E47: J7W5D261F | F47: MX1H4816BSK253707 | G47: HW2 Deluxe White / Белый перламутр | H47: K0OP | I47: 2WD | J47: AT | K47: 1591 | L47: 2025 | M47: 735_293366 | N47: 46131 | O47: Азамат Тоқтарбеков | P47: Денебаева Адемы Ержановна | Q47: 820223402948 | T47: 10990000 | U47: 10990000 | V47: 0 | W47: 0 | X47: 0 | Y47: 494550 | Z47: 494550 | AA47: 1s | AB47: 0.045 | AC47: =U47*AB47 -> 494550 | AD47: =AC47-V47 -> 494550 | AE47: 1 100 000.00 | AF47: 46134 | AG47: Усть-Каменогорск | AH47: Кредит | AI47: Стандартное кредитование | AJ47: Береке Банк | AK47: 84 месяца | AL47: 10 | AM47: 0 | AO47: 0 | AP47: 0 | AQ47: 132075774 | AR47: 127900 | AS47: 12007161 | AT47: 77772808223 | AU47: САП
A48: 1 | B48: 371 Астана ТОО «DCG ASTANA» (KIA) | C48: Ceed SW | D48: Luxe | E48: J7W5D261F | F48: MX1H5816BSK253777 | G48: H8G Penta Metal / Серый | H48: H33I | I48: 2WD | J48: AT | K48: 1591 | L48: 2025 | M48: 371_292860 | N48: 46125 | O48: Александр Кочетков | P48: Исаберген Мейіржан Бауыржанұлы | Q48: 930127302635 | T48: 11590000 | U48: 11490000 | V48: 0 | W48: 0 | X48: 100000 | Y48: 517050 | Z48: 517050 | AA48: 1s | AB48: 0.045 | AC48: =U48*AB48 -> 517050 | AD48: =AC48-V48 -> 517050 | AE48: 2 318 000.00 | AF48: 46129 | AG48: Астана | AH48: Льготный кредит | AI48: Льготное кредитование | AJ48: Halyk Bank | AK48: 84 месяца | AL48: 20 | AM48: 0 | AO48: 0 | AP48: 0 | AQ48: 132075421 | AS48: 12025426 | AT48: 77751646639 | AU48: САП
A49: 1 | B49: 371 Астана ТОО «DCG ASTANA» (KIA) | C49: Ceed SW | D49: Luxe | E49: J7W5D261F | F49: MX1H5816BSK253927 | G49: 1K Black Pearl / Чёрный перламутр | H49: H33I | I49: 2WD | J49: AT | K49: 1591 | L49: 2025 | M49: 371_292759 | N49: 46121 | O49: Владимир Ульянов | P49: Абильмажинов Айдархан Муратович | Q49: 820916351045 | T49: 11990000 | U49: 11490000 | V49: 0 | W49: 0 | X49: 500000 | Y49: 517050 | Z49: 517050 | AA49: 1s | AB49: 0.045 | AC49: =U49*AB49 -> 517050 | AD49: =AC49-V49 -> 517050 | AE49: 1 199 000.00 | AF49: 46134 | AG49: Астана | AH49: Кредит | AI49: Льготное кредитование | AJ49: Банк ЦентрКредит | AK49: 84 месяца | AL49: 10 | AM49: 0 | AO49: 0 | AP49: 0 | AQ49: 132075834 | AS49: 12025427 | AT49: 77015998080 | AU49: САП
A50: 1 | B50: 331 Шымкент ТОО «DCG ONTUSTIK» (KIA) | C50: Cerato | D50: Luxe+ | E50: DJS4D261F | F50: MX1F4416BSK005574 | G50: KLG Steel Gray / Стальной | H50: G02O | I50: 2WD | J50: AT | K50: 1591 | L50: 2025 | M50: 331_293135 | N50: 46127 | O50: Серик Адильбеков | P50: Карабекова Асемгул Онгарбековна | Q50: 950930401018 | T50: 10740000 | U50: 10490000 | V50: 0 | W50: 0 | X50: 250000 | Y50: 419600 | Z50: 419600 | AA50: 3s | AB50: 0.04 | AC50: =U50*AB50 -> 419600 | AD50: =AC50-V50 -> 419600 | AE50: 1 075 000.00 | AF50: 46132 | AG50: Шымкент | AH50: Кредит | AI50: Стандартное кредитование | AJ50: Береке Банк | AK50: 84 месяца | AL50: 10 | AM50: 0 | AN50: 215 Шымкент TOO «NOMAD MOTORS SHYM» (KIA) | AO50: 0 | AP50: 0 | AQ50: 132075509 | AS50: 12035559 | AT50: 77771967956 | AU50: САП
A51: 1 | B51: 1151 Алматы ТОО «DCG Qulja» (KIA) | C51: Ceed | D51: Luxe | E51: J7S6D261F | F51: MX1H2516BSK257902 | G51: H8G Penta Metal / Серый | H51: D2U5 | I51: 2WD | J51: AT | K51: 0 | L51: 2025 | M51: 1151_291952 | N51: 46111 | O51: Дайана Калиаскар | R51: ТОО "Микрофинансовая организация"Тойота Файнаншл Сервисез Казахстан" | S51: 130440002721 | T51: 10390000 | U51: 10690000 | V51: 0 | W51: 300000 | X51: 0 | Y51: 481050 | Z51: 481050 | AA51: 3s | AB51: 0.045 | AC51: =U51*AB51 -> 481050 | AD51: =AC51-V51 -> 481050 | AE51: 10 390 000.00 | AF51: 46119 | AG51: Алматы | AH51: Безналичный расчет | AI51: Безналичный | AJ51: Без привлечения кредита | AM51: 0 | AO51: 0 | AP51: 0 | AQ51: 132074755 | AR51: 129900 | AS51: 12035581 | AT51: 77717904545 | AU51: САП
A52: 1 | B52: 735 Усть-Каменогорск ТОО «DCG VOSTOK» (KIA) | C52: Ceed SW | D52: Comfort | E52: J7W5D261F | F52: MX1H4816BSK253788 | G52: CSS Lunar Silver / Стальной | H52: K0OP | I52: 2WD | J52: AT | K52: 1591 | L52: 2025 | M52: 735_292760 | N52: 46121 | O52: Азамат Тоқтарбеков | P52: Касымханов Мурат Токтаулович | Q52: 690422300869 | T52: 11690000 | U52: 10990000 | V52: 0 | W52: 0 | X52: 700000 | Y52: 494550 | Z52: 494550 | AA52: 1s | AB52: 0.045 | AC52: =U52*AB52 -> 494550 | AD52: =AC52-V52 -> 494550 | AE52: 1 200 000.00 | AF52: 46126 | AG52: Усть-Каменогорск | AH52: Кредит | AI52: Стандартное кредитование | AJ52: МФО Sapa Digital Finance | AK52: 84 месяца | AL52: 10 | AM52: 0 | AO52: 0 | AP52: 0 | AQ52: 132075078 | AR52: 127900 | AS52: 12036869 | AT52: 77778573737 | AU52: САП
A53: 1 | B53: 735 Усть-Каменогорск ТОО «DCG VOSTOK» (KIA) | C53: Ceed SW | D53: Luxe | E53: J7W5D261F | F53: MX1H5816BSK253881 | G53: CSS Lunar Silver / Стальной | H53: H33I | I53: 2WD | J53: AT | K53: 1591 | L53: 2025 | M53: 735_293044 | N53: 46126 | O53: Максим Косихин | P53: Ворошилов Василий Николаевич | Q53: 610726301766 | T53: 11490000 | U53: 11490000 | V53: 0 | W53: 0 | X53: 0 | Y53: 517050 | Z53: 517050 | AA53: 1s | AB53: 0.045 | AC53: =U53*AB53 -> 517050 | AD53: =AC53-V53 -> 517050 | AF53: 46127 | AG53: Усть-Каменогорск | AH53: Безналичный расчет | AI53: Безналичный | AJ53: Без привлечения кредита | AM53: 0 | AO53: 0 | AP53: 0 | AQ53: 132075205 | AS53: 12036872 | AT53: 77772645297 | AU53: САП
A54: 1 | B54: 1190 Шымкент ТОО «DCG ONTUSTIK» (KIA) AMQ | C54: Sorento 2025 | D54: Comfort | E54: GZW5L961G | F54: MXRRH81DDTY000175 | G54: KLG Steel Gray / Стальной | H54: G2IF | I54: 4WD | J54: AUTOT/M | K54: 2497 | L54: 2025 | M54: 1190_293592 | N54: 46134 | O54: Нұрсұлтан Көкежан | P54: Нурмагамбетова Гульнур Айбековна | Q54: 851215400430 | T54: 16990000 | U54: 16990000 | V54: 0 | W54: 0 | X54: 0 | Y54: 934450 | Z54: 934450 | AA54: 3s | AB54: 0.055 | AC54: =U54*AB54 -> 934450 | AD54: =AC54-V54 -> 934450 | AF54: 46135 | AG54: Шымкент | AH54: Безналичный расчет | AI54: Безналичный | AJ54: Без привлечения кредита | AM54: 0 | AN54: 1191 Шымкент TOO «NOMAD MOTORS SHYM» (KIA) AMQ | AO54: 0 | AP54: 0 | AQ54: 132075901 | AR54: 216900 | AS54: 12065253 | AT54: 77710658121 | AU54: KKZ
A55: 1 | B55: 1184 Актау ТОО «DCG Aktau» (KIA) AMQ | C55: Sorento 2025 | D55: Comfort | E55: GZW5L961G | F55: MXRRH81DDTY000180 | G55: KLG Steel Gray / Стальной | H55: G2IF | I55: 4WD | J55: AUTOT/M | K55: 2497 | L55: 2025 | M55: 1184_293736 | N55: 46136 | O55: Нурали Садыбаев | P55: Қалдыбаев Серік Жолдыбайұлы | Q55: 750704302366 | T55: 17690000 | U55: 16990000 | V55: 0 | W55: 0 | X55: 700000 | Y55: 934450 | Z55: 934450 | AA55: 3s | AB55: 0.055 | AC55: =U55*AB55 -> 934450 | AD55: =AC55-V55 -> 934450 | AE55: 8 000 000.00 | AF55: 46141 | AG55: Актау | AH55: Кредит | AI55: Стандартное кредитование | AJ55: Halyk Bank | AK55: 48 месяцев | AL55: 47 | AM55: 0 | AO55: 0 | AP55: 0 | AQ55: 132076437 | AR55: 216900 | AS55: 12066079 | AT55: 77025616175 | AU55: KKZ
A56: 1 | B56: 1181 Усть-Каменогорск ТОО «DCG VOSTOK» (KIA) AMQ | C56: Sorento 2025 | D56: Comfort | E56: GZW5L961G | F56: MXRRH81DDTY000167 | G56: AGT Graphite Gray / Серый | H56: G2IF | I56: 4WD | J56: AUTOT/M | K56: 2497 | L56: 2025 | M56: 1181_292815 | N56: 46122 | O56: Максим Косихин | P56: Айтказин Оралбек Айтказыулы | Q56: 590409300024 | T56: 16990000 | U56: 16990000 | V56: 0 | W56: 0 | X56: 0 | Y56: 934450 | Z56: 934450 | AA56: 1s | AB56: 0.045 | AC56: =U56*AB56 -> 764550 | AD56: =AC56-V56 -> 764550 | AF56: 46125 | AG56: Усть-Каменогорск | AH56: Безналичный расчет | AI56: Безналичный | AJ56: Без привлечения кредита | AM56: 0 | AO56: 0 | AP56: 0 | AQ56: 132075038 | AR56: 216900 | AS56: 12066363 | AT56: 77052822439 | AU56: KKZ
A57: 1 | B57: 1069 Актау TOO «DCG Aktau» (KIA) | C57: Sportage | D57: Style | E57: GYWDL9A1K | F57: MX1PV81FDSK020847 | G57: KLG Steel Gray / Стальной | H57: G0P2 | I57: 4WD | J57: AT | K57: 2497 | L57: 2025 | M57: 1069_293563 | N57: 46134 | O57: Нурали Садыбаев | P57: Аманьязов Ерлан Муратович | Q57: 880812302845 | T57: 15340000 | U57: 15090000 | V57: 0 | W57: 0 | X57: 250000 | Y57: 829950 | Z57: 829950 | AA57: 3s | AB57: 0.055 | AC57: =U57*AB57 -> 829950 | AD57: =AC57-V57 -> 829950 | AE57: 4 530 000.00 | AF57: 46140 | AG57: Актау | AH57: Кредит | AI57: Стандартное кредитование | AJ57: Шинхань Банк | AK57: 60 месяцев | AL57: 30 | AM57: 0 | AO57: 0 | AP57: 0 | AQ57: 132076233 | AR57: 201900 | AS57: 12073111 | AT57: 77089186689 | AU57: САП
A58: 1 | B58: 1192 Павлодар ТОО «DCG ERTIS» (KIA) AMQ | C58: K5 | D58: Luxe | E58: EUS42JG1J | F58: MXR6AA248TY900203 | G58: AG2 Graphite Gray / Серый | H58: G155 | I58: 2WD | J58: AUTOT/M | K58: 1975 | L58: 2025 | M58: 1192_292673 | N58: 46120 | O58: КАНАТ АЛЬЖАНОВ | P58: Бессинбенова Асель Джамбуловна | Q58: 860804450408 | T58: 12690000 | U58: 12690000 | V58: 0 | W58: 0 | X58: 0 | Y58: 697950 | Z58: 697950 | AA58: 3s | AB58: 0.055 | AC58: =U58*AB58 -> 697950 | AD58: =AC58-V58 -> 697950 | AE58: 3 933 900.00 | AF58: 46134 | AG58: Павлодар | AH58: Кредит | AI58: Стандартное кредитование | AJ58: МФО Sapa Digital Finance | AK58: 84 месяца | AL58: 31 | AM58: 0 | AO58: 0 | AP58: 0 | AQ58: 132075822 | AS58: 12073603 | AT58: 77015550985 | AU58: KKZ
A59: 1 | B59: 1190 Шымкент ТОО «DCG ONTUSTIK» (KIA) AMQ | C59: Sorento 2025 | D59: Style | E59: GZW7L961G | F59: MXRRH81DDTY000263 | G59: BN4 New Gray / Серый | H59: G2Z2 | I59: 4WD | J59: AUTOT/M | K59: 2497 | L59: 2025 | M59: 1190_292517 | N59: 46118 | O59: Ернар Жайдарбек | P59: Тультаев Берик Асильханович | Q59: 851114301532 | T59: 19990000 | U59: 19990000 | V59: 0 | W59: 0 | X59: 0 | Y59: 1099450 | Z59: 1099450 | AA59: 3s | AB59: 0.045 | AC59: =U59*AB59 -> 899550 | AD59: =AC59-V59 -> 899550 | AE59: 6 000 000.00 | AF59: 46120 | AG59: Шымкент | AH59: Кредит | AI59: Стандартное кредитование | AJ59: Береке Банк | AK59: 84 месяца | AL59: 30 | AM59: 0 | AO59: 0 | AP59: 0 | AQ59: 132074830 | AR59: 251900 | AS59: 12076071 | AT59: 77017378585 | AU59: KKZ
A60: 1 | B60: 1173 Алматы ТОО «DCG Qulja» (KIA) AMQ | C60: Sorento 2025 | D60: Comfort | E60: GZW5L961G | F60: MXRRH81DDTY000151 | G60: ABP Aurora Black Pearl / Чёрный перламутр | H60: G2IF | I60: 4WD | J60: AUTOT/M | K60: 2497 | L60: 2025 | M60: 1173_293631 | N60: 46135 | O60: Мади Мынбаев | P60: ОСПАНОВ АСЕТ МУХАМЕТХАНОВИЧ | Q60: 740101304957 | T60: 17290000 | U60: 16990000 | V60: 0 | W60: 0 | X60: 300000 | Y60: 934450 | Z60: 934450 | AA60: 3s | AB60: 0.055 | AC60: =U60*AB60 -> 934450 | AD60: =AC60-V60 -> 934450 | AE60: 10 000 000.00 | AF60: 46139 | AG60: Алматы | AH60: Кредит | AI60: Стандартное кредитование | AJ60: Евразийский банк | AK60: 36 месяцев | AL60: 57 | AM60: 0 | AO60: 0 | AP60: 0 | AQ60: 132076100 | AR60: 216900 | AS60: 12084904 | AT60: 77772323950 | AU60: KKZ
A61: 1 | B61: 1190 Шымкент ТОО «DCG ONTUSTIK» (KIA) AMQ | C61: Sorento 2025 | D61: Comfort | E61: GZW5L961G | F61: MXRRH81DDTY000146 | G61: SWP Snow White Pearl / Белый перламутр | H61: G2IF | I61: 4WD | J61: AUTOT/M | K61: 2497 | L61: 2025 | M61: 1190_292775 | N61: 46122 | O61: Нұрсұлтан Көкежан | P61: Керимбекова Айман Богенбаевна | Q61: 880818401806 | T61: 16990000 | U61: 16990000 | V61: 0 | W61: 0 | X61: 0 | Y61: 934450 | Z61: 934450 | AA61: 3s | AB61: 0.045 | AC61: =U61*AB61 -> 764550 | AD61: =AC61-V61 -> 764550 | AF61: 46128 | AG61: Шымкент | AH61: Безналичный расчет | AI61: Безналичный | AJ61: Без привлечения кредита | AM61: 0 | AN61: 1169 Алматы ТОО «DCG ALMATY» (KIA) AMQ | AO61: 0 | AP61: 0 | AQ61: 132075329 | AR61: 216900 | AS61: 12086642 | AT61: 77011171166 | AU61: KKZ
A62: 1 | B62: 331 Шымкент ТОО «DCG ONTUSTIK» (KIA) | C62: K5 | D62: Luxe | E62: EUS42JG1J | F62: MX16A414BTK047173 | G62: AG2 Graphite Gray / Серый | H62: G155 | I62: 2WD | J62: AT | K62: 1975 | L62: 2025 | M62: 331_292232 | N62: 46113 | O62: Нұрсұлтан Көкежан | P62: Қалдыбек Аружан Ғалымжанқызы | Q62: 20712600846 | T62: 13990000 | U62: 13690000 | V62: 0 | W62: 0 | X62: 300000 | Y62: 752950 | Z62: 752950 | AA62: 3s | AB62: 0.055 | AC62: =U62*AB62 -> 752950 | AD62: =AC62-V62 -> 752950 | AE62: 1 450 000.00 | AF62: 46118 | AG62: Шымкент | AH62: Кредит | AI62: Стандартное кредитование | AJ62: Банк ЦентрКредит | AK62: 84 месяца | AL62: 10 | AM62: 0 | AO62: 0 | AP62: 0 | AQ62: 132074682 | AS62: 12098324 | AT62: 77472307919 | AU62: САП
A63: 1 | B63: 331 Шымкент ТОО «DCG ONTUSTIK» (KIA) | C63: K5 | D63: Luxe | E63: EUS42JG1J | F63: MX16A414BTK047176 | G63: AG2 Graphite Gray / Серый | H63: G155 | J63: AT | K63: 1975 | L63: 2025 | M63: 331_292704 | N63: 46120 | O63: Абдукарим Абдукаим | P63: Жамелов Баглан Алтаевич | Q63: 860703302175 | T63: 12690000 | U63: 12690000 | V63: 0 | W63: 0 | X63: 0 | Y63: 697950 | Z63: 697950 | AA63: 3s | AB63: 0.055 | AC63: =U63*AB63 -> 697950 | AD63: =AC63-V63 -> 697950 | AE63: 2 690 000.00 | AF63: 46142 | AG63: Шымкент | AH63: Кредит | AI63: Льготное кредитование | AJ63: Halyk Bank | AK63: 84 месяца | AL63: 10 | AM63: 0 | AO63: 0 | AP63: 0 | AQ63: 132076498 | AS63: 12098325 | AT63: 77024582777 | AU63: САП
A64: 1 | B64: 863 Павлодар ТОО «DCG ERTIS» (KIA) | C64: K5 | D64: Luxe | E64: EUS42JG1J | F64: MX16A414BTK047315 | G64: SWP Snow White Pearl / Белый перламутр | H64: G155 | J64: AT | K64: 1975 | L64: 2025 | M64: 863_293148 | N64: 46128 | O64: ЕРЖАН КАРАМЕНДИНОВ | P64: Раздыков Руслан Алексеевич | Q64: 820519300528 | T64: 12690000 | U64: 12690000 | V64: 0 | W64: 0 | X64: 0 | Y64: 697950 | Z64: 697950 | AA64: 3s | AB64: 0.055 | AC64: =U64*AB64 -> 697950 | AD64: =AC64-V64 -> 697950 | AE64: 4 500 000.00 | AF64: 46129 | AG64: Павлодар | AH64: Кредит | AI64: Стандартное кредитование | AJ64: Altyn Bank | AK64: 84 месяца | AL64: 35 | AM64: 0 | AO64: 0 | AP64: 0 | AQ64: 132075409 | AS64: 12098362 | AT64: 77772728801 | AU64: САП
A65: 1 | B65: 365 Тараз ТОО «DCGTARAZ» (KIA) | C65: Sorento 2025 | D65: Luxe | E65: GZW7L961G | F65: MX1RH81DDTK379210 | G65: BN4 New Gray / Серый | H65: G2IJ | I65: 4WD | J65: AT | K65: 2497 | L65: 2025 | M65: 365_293312 | N65: 46130 | O65: Даниял Мурат | P65: Сыздыков Бахытбек Умирбекович | Q65: 680823300699 | T65: 18940000 | U65: 18390000 | V65: 0 | W65: 0 | X65: 550000 | Y65: 1011450 | Z65: 1011450 | AA65: 1s | AB65: 0.045 | AC65: =U65*AB65 -> 827550 | AD65: =AC65-V65 -> 827550 | AE65: 3 000 000.00 | AF65: 46133 | AG65: Тараз | AH65: Кредит | AI65: Стандартное кредитование | AJ65: Банк ЦентрКредит | AK65: 84 месяца | AL65: 20 | AM65: 0 | AO65: 0 | AP65: 0 | AQ65: 132075664 | AR65: 229900 | AS65: 12099432 | AT65: 77003563945 | AU65: САП
A66: 1 | B66: 1151 Алматы ТОО «DCG Qulja» (KIA) | C66: K5 | D66: Luxe | E66: EUS42JG1J | F66: MX16A414BTK047175 | G66: AG2 Graphite Gray / Серый | H66: G155 | J66: AT | K66: 1975 | L66: 2025 | M66: 1151_293331 | N66: 46132 | O66: Ерик Серкешбаев | P66: Дикомбаева Гульмира Аргымбаевна | Q66: 730216401625 | T66: 12690000 | U66: 12690000 | V66: 0 | W66: 0 | X66: 0 | Y66: 697950 | Z66: 697950 | AA66: 3s | AB66: 0.055 | AC66: =U66*AB66 -> 697950 | AD66: =AC66-V66 -> 697950 | AE66: 1 300 000.00 | AF66: 46136 | AG66: Алматы | AH66: Кредит | AI66: Стандартное кредитование | AJ66: МФО Sapa Digital Finance | AK66: 84 месяца | AL66: 10 | AM66: 0 | AO66: 0 | AP66: 0 | AQ66: 132075982 | AS66: 12099879 | AT66: 77788655633 | AU66: САП
A67: 1 | B67: 1069 Актау TOO «DCG Aktau» (KIA) | C67: Sorento 2025 | D67: Luxe | E67: GZW7L961G | F67: MX1RH81DDTK379731 | G67: SWP Snow White Pearl / Белый перламутр | H67: G2IJ | I67: 4WD | J67: AT | K67: 2497 | L67: 2025 | M67: 1069_292640 | N67: 46120 | O67: Нурали Садыбаев | P67: Булекенов Гани Газизович | Q67: 861130300414 | T67: 18946000 | U67: 18390000 | V67: 0 | W67: 0 | X67: 556000 | Y67: 1011450 | Z67: 1011450 | AA67: 3s | AB67: 0.045 | AC67: =U67*AB67 -> 827550 | AD67: =AC67-V67 -> 827550 | AE67: 3 000 000.00 | AF67: 46122 | AG67: Актау | AH67: Кредит | AI67: Стандартное кредитование | AJ67: Банк ЦентрКредит | AK67: 84 месяца | AL67: 16 | AM67: 0 | AO67: 0 | AP67: 0 | AQ67: 132075003 | AR67: 229900 | AS67: 12118163 | AT67: 77015526252 | AU67: САП
A68: 1 | B68: 331 Шымкент ТОО «DCG ONTUSTIK» (KIA) | C68: Sorento 2025 | D68: Comfort | E68: GZW5L961G | F68: MX1RH81DDTK378664 | G68: BN4 New Gray / Серый | H68: G2IF | I68: 4WD | J68: AT | K68: 2497 | L68: 2025 | M68: 331_293004 | N68: 46125 | O68: Нұрсұлтан Көкежан | P68: Атенов Абзал Абидилаевич | Q68: 910124301855 | T68: 16990000 | U68: 16990000 | V68: 0 | W68: 0 | X68: 0 | Y68: 934450 | Z68: 934450 | AA68: 3s | AB68: 0.045 | AC68: =U68*AB68 -> 764550 | AD68: =AC68-V68 -> 764550 | AE68: 1 700 000.00 | AF68: 46132 | AG68: Шымкент | AH68: Кредит | AI68: Стандартное кредитование | AJ68: Банк ЦентрКредит | AK68: 84 месяца | AL68: 10 | AM68: 0 | AN68: 365 Тараз ТОО «DCGTARAZ» (KIA) | AO68: 0 | AP68: 0 | AQ68: 132075532 | AR68: 216900 | AS68: 12122597 | AT68: 77753210992 | AU68: САП
A69: 1 | B69: 363 Алматы ТОО «DCG ALMATY» (KIA) | C69: Seltos | D69: Comfort | E69: THW52G61Q | F69: MX1EP81AKTK844000 | G69: KDG Gravity Gray / Серый | H69: D420 | I69: 4WD | J69: CVT | K69: 1999 | L69: 2025 | M69: 363_292466 | N69: 46118 | O69: Бахытжан Смагулов | P69: Пак Екатерина Андреевна | Q69: 960220400943 | T69: 11590000 | U69: 11590000 | V69: 0 | W69: 0 | X69: 0 | Y69: 521550 | Z69: 521550 | AA69: 1s | AB69: 0.045 | AC69: =U69*AB69 -> 521550 | AD69: =AC69-V69 -> 521550 | AE69: 11 590 000.00 | AF69: 46121 | AG69: Алматы | AH69: Наличный расчет | AI69: Наличный расчет | AJ69: Без привлечения кредита | AM69: 0 | AO69: 0 | AP69: 0 | AQ69: 132074887 | AR69: 152900 | AS69: 12122601 | AT69: 77012451115 | AU69: САП
A70: 1 | B70: 1151 Алматы ТОО «DCG Qulja» (KIA) | C70: Seltos | D70: Luxe | E70: THW52G61V | F70: MX1ER81AETK843552 | G70: F1A Pluton Blue / Fusion Black / Голубой с чёрной крышей | H70: G0DG | I70: 2WD | J70: CVT | K70: 1999 | L70: 2025 | M70: 1151_293032 | N70: 46126 | O70: Рахима Габдуллина | P70: МИМИКЕНОВ ИРАНГАИП ДУНЕНБАЕВИЧ | Q70: 641125300015 | T70: 11990000 | U70: 11990000 | V70: 0 | W70: 0 | X70: 0 | Y70: 539550 | Z70: 539550 | AA70: 3s | AB70: 0.045 | AC70: =U70*AB70 -> 539550 | AD70: =AC70-V70 -> 539550 | AE70: 11 990 000.00 | AF70: 46126 | AG70: Алматы | AH70: Наличный расчет | AI70: Наличный расчет | AJ70: Без привлечения кредита | AM70: 0 | AO70: 0 | AP70: 0 | AQ70: 132075155 | AR70: 153900 | AS70: 12122642 | AT70: 77019290161 | AU70: САП
A71: 1 | B71: 331 Шымкент ТОО «DCG ONTUSTIK» (KIA) | C71: Seltos | D71: Luxe | E71: THW52G61V | F71: MX1ER81AETK829970 | G71: KLG Steel Gray / Стальной | H71: G0DG | I71: 2WD | J71: CVT | K71: 1999 | L71: 2025 | M71: 331_292798 | N71: 46122 | O71: Нұрсұлтан Көкежан | P71: Камалова Әсем Тоғызбайқызы | Q71: 940120402101 | T71: 11990000 | U71: 11990000 | V71: 0 | W71: 0 | X71: 0 | Y71: 539550 | Z71: 539550 | AA71: 3s | AB71: 0.045 | AC71: =U71*AB71 -> 539550 | AD71: =AC71-V71 -> 539550 | AE71: 2 490 000.00 | AF71: 46128 | AG71: Шымкент | AH71: Кредит | AI71: Льготное кредитование | AJ71: Halyk Bank | AK71: 84 месяца | AL71: 20 | AM71: 0 | AO71: 0 | AP71: 0 | AQ71: 132075309 | AR71: 153900 | AS71: 12125665 | AT71: 77029515655 | AU71: САП
A72: 1 | B72: 363 Алматы ТОО «DCG ALMATY» (KIA) | C72: Seltos | D72: Comfort | E72: THW52G61Q | F72: MX1EP81AKTK843834 | G72: SWP Snow White Pearl / Белый перламутр | H72: D420 | I72: 4WD | J72: CVT | K72: 1999 | L72: 2025 | M72: 363_292722 | N72: 46121 | O72: Бахытжан Смагулов | P72: Ким Людмила Леонидовна | Q72: 830515401760 | T72: 11590000 | U72: 11590000 | V72: 0 | W72: 0 | X72: 0 | Y72: 521550 | Z72: 521550 | AA72: 1s | AB72: 0.045 | AC72: =U72*AB72 -> 521550 | AD72: =AC72-V72 -> 521550 | AE72: 11 590 000.00 | AF72: 46122 | AG72: Алматы | AH72: Наличный расчет | AI72: Наличный расчет | AJ72: Без привлечения кредита | AM72: 0 | AN72: 1219 Алматы ТОО «ASTER Автомобили» (KIA) | AO72: 0 | AP72: 0 | AQ72: 132075016 | AR72: 152900 | AS72: 12128578 | AT72: 77012451110 | AU72: САП
A73: 1 | B73: 1169 Алматы ТОО «DCG ALMATY» (KIA) AMQ | C73: Seltos | D73: Comfort | E73: THW52G61Q | F73: MXREP81AKTY900617 | G73: SWP Snow White Pearl / Белый перламутр | H73: D420 | I73: 4WD | J73: CVT | K73: 1999 | L73: 2025 | M73: 1169_292806 | N73: 46122 | O73: Бахытжан Смагулов | P73: Ким Светлана Леонидовна | Q73: 810802401678 | T73: 11590000 | U73: 11590000 | V73: 0 | W73: 0 | X73: 0 | Y73: 521550 | Z73: 521550 | AA73: 1s | AB73: 0.045 | AC73: =U73*AB73 -> 521550 | AD73: =AC73-V73 -> 521550 | AE73: 11 590 000.00 | AF73: 46127 | AG73: Алматы | AH73: Наличный расчет | AI73: Наличный расчет | AJ73: Без привлечения кредита | AM73: 0 | AN73: 1174 Тараз ТОО «DCGTARAZ» (KIA) AMQ | AO73: 0 | AP73: 0 | AQ73: 132075254 | AR73: 152900 | AS73: 12128981 | AT73: 77008078077 | AU73: KKZ
A74: 1 | B74: 1173 Алматы ТОО «DCG Qulja» (KIA) AMQ | C74: Seltos | D74: Tulpar | E74: THW52G61Q | F74: MXRER81AKTY900552 | G74: FSB Modern Black / Черный | H74: G0EZ | I74: 4WD | J74: CVT | K74: 1999 | L74: 2025 | M74: 1173_293754 | N74: 46136 | O74: Дайана Калиаскар | P74: ШИРБЕКОВА ЕЛИНУР ХАМИТОВНА | Q74: 30105601152 | T74: 12990000 | U74: 12990000 | V74: 0 | W74: 0 | X74: 0 | Y74: 584550 | Z74: 584550 | AA74: 3s | AB74: 0.045 | AC74: =U74*AB74 -> 584550 | AD74: =AC74-V74 -> 584550 | AF74: 46141 | AG74: Алматы | AH74: Наличный расчет | AI74: Наличный расчет | AJ74: Без привлечения кредита | AM74: 0 | AO74: 0 | AP74: 0 | AQ74: 132076305 | AR74: 165900 | AS74: 12130376 | AT74: 77089697993 | AU74: KKZ
A75: 1 | B75: 1181 Усть-Каменогорск ТОО «DCG VOSTOK» (KIA) AMQ | C75: Seltos | D75: Luxe | E75: THW52G61Q | F75: MXRER81AKTY900167 | G75: KDG Gravity Gray / Серый | H75: G0DI | I75: 4WD | J75: CVT | K75: 1999 | L75: 2025 | M75: 1181_292514 | N75: 46118 | O75: Азамат Тоқтарбеков | P75: Әбілқайыров Абай Ержанұлы | Q75: 960305350727 | T75: 12840000 | U75: 12590000 | V75: 0 | W75: 0 | X75: 250000 | Y75: 566550 | Z75: 566550 | AA75: 1s | AB75: 0.045 | AC75: =U75*AB75 -> 566550 | AD75: =AC75-V75 -> 566550 | AE75: 3 000 000.00 | AF75: 46120 | AG75: Усть-Каменогорск | AH75: Кредит | AI75: Стандартное кредитование | AJ75: Halyk Bank | AK75: 84 месяца | AL75: 40 | AM75: 0 | AO75: 0 | AP75: 0 | AQ75: 132074828 | AR75: 160900 | AS75: 12130673 | AT75: 77776229688 | AU75: KKZ
A76: 1 | B76: 1174 Тараз ТОО «DCGTARAZ» (KIA) AMQ | C76: Seltos | D76: Luxe | E76: THW52G61V | F76: MXRER81AETY900130 | G76: F1D Clear White / Fusion Black | H76: G0DG | I76: 2WD | J76: CVT | K76: 1999 | L76: 2025 | M76: 1174_292777 | N76: 46121 | O76: Сұлтан Пойызбаев | P76: Сауранбаева Гульнур Сатыбалдиевна | Q76: 880405401157 | T76: 11990000 | U76: 11990000 | V76: 0 | W76: 0 | X76: 0 | Y76: 539550 | Z76: 539550 | AA76: 1s | AB76: 0.045 | AC76: =U76*AB76 -> 539550 | AD76: =AC76-V76 -> 539550 | AE76: 7 500 000.00 | AF76: 46126 | AG76: Тараз | AH76: Кредит | AI76: Стандартное кредитование | AJ76: Altyn Bank | AK76: 84 месяца | AL76: 60 | AM76: 0 | AN76: 1169 Алматы ТОО «DCG ALMATY» (KIA) AMQ | AO76: 0 | AP76: 0 | AQ76: 132075141 | AR76: 153900 | AS76: 12131877 | AT76: 77078580024 | AU76: KKZ
A77: 1 | B77: 1190 Шымкент ТОО «DCG ONTUSTIK» (KIA) AMQ | C77: Seltos | D77: Luxe | E77: THW52G61Q | F77: MXRER81AKTY900169 | G77: KLG Steel Gray / Стальной | H77: G0DI | I77: 4WD | J77: CVT | K77: 1999 | L77: 2025 | M77: 1190_293610 | N77: 46134 | O77: Абылайхан Нагибек | P77: Файзиева Айгуль Кожановна | Q77: 740210401486 | T77: 12590000 | U77: 12590000 | V77: 0 | W77: 0 | X77: 0 | Y77: 566550 | Z77: 566550 | AA77: 3s | AB77: 0.045 | AC77: =U77*AB77 -> 566550 | AD77: =AC77-V77 -> 566550 | AF77: 46135 | AG77: Шымкент | AH77: Безналичный расчет | AI77: Безналичный | AJ77: Без привлечения кредита | AM77: 0 | AO77: 0 | AP77: 0 | AQ77: 132075932 | AR77: 160900 | AS77: 12136062 | AT77: 77756869503 | AU77: KKZ
A78: 1 | B78: 1190 Шымкент ТОО «DCG ONTUSTIK» (KIA) AMQ | C78: Seltos | D78: Tulpar | E78: THW52G61Q | F78: MXRER81AKTY900585 | G78: KLG Steel Gray / Стальной | H78: G0EZ | I78: 4WD | J78: CVT | K78: 1999 | L78: 2025 | M78: 1190_294170 | N78: 46142 | O78: Нұрсұлтан Көкежан | P78: Сарсенбаева Равия Кудайбергеновна | Q78: 480815401427 | T78: 12990000 | U78: 12990000 | V78: 0 | W78: 0 | X78: 0 | Y78: 584550 | Z78: 584550 | AA78: 3s | AB78: 0.045 | AC78: =U78*AB78 -> 584550 | AD78: =AC78-V78 -> 584550 | AF78: 46142 | AG78: Шымкент | AH78: Безналичный расчет | AI78: Безналичный | AJ78: Без привлечения кредита | AM78: 0 | AO78: 0 | AP78: 0 | AQ78: 132076701 | AR78: 165900 | AS78: 12136065 | AT78: 77028480611 | AU78: KKZ
A79: 1 | B79: 1190 Шымкент ТОО «DCG ONTUSTIK» (KIA) AMQ | C79: Seltos | D79: Comfort | E79: THW52G61Q | F79: MXREP81AKTY900616 | G79: SWP Snow White Pearl / Белый перламутр | H79: D420 | I79: 4WD | J79: CVT | K79: 1999 | L79: 2025 | M79: 1190_293007 | N79: 46125 | O79: Арман Сабыров | P79: Мухтарханова Наргиза Абдирасуловна | Q79: 850408402047 | T79: 11840000 | U79: 11590000 | V79: 0 | W79: 0 | X79: 250000 | Y79: 521550 | Z79: 521550 | AA79: 3s | AB79: 0.045 | AC79: =U79*AB79 -> 521550 | AD79: =AC79-V79 -> 521550 | AE79: 2 368 000.00 | AF79: 46128 | AG79: Шымкент | AH79: Кредит | AI79: Стандартное кредитование | AJ79: Altyn Bank | AK79: 84 месяца | AL79: 20 | AM79: 0 | AO79: 0 | AP79: 0 | AQ79: 132075299 | AR79: 152900 | AS79: 12136066 | AT79: 77758855033 | AU79: KKZ
A80: 1 | B80: 1190 Шымкент ТОО «DCG ONTUSTIK» (KIA) AMQ | C80: Soluto | D80: Prestige | E80: H7S4K461B | F80: MXR0AA29XTY901076 | G80: GY1 / Distinct Yellow / желтый | H80: G623 | J80: AUTOT/M | K80: 1368 | L80: 2025 | M80: 1190_292230 | N80: 46113 | O80: Нұрсұлтан Көкежан | R80: ИП "Keruen" | S80: 960103000298 | T80: 7590000 | U80: 7590000 | V80: 0 | W80: 0 | X80: 0 | Y80: 300000 | Z80: 300000 | AA80: 3s | AB80: 300000 | AC80: =AB80 -> 300000 | AD80: =AC80-V80 -> 300000 | AF80: 46114 | AG80: Шымкент | AH80: Безналичный расчет | AI80: Безналичный | AJ80: Без привлечения кредита | AM80: 0 | AO80: 0 | AP80: 0 | AS80: 12136068 | AT80: 77028499364 | AU80: KKZ
A81: 1 | B81: 363 Алматы ТОО «DCG ALMATY» (KIA) | C81: Carnival | D81: Luxe+ | E81: HSB8J961J | F81: MX1NB814BTK591313 | G81: ISG / Ivory Silver/Серебро слоновой кости / Серый | H81: D324 | I81: 2WD | J81: AT | K81: 3470 | L81: 2025 | M81: 363_292868 | N81: 46125 | O81: Адема Алибекова | P81: Бабахунов Ришад Сыдыкович | Q81: 820506300329 | T81: 22290000 | U81: 21990000 | V81: 0 | W81: 0 | X81: 300000 | Y81: 1429350 | Z81: 1429350 | AA81: 1s | AB81: 0.055 | AC81: =U81*AB81 -> 1209450 | AD81: =AC81-V81 -> 1209450 | AE81: 6 800 000.00 | AF81: 46126 | AG81: Алматы | AH81: Кредит | AI81: Стандартное кредитование | AJ81: Altyn Bank | AK81: 48 месяцев | AL81: 30 | AM81: 0 | AO81: 0 | AP81: 0 | AQ81: 132075161 | AR81: 229900 | AS81: 12141014 | AT81: 77017019991 | AU81: САП
A82: 1 | B82: 735 Усть-Каменогорск ТОО «DCG VOSTOK» (KIA) | C82: Sorento 2025 | D82: Luxe | E82: GZW7L961G | F82: MX1RH81DDTK379413 | G82: KLG Steel Gray / Стальной | H82: G2IJ | I82: 4WD | J82: AT | K82: 2497 | L82: 2025 | M82: 735_293652 | N82: 46135 | O82: Азамат Тоқтарбеков | P82: Айтамбаев Нурбол Нурбекович | Q82: 611211300949 | T82: 18390000 | U82: 18390000 | V82: 0 | W82: 0 | X82: 0 | Y82: 1011450 | Z82: 1011450 | AA82: 1s | AB82: 0.045 | AC82: =U82*AB82 -> 827550 | AD82: =AC82-V82 -> 827550 | AE82: 10 000 000.00 | AF82: 46140 | AG82: Усть-Каменогорск | AH82: Кредит | AI82: Стандартное кредитование | AJ82: Банк ЦентрКредит | AK82: 84 месяца | AL82: 55 | AM82: 0 | AO82: 0 | AP82: 0 | AQ82: 132076190 | AR82: 229900 | AS82: 12145739 | AT82: 77764438855 | AU82: САП
A83: 1 | B83: 1151 Алматы ТОО «DCG Qulja» (KIA) | C83: Sorento 2025 | D83: Comfort | E83: GZW5L961G | F83: MX1RH81DDTK374746 | G83: SWP Snow White Pearl / Белый перламутр | H83: G2IF | I83: 4WD | J83: AT | K83: 2497 | L83: 2025 | M83: 1151_292768 | N83: 46121 | O83: Дайана Калиаскар | P83: Байтенов Ерболат Абдикалиевич | Q83: 920112300165 | T83: 16990000 | U83: 16990000 | V83: 0 | W83: 0 | X83: 0 | Y83: 934450 | Z83: 934450 | AA83: 3s | AB83: 0.045 | AC83: =U83*AB83 -> 764550 | AD83: =AC83-V83 -> 764550 | AE83: 3 990 000.00 | AF83: 46126 | AG83: Алматы | AH83: Кредит | AI83: Стандартное кредитование | AJ83: МФО Sapa Digital Finance | AK83: 84 месяца | AL83: 23 | AM83: 0 | AO83: 0 | AP83: 0 | AQ83: 132075099 | AR83: 216900 | AS83: 12147766 | AT83: 77778474602 | AU83: САП
A84: 1 | B84: 1151 Алматы ТОО «DCG Qulja» (KIA) | C84: Sorento 2025 | D84: Comfort | E84: GZW5L961G | F84: MX1RH81DDTK376595 | G84: ABP Aurora Black Pearl / Чёрный перламутр | H84: G2IF | I84: 4WD | J84: AT | K84: 2497 | L84: 2025 | M84: 1151_293171 | N84: 46128 | O84: Мади Мынбаев | P84: КУАНДЫКОВ МУХТАР АБДУАЛЫУЛЫ | Q84: 920321300106 | T84: 17290000 | U84: 16990000 | V84: 0 | W84: 0 | X84: 300000 | Y84: 934450 | Z84: 934450 | AA84: 3s | AB84: 0.045 | AC84: =U84*AB84 -> 764550 | AD84: =AC84-V84 -> 764550 | AE84: 12 000 000.00 | AF84: 46132 | AG84: Алматы | AH84: Кредит | AI84: Стандартное кредитование | AJ84: Береке Банк | AK84: 60 месяцев | AL84: 70 | AM84: 0 | AO84: 0 | AP84: 0 | AQ84: 132075542 | AR84: 216900 | AS84: 12147768 | AT84: 77019289222 | AU84: САП
A85: 1 | B85: 1192 Павлодар ТОО «DCG ERTIS» (KIA) AMQ | C85: K5 | D85: Comfort | E85: EUS4D6G1U | F85: MXR6AA2D5TY900296 | G85: SWP Snow White Pearl / Белый перламутр | H85: D055 | I85: 2WD | J85: DCT | K85: 1497 | L85: 2025 | M85: 1192_294036 | N85: 46140 | O85: Алишер Сериков | P85: Якименко Оксана Сергеевна | Q85: 800728402226 | T85: 10990000 | U85: 10990000 | V85: 0 | W85: 0 | X85: 0 | Y85: 604450 | Z85: 604450 | AA85: 3s | AB85: 0.055 | AC85: =U85*AB85 -> 604450 | AD85: =AC85-V85 -> 604450 | AE85: 1 500 000.00 | AF85: 46142 | AG85: Павлодар | AH85: Кредит | AI85: Стандартное кредитование | AJ85: Береке Банк | AK85: 84 месяца | AL85: 13 | AM85: 0 | AN85: 1236 Астана Филиал ТОО «ASTER Автомобили» (KIA) AMQ | AO85: 0 | AP85: 0 | AQ85: 132076638 | AR85: 157900 | AS85: 12155439 | AT85: 77025894830 | AU85: KKZ
A86: 1 | B86: 1192 Павлодар ТОО «DCG ERTIS» (KIA) AMQ | C86: K5 | D86: Luxe | E86: EUS42JG1J | F86: MXR6AA24XTY900209 | G86: AG2 Graphite Gray / Серый | H86: G155 | I86: 2WD | J86: AUTOT/M | K86: 1975 | L86: 2025 | M86: 1192_292540 | N86: 46119 | O86: ЕРЖАН КАРАМЕНДИНОВ | P86: Баймурунова Гульнара Сабировна | Q86: 760819401430 | T86: 12690000 | U86: 12690000 | V86: 0 | W86: 0 | X86: 0 | Y86: 697950 | Z86: 697950 | AA86: 3s | AB86: 0.055 | AC86: =U86*AB86 -> 697950 | AD86: =AC86-V86 -> 697950 | AE86: 1 903 500.00 | AF86: 46125 | AG86: Павлодар | AH86: Кредит | AI86: Стандартное кредитование | AJ86: Банк ЦентрКредит | AK86: 60 месяцев | AL86: 15 | AM86: 0 | AO86: 0 | AP86: 0 | AQ86: 132075031 | AS86: 12155440 | AT86: 77777103050 | AU86: KKZ
A87: 1 | B87: 1169 Алматы ТОО «DCG ALMATY» (KIA) AMQ | C87: K5 | D87: Luxe | E87: EUS42JG1J | F87: MXR6AA242TY900238 | G87: SWP Snow White Pearl / Белый перламутр | H87: G155 | J87: AUTOT/M | K87: 1975 | L87: 2025 | M87: 1169_292303 | N87: 46115 | O87: Азамат Жұмахметов | P87: Болебаев Азат Жумагазыевич | Q87: 921224350049 | T87: 12990000 | U87: 12690000 | V87: 0 | W87: 0 | X87: 300000 | Y87: 752950 | Z87: 752950 | AA87: 1s | AB87: 0.045 | AC87: =U87*AB87 -> 571050 | AD87: =AC87-V87 -> 571050 | AE87: 1 300 000.00 | AF87: 46118 | AG87: Алматы | AH87: Кредит | AI87: Стандартное кредитование | AJ87: Банк ЦентрКредит | AK87: 84 месяца | AL87: 10 | AM87: 0 | AO87: 0 | AP87: 0 | AQ87: 132074675 | AS87: 12164059 | AT87: 77070191202 | AU87: KKZ
A88: 1 | B88: 1173 Алматы ТОО «DCG Qulja» (KIA) AMQ | C88: K5 | D88: Luxe | E88: EUS42JG1J | F88: MXR6AA244TY900208 | G88: AG2 Graphite Gray / Серый | H88: G155 | I88: 2WD | J88: AUTOT/M | K88: 1975 | L88: 2025 | M88: 1173_292945 | N88: 46125 | O88: Ерик Серкешбаев | P88: Тапаев Жаксылык Кенесович | Q88: 760414301735 | T88: 12940000 | U88: 12690000 | V88: 0 | W88: 0 | X88: 250000 | Y88: 697950 | Z88: 697950 | AA88: 3s | AB88: 0.055 | AC88: =U88*AB88 -> 697950 | AD88: =AC88-V88 -> 697950 | AE88: 10 000 000.00 | AF88: 46128 | AG88: Алматы | AH88: Кредит | AI88: Стандартное кредитование | AJ88: Банк ЦентрКредит | AK88: 84 месяца | AL88: 79 | AM88: 0 | AO88: 0 | AP88: 0 | AQ88: 132075320 | AS88: 12165236 | AT88: 77074990334 | AU88: KKZ
A89: 1 | B89: 1069 Актау TOO «DCG Aktau» (KIA) | C89: Sportage | D89: Luxe | E89: GYWDL9A1K | F89: MX1PV81FDTK021857 | G89: KLG Steel Gray / Стальной | H89: G0P1 | I89: 4WD | J89: AT | K89: 2497 | L89: 2025 | M89: 1069_293210 | N89: 46128 | O89: Тимур Нурибаев | P89: Асанова Светлана Шукирбаевна | Q89: 760227401244 | T89: 13990000 | U89: 13990000 | V89: 0 | W89: 0 | X89: 0 | Y89: 769450 | Z89: 769450 | AA89: 3s | AB89: 0.055 | AC89: =U89*AB89 -> 769450 | AD89: =AC89-V89 -> 769450 | AE89: 13 990 000.00 | AF89: 46132 | AG89: Актау | AH89: Наличный расчет | AI89: Наличный расчет | AJ89: Без привлечения кредита | AM89: 0 | AO89: 0 | AP89: 0 | AQ89: 132075549 | AR89: 187900 | AS89: 12169811 | AT89: 77016636613 | AU89: САП
A90: 1 | B90: 331 Шымкент ТОО «DCG ONTUSTIK» (KIA) | C90: Soul | D90: Luxe | E90: SKW5D261F | F90: MX1J381EBSK274621 | G90: F1D Clear White / Fusion Black | H90: G904 | I90: 2WD | J90: AT | K90: 1591 | L90: 2025 | M90: 331_293913 | N90: 46139 | O90: Ернар Жайдарбек | P90: Кучкарова Меруерт Барысбековна | Q90: 851219400918 | T90: 12240000 | U90: 11690000 | V90: 0 | W90: 0 | X90: 550000 | Y90: 526050 | Z90: 526050 | AA90: 3s | AB90: 0.045 | AC90: =U90*AB90 -> 526050 | AD90: =AC90-V90 -> 526050 | AE90: 2 000 000.00 | AF90: 46142 | AG90: Шымкент | AH90: Кредит | AI90: Стандартное кредитование | AJ90: МФО Sapa Digital Finance | AK90: 84 месяца | AL90: 20 | AM90: 0 | AN90: 343 Талдыкорган ТОО «Taldykorgan Auto Group» (KIA) | AO90: 0 | AP90: 0 | AQ90: 132076785 | AR90: 130900 | AS90: 12171459 | AT90: 77087576545 | AU90: САП
A91: 1 | B91: 371 Астана ТОО «DCG ASTANA» (KIA) | C91: Soul | D91: Luxe | E91: SKW5D261F | F91: MX1J381EBSK273139 | G91: F1D Clear White / Fusion Black | H91: G904 | I91: 2WD | J91: AT | K91: 1591 | L91: 2025 | M91: 371_293468 | N91: 46132 | O91: Виктория Чубинец | P91: Галиева Динара Бауыржановна | Q91: 841126450293 | T91: 11940000 | U91: 11690000 | V91: 0 | W91: 0 | X91: 250000 | Y91: 526050 | Z91: 526050 | AA91: 1s | AB91: 0.045 | AC91: =U91*AB91 -> 526050 | AD91: =AC91-V91 -> 526050 | AE91: 1 200 000.00 | AF91: 46134 | AG91: Астана | AH91: Кредит | AI91: Стандартное кредитование | AJ91: Евразийский банк | AK91: 84 месяца | AL91: 10 | AM91: 0 | AO91: 0 | AP91: 0 | AQ91: 132075831 | AR91: 130900 | AS91: 12171759 | AT91: 77013060678 | AU91: САП
A92: 1 | B92: 363 Алматы ТОО «DCG ALMATY» (KIA) | C92: Sportage | D92: Luxe | E92: GYWD2J61G | F92: MX1PV81DDTK021235 | G92: FSB Modern Black / Черный | H92: G0P1 | I92: 4WD | J92: AT | K92: 1999 | L92: 2025 | M92: 363_292933 | N92: 46125 | O92: Адема Алибекова | P92: Султамуратова Әсия Қанатқызы | Q92: 810928402106 | T92: 13490000 | U92: 13490000 | V92: 0 | W92: 0 | X92: 0 | Y92: 741950 | Z92: 741950 | AA92: 1s | AB92: 0.045 | AC92: =U92*AB92 -> 607050 | AD92: =AC92-V92 -> 607050 | AE92: 1 349 000.00 | AF92: 46127 | AG92: Алматы | AH92: Льготный кредит | AI92: Льготное кредитование | AJ92: Банк ЦентрКредит | AK92: 84 месяца | AL92: 10 | AM92: 0 | AO92: 0 | AP92: 0 | AQ92: 132075266 | AR92: 181900 | AS92: 12179876 | AT92: 77012881616 | AU92: САП
A93: 1 | B93: 1151 Алматы ТОО «DCG Qulja» (KIA) | C93: Soul | D93: Luxe | E93: SKW5D261F | F93: MX1J381EBTK274171 | G93: KDG Gravity Gray / Серый | H93: G904 | I93: 2WD | J93: AT | K93: 1591 | L93: 2025 | M93: 1151_292967 | N93: 46126 | O93: Амир Мамедов | P93: АТАНБЕКОВА ЛАУРА ДАРУБАЙҚЫЗЫ | Q93: 780618400087 | T93: 11990000 | U93: 11690000 | V93: 0 | W93: 0 | X93: 300000 | Y93: 526050 | Z93: 526050 | AA93: 3s | AB93: 0.045 | AC93: =U93*AB93 -> 526050 | AD93: =AC93-V93 -> 526050 | AE93: 8 000 000.00 | AF93: 46127 | AG93: Алматы | AH93: Кредит | AI93: Стандартное кредитование | AJ93: МФО Sapa Digital Finance | AK93: 24 месяца | AL93: 67 | AM93: 0 | AO93: 0 | AP93: 0 | AQ93: 132075247 | AR93: 130900 | AS93: 12179887 | AT93: 77011813378 | AU93: САП
A94: 1 | B94: 1151 Алматы ТОО «DCG Qulja» (KIA) | C94: Cerato | D94: Luxe+ | E94: DJS42G61F | F94: MX1F441CBTK006485 | G94: UD Clear White / Белый | H94: G02O | I94: 2WD | J94: AT | K94: 2 | L94: 2025 | M94: 1151_294044 | N94: 46141 | O94: Ерик Серкешбаев | P94: Уәтаев Елнұр Ғизатұлы | Q94: 51025550275 | T94: 10990000 | U94: 10990000 | V94: 0 | W94: 0 | X94: 0 | Y94: 439600 | Z94: 439600 | AA94: 3s | AB94: 0.04 | AC94: =U94*AB94 -> 439600 | AD94: =AC94-V94 -> 439600 | AF94: 46142 | AG94: Алматы | AH94: Наличный расчет | AI94: Наличный расчет | AJ94: Без привлечения кредита | AM94: 0 | AN94: 363 Алматы ТОО «DCG ALMATY» (KIA) | AO94: 0 | AP94: 0 | AQ94: 132076675 | AS94: 12185769 | AT94: 77786347407 | AU94: САП
A95: 1 | B95: 363 Алматы ТОО «DCG ALMATY» (KIA) | C95: Sportage | D95: Luxe | E95: GYWDL9A1K | F95: MX1PV81FDTK021834 | G95: KLG Steel Gray / Стальной | H95: G0P1 | I95: 4WD | J95: AT | K95: 2497 | L95: 2025 | M95: 363_293276 | N95: 46129 | O95: Азамат Жұмахметов | P95: Алданова Гулбиби Оразхановна | Q95: 801217402300 | T95: 13990000 | U95: 13990000 | V95: 0 | W95: 0 | X95: 0 | Y95: 769450 | Z95: 769450 | AA95: 1s | AB95: 0.045 | AC95: =U95*AB95 -> 629550 | AD95: =AC95-V95 -> 629550 | AE95: 2 798 000.00 | AF95: 46139 | AG95: Алматы | AH95: Льготный кредит | AI95: Льготное кредитование | AJ95: Fortebank | AK95: 84 месяца | AL95: 20 | AM95: 0 | AO95: 0 | AP95: 0 | AQ95: 132076155 | AR95: 187900 | AS95: 12187607 | AT95: 77071195643 | AU95: САП
A96: 1 | B96: 363 Алматы ТОО «DCG ALMATY» (KIA) | C96: Sportage | D96: Luxe | E96: GYWDL9A1K | F96: MX1PV81FDTK021828 | G96: KLG Steel Gray / Стальной | H96: G0P1 | I96: 4WD | J96: AT | K96: 2497 | L96: 2025 | M96: 363_293019 | N96: 46126 | O96: Адема Алибекова | P96: Жолмурзаев Адилет Нуртасович | Q96: 900416300268 | T96: 14240000 | U96: 13990000 | V96: 0 | W96: 0 | X96: 250000 | Y96: 769450 | Z96: 769450 | AA96: 1s | AB96: 0.045 | AC96: =U96*AB96 -> 629550 | AD96: =AC96-V96 -> 629550 | AE96: 6 500 000.00 | AF96: 46127 | AG96: Алматы | AH96: Кредит | AI96: Стандартное кредитование | AJ96: Halyk Bank | AK96: 60 месяцев | AL96: 45 | AM96: 0 | AO96: 0 | AP96: 0 | AQ96: 132075261 | AR96: 187900 | AS96: 12187609 | AT96: 77056663670 | AU96: САП
A97: 1 | B97: 363 Алматы ТОО «DCG ALMATY» (KIA) | C97: Cerato | D97: Comfort | E97: DJS4D261F | F97: MX1F3416BTK006548 | G97: UD Clear White / Белый | H97: D0A6 | I97: 2WD | J97: AT | K97: 1591 | L97: 2025 | M97: 363_292459 | N97: 46118 | O97: Абылай Куттыбай | P97: Зайитов Мухлис Мундашович | Q97: 740321301364 | T97: 9990000 | U97: 9990000 | V97: 0 | W97: 0 | X97: 0 | Y97: 399600 | Z97: 399600 | AA97: 1s | AB97: 0.04 | AC97: =U97*AB97 -> 399600 | AD97: =AC97-V97 -> 399600 | AE97: 9 990 000.00 | AF97: 46122 | AG97: Алматы | AH97: Наличный расчет | AI97: Наличный расчет | AJ97: Без привлечения кредита | AM97: 0 | AO97: 0 | AP97: 0 | AQ97: 132075007 | AS97: 12187638 | AT97: 77012451110 | AU97: САП
A98: 1 | B98: 1151 Алматы ТОО «DCG Qulja» (KIA) | C98: Sportage | D98: Luxe | E98: GYWDL9A1K | F98: MX1PV81FDTK021897 | G98: KDG Gravity Gray / Серый | H98: G0P1 | I98: 4WD | J98: AT | K98: 2497 | L98: 2025 | M98: 1151_293213 | N98: 46129 | O98: Ерик Серкешбаев | P98: Турдиева Асемгул Кайнелденовна | Q98: 770706401329 | T98: 13990000 | U98: 13990000 | V98: 0 | W98: 0 | X98: 0 | Y98: 769450 | Z98: 769450 | AA98: 3s | AB98: 0.055 | AC98: =U98*AB98 -> 769450 | AD98: =AC98-V98 -> 769450 | AE98: 3 990 000.00 | AF98: 46135 | AG98: Алматы | AH98: Льготный кредит | AI98: Льготное кредитование | AJ98: Halyk Bank | AK98: 84 месяца | AL98: 25 | AM98: 0 | AO98: 0 | AP98: 0 | AQ98: 132075953 | AR98: 187900 | AS98: 12189860 | AT98: 77472648252 | AU98: САП
A99: 1 | B99: 1151 Алматы ТОО «DCG Qulja» (KIA) | C99: Sportage | D99: Luxe | E99: GYWDL9A1K | F99: MX1PV81FDTK021898 | G99: KDG Gravity Gray / Серый | H99: G0P1 | I99: 4WD | J99: AT | K99: 2497 | L99: 2025 | M99: 1151_293530 | N99: 46133 | O99: Ерик Серкешбаев | P99: Айдосқызы Айша | Q99: 509601956 | T99: 13990000 | U99: 13990000 | V99: 0 | W99: 0 | X99: 0 | Y99: 769450 | Z99: 769450 | AA99: 3s | AB99: 0.055 | AC99: =U99*AB99 -> 769450 | AD99: =AC99-V99 -> 769450 | AE99: 1 400 000.00 | AF99: 46136 | AG99: Алматы | AH99: Кредит | AI99: Стандартное кредитование | AJ99: Банк ЦентрКредит | AK99: 84 месяца | AL99: 10 | AM99: 0 | AO99: 0 | AP99: 0 | AQ99: 132076011 | AR99: 187900 | AS99: 12189870 | AT99: 77478447253 | AU99: САП
A100: 1 | B100: 363 Алматы ТОО «DCG ALMATY» (KIA) | C100: Cerato | D100: Luxe+ | E100: DJS42G61F | F100: MX1F441CBSK003698 | G100: KDG Gravity Gray / Серый | H100: G02O | I100: 2WD | J100: AT | K100: 2 | L100: 2025 | M100: 363_293689 | N100: 46135 | O100: Даур Құттыбай | P100: Тұрғанбаев Мерей Мейрамханұлы | Q100: 940917301831 | T100: 11290000 | U100: 10990000 | V100: 0 | W100: 0 | X100: 300000 | Y100: 439600 | Z100: 439600 | AA100: 1s | AB100: 0.04 | AC100: =U100*AB100 -> 439600 | AD100: =AC100-V100 -> 439600 | AE100: 1 130 000.00 | AF100: 46140 | AG100: Алматы | AH100: Кредит | AI100: Стандартное кредитование | AJ100: МФО Sapa Digital Finance | AK100: 84 месяца | AL100: 10 | AM100: 0 | AO100: 0 | AP100: 0 | AQ100: 132076187 | AS100: 12197443 | AT100: 77767769595 | AU100: САП
...

Sheet Лист1
B1: до 03.04 | D1: 46115 | F1: 46132
B2: 1s | C2: 3s | D2: 1s | E2: 3s | F2: 1s | G2: 3s
A3: Carnival | B3: =C3-1% -> 0.055 | C3: 0.065 | D3: =E3-1% -> 0.055 | E3: 0.065 | F3: =G3-1% -> 0.055 | G3: 0.065
A4: Ceed | B4: 0.045 | C4: 0.045 | D4: 0.045 | E4: 0.045 | F4: 0.045 | G4: 0.045
A5: Ceed SW | B5: 0.045 | C5: 0.045 | D5: 0.045 | E5: 0.045 | F5: 0.045 | G5: 0.045
A6: Cerato | B6: 0.04 | C6: 0.04 | D6: 0.04 | E6: 0.04 | F6: 0.04 | G6: 0.04
A7: K5 | B7: =C7-1% -> 0.045 | C7: 0.055 | D7: =E7-1% -> 0.045 | E7: 0.055 | F7: =G7-1% -> 0.045 | G7: 0.055
A8: K8 | B8: =C8-1% -> 0.055 | C8: 0.065 | D8: =E8-1% -> 0.055 | E8: 0.065 | F8: =G8-1% -> 0.055 | G8: 0.065
A9: Seltos | B9: 0.045 | C9: 0.045 | D9: 0.045 | E9: 0.045 | F9: 0.045 | G9: 0.045
A10: Soluto | B10: 300000 | C10: 300000 | D10: 300000 | E10: 300000 | F10: 300000 | G10: 300000
A11: Sorento 2026 | B11: =C11-1% -> 0.045 | C11: 0.055 | D11: =E11-1% -> 0.045 | E11: 0.055 | F11: 0.045 | G11: 0.045
A12: Sorento 2025 | B12: 0.045 | C12: 0.045 | D12: 0.045 | E12: 0.045 | F12: =G12-1% -> 0.045 | G12: 0.055
A13: Soul | B13: 0.045 | C13: 0.045 | D13: 0.045 | E13: 0.045 | F13: 0.045 | G13: 0.045
A14: Sportage | B14: =C14-1% -> 0.045 | C14: 0.055 | D14: =E14-1% -> 0.045 | E14: 0.055 | F14: =G14-1% -> 0.045 | G14: 0.055
A15: Sportage comfort | B15: 0.03 | C15: 0.03 | D15: 0.03 | E15: 0.03 | F15: 0.03 | G15: 0.03

Sheet Анализ Шеви
A3: ДЦ | B3: Кол | C3: РРЦ | D3: ДОП | E3: Маржа | F3: Средний маржа | G3: %
A4: 1085 Актау ТОО «AUTOCENTER ONTUSTIK» (Chevrolet) | B4: 91 | C4: 6103186.8 | D4: 8430000 | E4: 20700000 | F4: =E4/B4 -> 227472.53 | G4: =F4/C4 -> 0.037271107
A5: 1120 Атырау ТОО «AUTOCENTER ONTUSTIK» (Chevrolet) | B5: 72 | C5: 6144166.7 | D5: 2350000 | E5: 17100000 | F5: =E5/B5 -> 237500 | G5: =F5/C5 -> 0.03865455
A6: 1159 Алматы ТОО «AUTOCENTER ONTUSTIK» (Chevrolet) | B6: 4 | C6: 6765000 | D6: 900000 | E6: 1200000 | F6: =E6/B6 -> 300000 | G6: =F6/C6 -> 0.044345898
A7: 119 Шымкент ТОО «AUTOCENTER ONTUSTIK» (Chevrolet) | B7: 375 | C7: 6365466.7 | D7: 15165000 | E7: 82340000 | F7: =E7/B7 -> 219573.33 | G7: =F7/C7 -> 0.03449446
A8: 1267 Алматы TOO «DCG Zhetysu» (Chevrolet) | B8: 72 | C8: 7270555.6 | D8: 0 | E8: 17450000 | F8: =E8/B8 -> 242361.11 | G8: =F8/C8 -> 0.033334607
A9: 397 Тараз ТОО «AUTOCENTER ONTUSTIK» (Chevrolet) | B9: 118 | C9: 6153559.3 | D9: 6850000 | E9: 25950000 | F9: =E9/B9 -> 219915.25 | G9: =F9/C9 -> 0.035737895
A10: 858 Астана ТОО «DCG Astana» (Chevrolet) | B10: 108 | C10: 7463240.7 | D10: 3897000 | E10: 29000000 | F10: =E10/B10 -> 268518.52 | G10: =F10/C10 -> 0.03597881
A11: 866 Усть-Каменогорск ТОО «DCG VOSTOK» (Chevrolet) | B11: 130 | C11: 6150769.2 | D11: 12140000 | E11: 29500000 | F11: =E11/B11 -> 226923.08 | G11: =F11/C11 -> 0.036893447
A12: 872 Павлодар ТОО «DCG ERTIS» (Chevrolet) | B12: 94 | C12: 6692659.6 | D12: 4770000 | E12: 23100000 | F12: =E12/B12 -> 245744.68 | G12: =F12/C12 -> 0.036718539
A13: 920 Уральск ТОО «AUTOCENTER ONTUSTIK» (Chevrolet) | B13: 124 | C13: 6254919.4 | D13: 3201850 | E13: 29050000 | F13: =E13/B13 -> 234274.19 | G13: =F13/C13 -> 0.037454391
A14: 922 Кызылорда ТОО «AUTOCENTER ONTUSTIK» (Chevrolet) | B14: 130 | C14: 6141538.5 | D14: 5890000 | E14: 28700000 | F14: =E14/B14 -> 220769.23 | G14: =F14/C14 -> 0.035946894
A15: 935 Шымкент TOO «AUTOCENTER ONTUSTIK» Байдибек би (Chevrolet) | B15: 469 | C15: 6481897.7 | D15: 30654500 | E15: 108040000 | F15: =E15/B15 -> 230362.47 | G15: =F15/C15 -> 0.035539357
A16: Общий итог | B16: 1787 | C16: 6441096.8 | D16: 94248350 | E16: 412130000 | F16: =E16/B16 -> 230626.75 | G16: =F16/C16 -> 0.035805509
A21: Модель | B21: Кол | C21: РРЦ | D21: Ср Маржа | E21: % | F21: % авто
A22: Cobalt | B22: 1748 | C22: 6142860.4 | D22: 223586.96 | E22: =D22/C22 -> 0.036397857 | F22: =B22/$B$27 -> 0.97817571
A23: Labo | B23: 3 | C23: 5590000 | D23: 200000 | E23: =D23/C23 -> 0.035778175 | F23: =B23/$B$27 -> 0.0016787913
A24: Onix | B24: 23 | C24: 7650869.6 | D24: 330434.78 | E24: =D24/C24 -> 0.04318918 | F24: =B24/$B$27 -> 0.012870733
A25: Tahoe MY25 | B25: 11 | C25: 50800000 | D25: 1118181.8 | E25: =D25/C25 -> 0.022011453 | F25: =B25/$B$27 -> 0.006155568
A26: Tracker MY22 | B26: 2 | C26: 10490000 | D26: 400000 | E26: =D26/C26 -> 0.038131554 | F26: =B26/$B$27 -> 0.0011191942
A27: Общий итог | B27: 1787 | C27: 6441096.8 | D27: 230626.75 | E27: =D27/C27 -> 0.035805509 | F27: =B27/$B$27 -> 1
A30: Сумма скидки | B30: (несколько элементов)
A32: ДЦ | B32: Коли | C32: Скидка
A33: 1085 Актау ТОО «AUTOCENTER ONTUSTIK» (Chevrolet) | B33: 16 | C33: 550000
A34: 1120 Атырау ТОО «AUTOCENTER ONTUSTIK» (Chevrolet) | B34: 12 | C34: 700000
A35: 119 Шымкент ТОО «AUTOCENTER ONTUSTIK» (Chevrolet) | B35: 4 | C35: 1260000
A36: 1267 Алматы TOO «DCG Zhetysu» (Chevrolet) | B36: 1 | C36: 1000000
A37: 397 Тараз ТОО «AUTOCENTER ONTUSTIK» (Chevrolet) | B37: 12 | C37: 600000
A38: 935 Шымкент TOO «AUTOCENTER ONTUSTIK» Байдибек би (Chevrolet) | B38: 3 | C38: 60000
A39: Общий итог | B39: 48 | C39: 4170000

Sheet Шеви
A1: Кол-во | B1: Название ДЦ | C1: Модель CHEVROLET! | D1: Комплектация CHEVROLET | E1: Цвет УС CHEVROLET | F1: VIN KZ | G1: Номер договора | H1: Дата договора | I1: Ответственный | J1: ФИО | K1: Контакт: ИИН/БИН | L1: Компания: Название компании | M1: Компания: БИН | N1: Телефон | O1: Цена реализации | P1: Рекомендуемая розничная цена | Q1: Сумма скидки | R1: Стоимость доп. оборудования | S1: Максимальное вознаграждение дилера | T1: Вознаграждение без скидки | U1: Тип продажи А/М | V1: Источник для отчета (archived) | W1: Место реализации (город) | X1: Дата подписания акта п/п | Y1: Кредит в банке | Z1: Число попаданий на замечания | AA1: ID | AB1: Название ДЦ. откуда забрали машину | AC1: Вознаграждение дилера (за перемещённую машину) | AD1: Способ приобретения | AE1: Год выпуска
A2: 1 | B2: 1120 Атырау ТОО «AUTOCENTER ONTUSTIK» (Chevrolet) | C2: Cobalt | D2: Elegant AT | E2: GUM Бирюзовый | F2: MX1JA69V9SK527884 | G2: 1120_306361 | H2: 46110 | I2: Галимжан Жулкашов | J2: Ермышева Майра Рыспаевна | K2: 730513401174 | N2: 77014678471 | O2: 6490000 | P2: 6490000 | Q2: 0 | R2: 0 | S2: 300000 | T2: 300000 | U2: Безналичный расчет | W2: Атырау | X2: 46113 | Y2: Без привлечения кредита | Z2: 0 | AA2: 8778428 | AC2: 0 | AD2: Безналичный | AE2: 2025
A3: 1 | B3: 1085 Актау ТОО «AUTOCENTER ONTUSTIK» (Chevrolet) | C3: Cobalt | D3: Elegant AT | E3: GUM Бирюзовый | F3: MX1JA69V9SK527833 | G3: 1085_306849 | H3: 46115 | I3: Алтынбек Абилов | J3: Базаров Мухит Маметович | K3: 900216301417 | N3: 77053726978 | O3: 6725000 | P3: 6490000 | Q3: 0 | R3: 235000 | S3: 300000 | T3: 300000 | U3: Кредит | W3: Актау | X3: 46119 | Y3: Береке Банк | Z3: 0 | AA3: 8779692 | AC3: 0 | AD3: Стандартное кредитование | AE3: 2025
A4: 1 | B4: 1120 Атырау ТОО «AUTOCENTER ONTUSTIK» (Chevrolet) | C4: Cobalt | D4: Elegant AT | E4: GUM Бирюзовый | F4: MX1JA69V9SK527361 | G4: 1120_307761 | H4: 46123 | I4: Серік Жахан | J4: Сарсенов Есенбек Қайратұлы | K4: 981206350140 | N4: 77756246959 | O4: 6290000 | P4: 6290000 | Q4: 0 | R4: 0 | S4: 200000 | T4: 200000 | U4: Кредит | W4: Атырау | X4: 46125 | Y4: Банк ЦентрКредит | Z4: 0 | AA4: 8926109 | AC4: 0 | AD4: Стандартное кредитование | AE4: 2025
A5: 1 | B5: 935 Шымкент TOO «AUTOCENTER ONTUSTIK» Байдибек би (Chevrolet) | C5: Onix | D5: Premier 1 | E5: GBO Черный | F5: MX1CNAAA0SK002396 | G5: 935_311082 | H5: 46136 | I5: Диас Туткабай | J5: Канатова Юлдуз Илхамжановна | K5: 941020401011 | N5: 77786364629 | O5: 7540000 | P5: 7290000 | Q5: 0 | R5: 250000 | S5: 300000 | T5: 300000 | U5: Кредит | V5: Заявка с сайта Chevrolet | W5: Шымкент | X5: 46137 | Y5: Halyk Bank | Z5: 1 | AA5: 8970253 | AB5: 1085 Актау ТОО «AUTOCENTER ONTUSTIK» (Chevrolet) | AC5: 0 | AD5: Стандартное кредитование | AE5: 2025
A6: 1 | B6: 920 Уральск ТОО «AUTOCENTER ONTUSTIK» (Chevrolet) | C6: Tracker MY22 | D6: 1LT AT | E6: GAZ Бело-дымчатый | F6: MX1CJAAB0SK535802 | G6: 920_307278 | H6: 46120 | I6: Бауржан Ихсанов | J6: Искаков Раниль Максутович | K6: 761025301410 | N6: 77778612902 | O6: 10240000 | P6: 10240000 | Q6: 0 | R6: 0 | S6: 400000 | T6: 400000 | U6: Кредит | W6: Уральск | X6: 46122 | Y6: Банк ЦентрКредит | Z6: 0 | AA6: 9030971 | AC6: 0 | AD6: Стандартное кредитование | AE6: 2025
A7: 1 | B7: 119 Шымкент ТОО «AUTOCENTER ONTUSTIK» (Chevrolet) | C7: Labo | D7: LABO | E7: GAZ Бело-дымчатый | F7: MXCCLAB00SK882388 | G7: 119_307092 | H7: 46118 | I7: Инара Курбанова | J7: Ирсалиев Нурлан Абубакирович | K7: 920626050904 | N7: 77051953354 | O7: 5590000 | P7: 5590000 | Q7: 0 | R7: 0 | S7: 200000 | T7: 200000 | U7: Безналичный расчет | W7: Шымкент | X7: 46120 | Y7: Без привлечения кредита | Z7: 0 | AA7: 9065693 | AC7: 0 | AD7: Безналичный | AE7: 2025
A8: 1 | B8: 935 Шымкент TOO «AUTOCENTER ONTUSTIK» Байдибек би (Chevrolet) | C8: Onix | D8: 4LT AT (LTZ) | E8: GAZ Бело-дымчатый | F8: MX1CNAAA0SK003344 | G8: 935_308501 | H8: 46127 | I8: Диас Туткабай | J8: Салыбек Рысбек Балтабекұлы | K8: 970401300734 | N8: 77781865767 | O8: 6990000 | P8: 6990000 | Q8: 0 | R8: 0 | S8: 300000 | T8: 300000 | U8: Безналичный расчет | W8: Шымкент | X8: 46128 | Y8: Без привлечения кредита | Z8: 1 | AA8: 9223661 | AB8: 119 Шымкент ТОО «AUTOCENTER ONTUSTIK» (Chevrolet) | AC8: 0 | AD8: Безналичный | AE8: 2025
A9: 1 | B9: 119 Шымкент ТОО «AUTOCENTER ONTUSTIK» (Chevrolet) | C9: Labo | D9: LABO | E9: GAZ Бело-дымчатый | F9: MXCCLAB00SK882351 | G9: 119_312147 | H9: 46140 | I9: Айгерим Рыстыбай | J9: Мирахметов Достон Бахтиярович | K9: 971012301413 | N9: 77780060011 | O9: 5590000 | P9: 5590000 | Q9: 0 | R9: 0 | S9: 200000 | T9: 200000 | U9: Безналичный расчет | W9: Шымкент | X9: 46142 | Y9: Без привлечения кредита | Z9: 0 | AA9: 9281651 | AB9: 1267 Алматы TOO «DCG Zhetysu» (Chevrolet) | AC9: 0 | AD9: Безналичный | AE9: 2025
A10: 1 | B10: 119 Шымкент ТОО «AUTOCENTER ONTUSTIK» (Chevrolet) | C10: Labo | D10: LABO | E10: GAZ Бело-дымчатый | F10: MXCCLAB00SK882425 | G10: 119_312148 | H10: 46140 | I10: Инара Курбанова | J10: Мирахметов Достон Бахтиярович | K10: 971012301413 | N10: 77780060010 | O10: 5590000 | P10: 5590000 | Q10: 0 | R10: 0 | S10: 200000 | T10: 200000 | U10: Безналичный расчет | W10: Шымкент | X10: 46142 | Y10: Без привлечения кредита | Z10: 0 | AA10: 9281654 | AB10: 1267 Алматы TOO «DCG Zhetysu» (Chevrolet) | AC10: 0 | AD10: Безналичный | AE10: 2025
A11: 1 | B11: 858 Астана ТОО «DCG Astana» (Chevrolet) | C11: Cobalt | D11: Elegant AT | E11: GAZ Бело-дымчатый | F11: MX1JA69V9SK143469 | G11: 858_308671 | H11: 46128 | I11: Рүстем Құдайберген | J11: Танатаров Ержан Аманжолович | K11: 881111350584 | N11: 77078881399 | O11: 6540000 | P11: 6290000 | Q11: 0 | R11: 250000 | S11: 200000 | T11: 200000 | U11: Кредит | V11: Заявка с сайта Chevrolet | W11: Астана | X11: 46134 | Y11: МФО Sapa Digital Finance | Z11: 0 | AA11: 9380162 | AC11: 0 | AD11: Стандартное кредитование | AE11: 2025
A12: 1 | B12: 858 Астана ТОО «DCG Astana» (Chevrolet) | C12: Cobalt | D12: Elegant AT | E12: GAZ Бело-дымчатый | F12: MX1JA69V9SK145879 | G12: 858_307625 | H12: 46122 | I12: Рүстем Құдайберген | J12: Әбілжанов Абай Амангелдыұлы | K12: 950727350353 | N12: 77015924705 | O12: 6290000 | P12: 6290000 | Q12: 0 | R12: 0 | S12: 200000 | T12: 200000 | U12: Кредит | W12: Астана | X12: 46126 | Y12: Банк ЦентрКредит | Z12: 0 | AA12: 9380165 | AC12: 0 | AD12: Стандартное кредитование | AE12: 2025
A13: 1 | B13: 858 Астана ТОО «DCG Astana» (Chevrolet) | C13: Cobalt | D13: Elegant AT | E13: GAZ Бело-дымчатый | F13: MX1JA69V9SK145251 | G13: 858_308848 | H13: 46129 | I13: Айдина Исабаева | J13: Шеховцов Владимир Иванович | K13: 600428301467 | N13: 77014159737 | O13: 6290000 | P13: 6290000 | Q13: 0 | R13: 0 | S13: 200000 | T13: 200000 | U13: Наличный расчет | W13: Астана | X13: 46135 | Y13: Без привлечения кредита | Z13: 0 | AA13: 9380169 | AC13: 0 | AD13: Наличный расчет | AE13: 2025
A14: 1 | B14: 858 Астана ТОО «DCG Astana» (Chevrolet) | C14: Cobalt | D14: Elegant AT | E14: GAZ Бело-дымчатый | F14: MX1JA69V9SK145918 | G14: 858_308473 | H14: 46127 | I14: Рүстем Құдайберген | J14: Бөхийхан Жаркын | K14: 920820350571 | N14: 77052543007 | O14: 6290000 | P14: 6290000 | Q14: 0 | R14: 0 | S14: 200000 | T14: 200000 | U14: Кредит | V14: WhatsApp | W14: Астана | X14: 46133 | Y14: Банк ЦентрКредит | Z14: 0 | AA14: 9380171 | AC14: 0 | AD14: Стандартное кредитование | AE14: 2025
A15: 1 | B15: 872 Павлодар ТОО «DCG ERTIS» (Chevrolet) | C15: Tracker MY22 | D15: Premier AT | E15: G4V Синий | F15: MX1CJAAB0TK000998 | G15: 872_307203 | H15: 46119 | I15: Ануар Жумашев | J15: Кожегельдина Зарина Жолдасбековна | K15: 930109450742 | N15: 77028579157 | O15: 10740000 | P15: 10740000 | Q15: 0 | R15: 0 | S15: 400000 | T15: 400000 | U15: Кредит | W15: Павлодар | X15: 46125 | Y15: МФО Sapa Digital Finance | Z15: 0 | AA15: 9394199 | AC15: 0 | AD15: Стандартное кредитование | AE15: 2025
A16: 1 | B16: 1120 Атырау ТОО «AUTOCENTER ONTUSTIK» (Chevrolet) | C16: Cobalt | D16: Elegant AT | E16: GAN Серебристый | F16: MX1JA69V9SK165151 | G16: 1120_306825 | H16: 46115 | I16: Галимжан Жулкашов | L16: АО КИК | M16: 130440006762 | N16: 77017055015 | O16: 6440000 | P16: 6490000 | Q16: 50000 | R16: 0 | S16: 300000 | T16: 250000 | U16: Безналичный расчет | W16: Атырау | X16: 46115 | Y16: Без привлечения кредита | Z16: 0 | AA16: 9443690 | AC16: 0 | AD16: Безналичный | AE16: 2025
A17: 1 | B17: 1120 Атырау ТОО «AUTOCENTER ONTUSTIK» (Chevrolet) | C17: Cobalt | D17: Elegant AT | E17: GK2 Серо-зеленый | F17: MX1JA69V9SK166530 | G17: 1120_308518 | H17: 46127 | I17: Нурдаулет Утепкалиев | J17: Дженгиз Седат Ибрахимович | K17: 990910300031 | N17: 77755970304 | O17: 6290000 | P17: 6290000 | Q17: 0 | R17: 0 | S17: 200000 | T17: 200000 | U17: Кредит | W17: Атырау | X17: 46128 | Y17: Halyk Bank | Z17: 0 | AA17: 9443696 | AC17: 0 | AD17: Стандартное кредитование | AE17: 2025
A18: 1 | B18: 1085 Актау ТОО «AUTOCENTER ONTUSTIK» (Chevrolet) | C18: Cobalt | D18: Elegant AT | E18: GAN Серебристый | F18: MX1JA69V9SK165164 | G18: 1085_307339 | H18: 46121 | I18: Алтынбек Абилов | J18: Кушумкулов Убайдылла Базаргельдыевич | K18: 620801302793 | N18: 77007770862 | O18: 6490000 | P18: 6490000 | Q18: 0 | R18: 0 | S18: 300000 | T18: 300000 | U18: Наличный расчет | W18: Актау | X18: 46122 | Y18: Без привлечения кредита | Z18: 0 | AA18: 9482460 | AC18: 0 | AD18: Наличный расчет | AE18: 2025
A19: 1 | B19: 1085 Актау ТОО «AUTOCENTER ONTUSTIK» (Chevrolet) | C19: Cobalt | D19: Elegant AT | E19: GAN Серебристый | F19: MX1JA69V9SK168108 | G19: 1085_307384 | H19: 46121 | I19: Алтынбек Абилов | J19: Беисов Махамбет Елемесович | K19: 720717302817 | N19: 77025811177 | O19: 6740000 | P19: 6290000 | Q19: 0 | R19: 450000 | S19: 200000 | T19: 200000 | U19: Кредит | W19: Актау | X19: 46125 | Y19: Halyk Bank | Z19: 1 | AA19: 9482462 | AC19: 0 | AD19: Стандартное кредитование | AE19: 2025
A20: 1 | B20: 922 Кызылорда ТОО «AUTOCENTER ONTUSTIK» (Chevrolet) | C20: Onix | D20: 4LT AT (LTZ) | E20: GAZ Бело-дымчатый | F20: MX1CNAAA0SK003199 | G20: 922_307065 | H20: 46118 | I20: Жасулан Шакетов | J20: Өтегенова Ләззат Жаңабайқызы | K20: 830310400946 | N20: 77011120031 | O20: 6990000 | P20: 6990000 | Q20: 0 | R20: 0 | S20: 300000 | T20: 300000 | U20: Наличный расчет | W20: Кызылорда | X20: 46119 | Y20: Без привлечения кредита | Z20: 0 | AA20: 9530913 | AC20: 0 | AD20: Наличный расчет | AE20: 2025
A21: 1 | B21: 935 Шымкент TOO «AUTOCENTER ONTUSTIK» Байдибек би (Chevrolet) | C21: Onix | D21: 4LT AT (LTZ) | E21: GAZ Бело-дымчатый | F21: MX1CNAAA0SK003548 | G21: 935_306840 | H21: 46115 | I21: Диас Туткабай | J21: Улықбек Ақтай Қайратұлы | K21: 20225500307 | N21: 77078040469 | O21: 6990000 | P21: 6990000 | Q21: 0 | R21: 0 | S21: 300000 | T21: 300000 | U21: Безналичный расчет | W21: Шымкент | X21: 46115 | Y21: Без привлечения кредита | Z21: 0 | AA21: 9535169 | AB21: 119 Шымкент ТОО «AUTOCENTER ONTUSTIK» (Chevrolet) | AC21: 0 | AD21: Безналичный | AE21: 2025
A22: 1 | B22: 922 Кызылорда ТОО «AUTOCENTER ONTUSTIK» (Chevrolet) | C22: Cobalt | D22: Elegant AT | E22: GAZ Бело-дымчатый | F22: MX1JA69V9SK155396 | G22: 922_306792 | H22: 46114 | I22: Саламат Әмірбек | J22: Утебаев Берик Калдыбаевич | K22: 900317301614 | N22: 77029730808 | O22: 6490000 | P22: 6490000 | Q22: 0 | R22: 0 | S22: 300000 | T22: 300000 | U22: Наличный расчет | W22: Кызылорда | X22: 46115 | Y22: Без привлечения кредита | Z22: 0 | AA22: 9543818 | AB22: 872 Павлодар ТОО «DCG ERTIS» (Chevrolet) | AC22: 0 | AD22: Наличный расчет | AE22: 2025
A23: 1 | B23: 872 Павлодар ТОО «DCG ERTIS» (Chevrolet) | C23: Onix | D23: 4LT AT (LTZ) | E23: GAZ Бело-дымчатый | F23: MX1CNAAA0SK005230 | G23: 872_311611 | H23: 46139 | I23: Азамат Манабаев | J23: Золотухин Андрей Александрович | K23: 780714301417 | N23: 77474067452 | O23: 6990000 | P23: 6990000 | Q23: 0 | R23: 0 | S23: 300000 | T23: 300000 | U23: Кредит | W23: Павлодар | X23: 46140 | Y23: Банк ЦентрКредит | Z23: 0 | AA23: 9543948 | AC23: 0 | AD23: Стандартное кредитование | AE23: 2025
A24: 1 | B24: 1085 Актау ТОО «AUTOCENTER ONTUSTIK» (Chevrolet) | C24: Cobalt | D24: Elegant AT | E24: GAN Серебристый | F24: MX1JA69V9TK172965 | G24: 1085_307327 | H24: 46121 | I24: Алтынбек Абилов | J24: Жолдасова Алия Бакбергеновна | K24: 910403401015 | N24: 77760234614 | O24: 6490000 | P24: 6490000 | Q24: 0 | R24: 0 | S24: 300000 | T24: 300000 | U24: Кредит | W24: Актау | X24: 46122 | Y24: Береке Банк | Z24: 0 | AA24: 9569312 | AC24: 0 | AD24: Стандартное кредитование | AE24: 2025
A25: 1 | B25: 1120 Атырау ТОО «AUTOCENTER ONTUSTIK» (Chevrolet) | C25: Cobalt | D25: Elegant AT | E25: GAN Серебристый | F25: MX1JA69V9TK172421 | G25: 1120_306825 | H25: 46115 | I25: Галимжан Жулкашов | L25: АО КИК | M25: 130440006762 | N25: 77017055015 | O25: 6440000 | P25: 6490000 | Q25: 50000 | R25: 0 | S25: 300000 | T25: 250000 | U25: Безналичный расчет | W25: Атырау | X25: 46115 | Y25: Без привлечения кредита | Z25: 0 | AA25: 9606703 | AC25: 0 | AD25: Безналичный | AE25: 2025
A26: 1 | B26: 935 Шымкент TOO «AUTOCENTER ONTUSTIK» Байдибек би (Chevrolet) | C26: Cobalt | D26: Elegant AT | E26: GAZ Бело-дымчатый | F26: MX1JA69V9TK048613 | G26: 935_307271 | H26: 46120 | I26: Ербол Рашид | J26: Қиябек Мереке Батырханқызы | K26: 960511401130 | N26: 77055511306 | O26: 6490000 | P26: 6490000 | Q26: 0 | R26: 0 | S26: 300000 | T26: 300000 | U26: Безналичный расчет | V26: Социальные сети | W26: Шымкент | X26: 46120 | Y26: Без привлечения кредита | Z26: 0 | AA26: 9642549 | AC26: 0 | AD26: Безналичный | AE26: 2025
A27: 1 | B27: 1120 Атырау ТОО «AUTOCENTER ONTUSTIK» (Chevrolet) | C27: Cobalt | D27: Elegant AT | E27: GAN Серебристый | F27: MX1JA69V9TK032531 | G27: 1120_306825 | H27: 46115 | I27: Галимжан Жулкашов | L27: АО КИК | M27: 130440006762 | N27: 77017055015 | O27: 6440000 | P27: 6490000 | Q27: 50000 | R27: 0 | S27: 300000 | T27: 250000 | U27: Безналичный расчет | W27: Атырау | X27: 46115 | Y27: Без привлечения кредита | Z27: 0 | AA27: 9644758 | AC27: 0 | AD27: Безналичный | AE27: 2025
A28: 1 | B28: 1120 Атырау ТОО «AUTOCENTER ONTUSTIK» (Chevrolet) | C28: Cobalt | D28: Elegant AT | E28: GK2 Серо-зеленый | F28: MX1JA69V9TK036456 | G28: 1120_308741 | H28: 46128 | I28: Нурдаулет Утепкалиев | J28: Маженов Асыланбек Алдонгарович | K28: 880721302810 | N28: 77782967888 | O28: 6290000 | P28: 6290000 | Q28: 0 | R28: 0 | S28: 200000 | T28: 200000 | U28: Кредит | W28: Атырау | X28: 46129 | Y28: Банк ЦентрКредит | Z28: 0 | AA28: 9644763 | AC28: 0 | AD28: Стандартное кредитование | AE28: 2025
A29: 1 | B29: 1085 Актау ТОО «AUTOCENTER ONTUSTIK» (Chevrolet) | C29: Cobalt | D29: Elegant AT | E29: GAZ Бело-дымчатый | F29: MX1JA69V9TK023498 | G29: 1085_307513 | H29: 46122 | I29: Алтынбек Абилов | J29: Бисенбайұлы Әділ | K29: 50926551635 | N29: 77076081340 | O29: 6290000 | P29: 6290000 | Q29: 0 | R29: 0 | S29: 200000 | T29: 200000 | U29: Наличный расчет | V29: Заявка с сайта Chevrolet | W29: Актау | X29: 46125 | Y29: Без привлечения кредита | Z29: 0 | AA29: 9645268 | AC29: 0 | AD29: Наличный расчет | AE29: 2025
A30: 1 | B30: 1085 Актау ТОО «AUTOCENTER ONTUSTIK» (Chevrolet) | C30: Cobalt | D30: Elegant AT | E30: GAN Серебристый | F30: MX1JA69V9TK073290 | G30: 1085_307392 | H30: 46121 | I30: Алтынбек Абилов | J30: Абиев Нуржигит Ибраимович | K30: 960116300991 | N30: 77027869613 | O30: 6440000 | P30: 6290000 | Q30: 0 | R30: 150000 | S30: 200000 | T30: 200000 | U30: Кредит | W30: Актау | X30: 46125 | Y30: Береке Банк | Z30: 0 | AA30: 9645273 | AC30: 0 | AD30: Стандартное кредитование | AE30: 2025
A31: 1 | B31: 1085 Актау ТОО «AUTOCENTER ONTUSTIK» (Chevrolet) | C31: Cobalt | D31: Elegant AT | E31: GAZ Бело-дымчатый | F31: MX1JA69V9TK073314 | G31: 1085_307190 | H31: 46119 | I31: Алтынбек Абилов | J31: Сарсенов Марат Койшиевич | K31: 700905302141 | N31: 77787411970 | O31: 6490000 | P31: 6490000 | Q31: 0 | R31: 0 | S31: 300000 | T31: 300000 | U31: Наличный расчет | V31: Заявка с сайта Chevrolet | W31: Актау | X31: 46120 | Y31: Без привлечения кредита | Z31: 0 | AA31: 9645275 | AC31: 0 | AD31: Наличный расчет | AE31: 2025
A32: 1 | B32: 1085 Актау ТОО «AUTOCENTER ONTUSTIK» (Chevrolet) | C32: Cobalt | D32: Elegant AT | E32: GAZ Бело-дымчатый | F32: MX1JA69V9TK179013 | G32: 1085_307194 | H32: 46119 | I32: Алтынбек Абилов | J32: Темірбеков Мырзабек Темірбекұлы | K32: 931213351584 | N32: 77011741611 | O32: 6490000 | P32: 6490000 | Q32: 0 | R32: 0 | S32: 300000 | T32: 300000 | U32: Кредит | V32: Заявка с сайта Chevrolet | W32: Актау | X32: 46120 | Y32: Без привлечения кредита | Z32: 0 | AA32: 9645490 | AC32: 0 | AD32: Наличный расчет | AE32: 2025
A33: 1 | B33: 1085 Актау ТОО «AUTOCENTER ONTUSTIK» (Chevrolet) | C33: Cobalt | D33: Elegant AT | E33: GAZ Бело-дымчатый | F33: MX1JA69V9TK176026 | G33: 1085_306837 | H33: 46115 | I33: Алтынбек Абилов | J33: Джанетов Нурахмет | K33: 650502302743 | N33: 77082182207 | O33: 6490000 | P33: 6490000 | Q33: 0 | R33: 0 | S33: 300000 | T33: 300000 | U33: Кредит | W33: Актау | X33: 46119 | Y33: Halyk Bank | Z33: 0 | AA33: 9645494 | AC33: 0 | AD33: Стандартное кредитование | AE33: 2025
A34: 1 | B34: 1085 Актау ТОО «AUTOCENTER ONTUSTIK» (Chevrolet) | C34: Cobalt | D34: Elegant AT | E34: GAZ Бело-дымчатый | F34: MX1JA69V9TK178066 | G34: 1085_308516 | H34: 46127 | I34: Алтынбек Абилов | J34: Молакбаев Ондас Айдарбаевич | K34: 840713399060 | N34: 77787785117 | O34: 6290000 | P34: 6290000 | Q34: 0 | R34: 0 | S34: 200000 | T34: 200000 | U34: Наличный расчет | W34: Актау | X34: 46135 | Y34: Без привлечения кредита | Z34: 0 | AA34: 9645498 | AC34: 0 | AD34: Наличный расчет | AE34: 2025
A35: 1 | B35: 1085 Актау ТОО «AUTOCENTER ONTUSTIK» (Chevrolet) | C35: Cobalt | D35: Elegant AT | E35: GK2 Серо-зеленый | F35: MX1JA69V9TK036539 | G35: 1085_307607 | H35: 46122 | I35: Алтынбек Абилов | J35: Жанабергенов Еркебулан Сексенбайулы | K35: 980109350359 | N35: 77058820745 | O35: 6540000 | P35: 6290000 | Q35: 0 | R35: 250000 | S35: 200000 | T35: 200000 | U35: Кредит | W35: Актау | X35: 46127 | Y35: Halyk Bank | Z35: 0 | AA35: 9645501 | AC35: 0 | AD35: Стандартное кредитование | AE35: 2025
A36: 1 | B36: 872 Павлодар ТОО «DCG ERTIS» (Chevrolet) | C36: Onix | D36: Premier 1 | E36: GAZ Бело-дымчатый | F36: MX1CNAAA0TK006068 | G36: 872_307021 | H36: 46118 | I36: Мерхат Муканов | J36: Авидилхан Даянгул | K36: 810827450996 | N36: 77079751301 | O36: 7540000 | P36: 7290000 | Q36: 0 | R36: 250000 | S36: 300000 | T36: 300000 | U36: Кредит | W36: Павлодар | X36: 46125 | Y36: Береке Банк | Z36: 0 | AA36: 9650928 | AC36: 0 | AD36: Стандартное кредитование | AE36: 2025
A37: 1 | B37: 872 Павлодар ТОО «DCG ERTIS» (Chevrolet) | C37: Onix | D37: Premier 1 | E37: GAN Серебристый | F37: MX1CNAAA0TK006495 | G37: 872_306921 | H37: 46116 | I37: Алишер Сиюнич | J37: Кожагельдинов Роман Токтарович | K37: 910219350077 | N37: 77051038383 | O37: 7290000 | P37: 7290000 | Q37: 0 | R37: 0 | S37: 300000 | T37: 300000 | U37: Кредит | W37: Павлодар | X37: 46121 | Y37: Halyk Bank | Z37: 0 | AA37: 9650930 | AC37: 0 | AD37: Стандартное кредитование | AE37: 2025
A38: 1 | B38: 872 Павлодар ТОО «DCG ERTIS» (Chevrolet) | C38: Onix | D38: Premier 1 | E38: GAN Серебристый | F38: MX1CNAAA0TK006486 | G38: 872_308296 | H38: 46126 | I38: Ануар Жумашев | J38: Сулейменова Сабина Тлектесовна | K38: 51225650457 | N38: 77761484998 | O38: 7290000 | P38: 7290000 | Q38: 0 | R38: 0 | S38: 300000 | T38: 300000 | U38: Наличный расчет | W38: Павлодар | X38: 46126 | Y38: Без привлечения кредита | Z38: 0 | AA38: 9650931 | AC38: 0 | AD38: Наличный расчет | AE38: 2025
A39: 1 | B39: 1120 Атырау ТОО «AUTOCENTER ONTUSTIK» (Chevrolet) | C39: Cobalt | D39: Elegant AT | E39: GYM Пепельно-серый | F39: MX1JA69V9TK036071 | G39: 1120_306825 | H39: 46115 | I39: Галимжан Жулкашов | L39: АО КИК | M39: 130440006762 | N39: 77017055015 | O39: 6440000 | P39: 6490000 | Q39: 50000 | R39: 0 | S39: 300000 | T39: 250000 | U39: Безналичный расчет | W39: Атырау | X39: 46115 | Y39: Без привлечения кредита | Z39: 0 | AA39: 9652698 | AC39: 0 | AD39: Безналичный | AE39: 2025
A40: 1 | B40: 1120 Атырау ТОО «AUTOCENTER ONTUSTIK» (Chevrolet) | C40: Cobalt | D40: Elegant AT | E40: GAN Серебристый | F40: MX1JA69V9TK028447 | G40: 1120_306825 | H40: 46115 | I40: Галимжан Жулкашов | L40: АО КИК | M40: 130440006762 | N40: 77017055015 | O40: 6440000 | P40: 6490000 | Q40: 50000 | R40: 0 | S40: 300000 | T40: 250000 | U40: Безналичный расчет | W40: Атырау | X40: 46115 | Y40: Без привлечения кредита | Z40: 0 | AA40: 9652708 | AC40: 0 | AD40: Безналичный | AE40: 2025
A41: 1 | B41: 1120 Атырау ТОО «AUTOCENTER ONTUSTIK» (Chevrolet) | C41: Cobalt | D41: Elegant AT | E41: GAZ Бело-дымчатый | F41: MX1JA69V9TK046890 | G41: 1120_306825 | H41: 46115 | I41: Нурдаулет Утепкалиев | L41: АО КИК | M41: 130440006762 | N41: 77017055015 | O41: 6440000 | P41: 6490000 | Q41: 50000 | R41: 0 | S41: 300000 | T41: 250000 | U41: Безналичный расчет | W41: Атырау | X41: 46115 | Y41: Без привлечения кредита | Z41: 0 | AA41: 9652711 | AC41: 0 | AD41: Безналичный | AE41: 2025
A42: 1 | B42: 866 Усть-Каменогорск ТОО «DCG VOSTOK» (Chevrolet) | C42: Cobalt | D42: Elegant AT | E42: GAZ Бело-дымчатый | F42: MX1JA69V9TK076142 | G42: 866_307024 | H42: 46118 | I42: Асқар Бахытжан | J42: Калиев Бауыржан Ментайевич | K42: 850611300984 | N42: 77766656553 | O42: 6490000 | P42: 6490000 | Q42: 0 | R42: 0 | S42: 300000 | T42: 300000 | U42: Кредит | V42: 2 GIS/Яндекс | W42: Усть-Каменогорск | X42: 46120 | Y42: Береке Банк | Z42: 0 | AA42: 9653603 | AC42: 0 | AD42: Стандартное кредитование | AE42: 2025
A43: 1 | B43: 866 Усть-Каменогорск ТОО «DCG VOSTOK» (Chevrolet) | C43: Cobalt | D43: Elegant AT | E43: GAZ Бело-дымчатый | F43: MX1JA69V9TK076270 | G43: 866_306948 | H43: 46117 | I43: Жандос Тоқтасынов | J43: Бодиев Ерсұлтан Бағадатұлы | K43: 940207350334 | N43: 77751310035 | O43: 6740000 | P43: 6490000 | Q43: 0 | R43: 250000 | S43: 300000 | T43: 300000 | U43: Кредит | V43: WhatsApp | W43: Усть-Каменогорск | X43: 46119 | Y43: Банк ЦентрКредит | Z43: 0 | AA43: 9653607 | AC43: 0 | AD43: Стандартное кредитование | AE43: 2025
A44: 1 | B44: 866 Усть-Каменогорск ТОО «DCG VOSTOK» (Chevrolet) | C44: Cobalt | D44: Elegant AT | E44: GAZ Бело-дымчатый | F44: MX1JA69V9TK073253 | G44: 866_306821 | H44: 46115 | I44: Жандос Тоқтасынов | J44: Кисамгалиев Ержан Каримович | K44: 640702300267 | N44: 77055075613 | O44: 6490000 | P44: 6490000 | Q44: 0 | R44: 0 | S44: 300000 | T44: 300000 | U44: Безналичный расчет | V44: Постоянный клиент/уже приходил | W44: Усть-Каменогорск | X44: 46115 | Y44: Без привлечения кредита | Z44: 0 | AA44: 9658643 | AC44: 0 | AD44: Безналичный | AE44: 2025
A45: 1 | B45: 1120 Атырау ТОО «AUTOCENTER ONTUSTIK» (Chevrolet) | C45: Cobalt | D45: Elegant AT | E45: GAN Серебристый | F45: MX1JA69V9TK072269 | G45: 1120_307515 | H45: 46122 | I45: Нурдаулет Утепкалиев | J45: Джумагалиев Сембай | K45: 641009300887 | N45: 77026208764 | O45: 6740000 | P45: 6290000 | Q45: 0 | R45: 450000 | S45: 200000 | T45: 200000 | U45: Кредит | W45: Атырау | X45: 46125 | Y45: Банк ЦентрКредит | Z45: 2 | AA45: 9658661 | AC45: 0 | AD45: Стандартное кредитование | AE45: 2025
A46: 1 | B46: 1120 Атырау ТОО «AUTOCENTER ONTUSTIK» (Chevrolet) | C46: Cobalt | D46: Elegant AT | E46: GAN Серебристый | F46: MX1JA69V9TK072272 | G46: 1120_306942 | H46: 46117 | I46: Нурдаулет Утепкалиев | J46: Кенжегалиев Сарсенбай Отарович | K46: 690522302432 | N46: 77757119169 | O46: 6740000 | P46: 6490000 | Q46: 0 | R46: 250000 | S46: 300000 | T46: 300000 | U46: Кредит | W46: Атырау | X46: 46121 | Y46: Береке Банк | Z46: 0 | AA46: 9658662 | AC46: 0 | AD46: Стандартное кредитование | AE46: 2025
A47: 1 | B47: 1120 Атырау ТОО «AUTOCENTER ONTUSTIK» (Chevrolet) | C47: Cobalt | D47: Elegant AT | E47: GAZ Бело-дымчатый | F47: MX1JA69V9TK072326 | G47: 1120_306825 | H47: 46115 | I47: Нурдаулет Утепкалиев | L47: АО КИК | M47: 130440006762 | N47: 77017055015 | O47: 6440000 | P47: 6490000 | Q47: 50000 | R47: 0 | S47: 300000 | T47: 250000 | U47: Безналичный расчет | W47: Атырау | X47: 46115 | Y47: Без привлечения кредита | Z47: 0 | AA47: 9658665 | AC47: 0 | AD47: Безналичный | AE47: 2025
A48: 1 | B48: 1120 Атырау ТОО «AUTOCENTER ONTUSTIK» (Chevrolet) | C48: Cobalt | D48: Elegant AT | E48: GAZ Бело-дымчатый | F48: MX1JA69V9TK072389 | G48: 1120_306825 | H48: 46115 | I48: Нурдаулет Утепкалиев | L48: АО КИК | M48: 130440006762 | N48: 77017055015 | O48: 6440000 | P48: 6490000 | Q48: 50000 | R48: 0 | S48: 300000 | T48: 250000 | U48: Безналичный расчет | W48: Атырау | X48: 46115 | Y48: Без привлечения кредита | Z48: 0 | AA48: 9658667 | AC48: 0 | AD48: Безналичный | AE48: 2025
A49: 1 | B49: 1120 Атырау ТОО «AUTOCENTER ONTUSTIK» (Chevrolet) | C49: Cobalt | D49: Elegant AT | E49: GAZ Бело-дымчатый | F49: MX1JA69V9TK073315 | G49: 1120_307432 | H49: 46122 | I49: Нурдаулет Утепкалиев | J49: Сапаров Алим Тулепович | K49: 780207303010 | N49: 77712600008 | O49: 6190000 | P49: 6290000 | Q49: 100000 | R49: 0 | S49: 200000 | T49: 100000 | U49: Безналичный расчет | W49: Атырау | X49: 46125 | Y49: Без привлечения кредита | Z49: 1 | AA49: 9658675 | AC49: 0 | AD49: Безналичный | AE49: 2025
A50: 1 | B50: 866 Усть-Каменогорск ТОО «DCG VOSTOK» (Chevrolet) | C50: Onix | D50: 4LT AT (LTZ) | E50: GAZ Бело-дымчатый | F50: MX1CNAAA0TK006555 | G50: 866_308396 | H50: 46127 | I50: Асқар Бахытжан | J50: Елеубекова Назгуль Емелбековна | K50: 870625401409 | N50: 77086146425 | O50: 6990000 | P50: 6990000 | Q50: 0 | R50: 0 | S50: 300000 | T50: 300000 | U50: Кредит | V50: Instagram | W50: Усть-Каменогорск | X50: 46132 | Y50: Береке Банк | Z50: 0 | AA50: 9658875 | AC50: 0 | AD50: Стандартное кредитование | AE50: 2025
A51: 1 | B51: 1085 Актау ТОО «AUTOCENTER ONTUSTIK» (Chevrolet) | C51: Cobalt | D51: Elegant AT | E51: GAN Серебристый | F51: MX1JA69V9TK026330 | G51: 1085_306699 | H51: 46113 | I51: Алтынбек Абилов | J51: Мадинов Ербол Сарсенгазыевич | K51: 890518301642 | N51: 77751131111 | O51: 6490000 | P51: 6490000 | Q51: 0 | R51: 0 | S51: 300000 | T51: 300000 | U51: Кредит | W51: Актау | X51: 46115 | Y51: Шинхань Банк | Z51: 0 | AA51: 9658957 | AC51: 0 | AD51: Стандартное кредитование | AE51: 2025
A52: 1 | B52: 1085 Актау ТОО «AUTOCENTER ONTUSTIK» (Chevrolet) | C52: Cobalt | D52: Elegant AT | E52: GAN Серебристый | F52: MX1JA69V9TK033520 | G52: 1085_306694 | H52: 46113 | I52: Алтынбек Абилов | J52: Алихаджиева Нина Васильевна | K52: 581021401843 | N52: 77017455214 | O52: 6490000 | P52: 6490000 | Q52: 0 | R52: 0 | S52: 300000 | T52: 300000 | U52: Наличный расчет | V52: Заявка с сайта Chevrolet | W52: Актау | X52: 46115 | Y52: Без привлечения кредита | Z52: 0 | AA52: 9658964 | AC52: 0 | AD52: Наличный расчет | AE52: 2025
A53: 1 | B53: 1120 Атырау ТОО «AUTOCENTER ONTUSTIK» (Chevrolet) | C53: Cobalt | D53: Elegant AT | E53: GAZ Бело-дымчатый | F53: MX1JA69V9TK049160 | G53: 1120_306825 | H53: 46115 | I53: Нурдаулет Утепкалиев | L53: АО КИК | M53: 130440006762 | N53: 77017055015 | O53: 6440000 | P53: 6490000 | Q53: 50000 | R53: 0 | S53: 300000 | T53: 250000 | U53: Безналичный расчет | W53: Атырау | X53: 46115 | Y53: Без привлечения кредита | Z53: 0 | AA53: 9662551 | AC53: 0 | AD53: Безналичный | AE53: 2025
